Workbook

Sheet YIELD_CALCULATOR
B2: Bitcoin Lightning Credit Derivatives A permissionless, decentralized and distributed strategy for ultra-high yields using leveraged bitcoin growth and lightning transaction fee exposure | D2: Bitcoin Yield Estimate Variables BiGY = Bitcoin Growth Yield (CAGR) BiLY = Bitcoin Liquidity Yield BiTY = Bitcoin Transaction Yield | G2: Bitcoin Yield Estimate 5 Year Summary SR = Stable Receiver SB = Stable Balancer SP = Stable Provider | K2: Lightning Bank 5 Year Revenue Summary TVL = Total Value Locked
K3: Bitcoin TVL | L3: Measure | M3: BTC | N3: USD
D4: Bitcoin USD Price Start | E4: 100000 | G4: SR USD Comp. | H4: Annual Avg. % | I4: =I43 -> 0.271293 | K4: =C127 -> 20000 | L4: Annual Avg. | M4: =I128 -> 243.55698 | N4: =M4*$I$15 -> 90431000
D5: Annual Bitcoin Growth Yield % | E5: 0.3 | G5: SP BiGY BTC | H5: Annual Avg. % | I5: =I67 -> 0.14613419 | K5: =C127 -> 20000 | L5: Cumulative | M5: =I129 -> 1217.7849 | N5: =M5*$I$15 -> 4.52155e+08
D6: Annual Bitcoin Liquidity Yield % | E6: 0.02 | G6: SP BiLY BTC | H6: Annual Avg. % | I6: =I80 -> 0.029742279 | K6: =C130 -> 400000 | L6: Annual Avg. | M6: =I131 -> 4871.1395 | N6: =M6*$I$15 -> 1.80862e+09
D7: Annual Bitcoin Transaction Yield % | E7: 0.01 | G7: SP BiTY BTC | H7: Annual Avg. % | I7: =I95 -> 0.01487114 | K7: =C130 -> 400000 | L7: Cumulative | M7: =I132 -> 24355.698 | N7: =M7*$I$15 -> 9043100000
D8: Stable Receiver Security Annual USD % | E8: 0.15 | G8: SP BiLY SR BTC | H8: Annual Avg. % | I8: =-I35 -> -0.073067093 | K8: =C133 -> 1000000 | L8: Annual Avg. | M8: =I134 -> 12177.849 | N8: =M8*$I$15 -> 4521550000
D9: Stable Balancer Security Annual USD % | E9: 0.05 | G9: SP BiLY SB BTC | H9: Annual Avg. % | I9: =-I51 -> -0.024355698 | K9: =C133 -> 1000000 | L9: Cumulative | M9: =I135 -> 60889.244 | N9: =M9*$I$15 -> 22607750000
D10: Stable Balancer Debt Annual USD % | E10: 0.075 | G10: SP Total BTC | H10: Annual Avg. % | I10: =I110 -> 0.093324814
D11: Stable Provider Debt-to-Value % | E11: 0
B13: Yield Estimate Calculator | C13: Unit of Account | D13: Measure | E13: Year 1 | F13: Year 2 | G13: Year 3 | H13: Year 4 | I13: Year 5 | J13: Year 6 | K13: Year 7 | L13: Year 8 | M13: Year 9 | N13: Year 10
B15: Bitcoin | C15: USD | D15: Price | E15: =($E$4 * $E$5) + $E$4 -> 130000 | F15: =(E15 * $E$5) + E15 -> 169000 | G15: =(F15 * $E$5) + F15 -> 219700 | H15: =(G15 * $E$5) + G15 -> 285610 | I15: =(H15 * $E$5) + H15 -> 371293 | J15: =(I15 * $E$5) + I15 -> 482680.9 | K15: =(J15 * $E$5) + J15 -> 627485.17 | L15: =(K15 * $E$5) + K15 -> 815730.72 | M15: =(L15 * $E$5) + L15 -> 1060449.9 | N15: =(M15 * $E$5) + M15 -> 1378584.9
D16: Marketcap | E16: =E15*21000000 -> 2730000000000 | F16: =F15*21000000 -> 3549000000000 | G16: =G15*21000000 -> 4613700000000 | H16: =H15*21000000 -> 5997810000000 | I16: =I15*21000000 -> 7797153000000 | J16: =J15*21000000 -> 10136298900000 | K16: =K15*21000000 -> 13177188570000 | L16: =L15*21000000 -> 17130345141000 | ... N16: =N15*21000000 -> 28950283288290
B17: Bitcoin Growth Yield (BiGY) | C17: BTC | D17: Stable Security Cumulative % | E17: =(E15-$E4)/E15 -> 0.23076923 | F17: =(F15-$E4)/F15 -> 0.40828402 | G17: =(G15-$E4)/G15 -> 0.54483386 | H17: =(H15-$E4)/H15 -> 0.6498722 | I17: =(I15-$E4)/I15 -> 0.73067093 | J17: =(J15-$E4)/J15 -> 0.79282379 | K17: =(K15-$E4)/K15 -> 0.84063368 | L17: =(L15-$E4)/L15 -> 0.87741053 | ... N17: =(N15-$E4)/N15 -> 0.92746185
D18: Stable Security Remaining % | E18: =1-E17 -> 0.76923077 | F18: =1-F17 -> 0.59171598 | G18: =1-G17 -> 0.45516614 | H18: =1-H17 -> 0.3501278 | I18: =1-I17 -> 0.26932907 | J18: =1-J17 -> 0.20717621 | K18: =1-K17 -> 0.15936632 | L18: =1-L17 -> 0.12258947 | ... N18: =1-N17 -> 0.07253815
D19: Stable Security Annual % | E19: =E17 -> 0.23076923 | F19: =F17-E17 -> 0.17751479 | G19: =G17-F17 -> 0.13654984 | H19: =H17-G17 -> 0.10503834 | I19: =I17-H17 -> 0.080798722 | J19: =J17-I17 -> 0.062152863 | K19: =K17-J17 -> 0.047809895 | L19: =L17-K17 -> 0.036776842 | M19: =M17-L17 -> 0.028289879 | N19: =N17-M17 -> 0.021761445
D20: Stable Security Annual Average % | I20: =AVERAGE(E19:I19) -> 0.14613419 | N20: =AVERAGE(E19:N19) -> 0.092746185
D21: Stable Debt Annual % | E21: =$E$11*E19 -> 0 | F21: =$E$11*F19 -> 0 | G21: =$E$11*G19 -> 0 | H21: =$E$11*H19 -> 0 | I21: =$E$11*I19 -> 0 | J21: =$E$11*J19 -> 0 | K21: =$E$11*K19 -> 0 | L21: =$E$11*L19 -> 0 | ... N21: =$E$11*N19 -> 0
D22: Stable Debt Annual Avg. % | I22: =AVERAGE(E21:I21) -> 0 | N22: =AVERAGE(E21:N21) -> 0
D23: Total Annual % | E23: =E19+E21 -> 0.23076923 | F23: =F19+F21 -> 0.17751479 | G23: =G19+G21 -> 0.13654984 | H23: =H19+H21 -> 0.10503834 | I23: =I19+I21 -> 0.080798722 | J23: =J19+J21 -> 0.062152863 | K23: =K19+K21 -> 0.047809895 | L23: =L19+L21 -> 0.036776842 | ... N23: =N19+N21 -> 0.021761445
D24: Total Annual Average % | I24: =AVERAGE(E23:I23) -> 0.14613419 | N24: =AVERAGE(E23:N23) -> 0.092746185
B25: Bitcoin Liquidity Yield (BiLY) | C25: BTC | D25: Annual % | E25: =((1+$E$11)*$E$6)+($E$6*E18) -> 0.035384615 | F25: =((1+$E$11)*$E$6)+($E$6*F18) -> 0.03183432 | G25: =((1+$E$11)*$E$6)+($E$6*G18) -> 0.029103323 | H25: =((1+$E$11)*$E$6)+($E$6*H18) -> 0.027002556 | I25: =((1+$E$11)*$E$6)+($E$6*I18) -> 0.025386581 | J25: =((1+$E$11)*$E$6)+($E$6*J18) -> 0.024143524 | K25: =((1+$E$11)*$E$6)+($E$6*K18) -> 0.023187326 | L25: =((1+$E$11)*$E$6)+($E$6*L18) -> 0.022451789 | ... N25: =((1+$E$11)*$E$6)+($E$6*N18) -> 0.021450763
D26: Annual Average % | I26: =AVERAGE(E25:I25) -> 0.029742279 | N26: =AVERAGE(E25:N25) -> 0.026183079
D27: Cumulative % | E27: =E25 -> 0.035384615 | F27: =E27+F25 -> 0.067218935 | G27: =F27+G25 -> 0.096322258 | H27: =G27+H25 -> 0.12332481 | I27: =H27+I25 -> 0.1487114 | J27: =I27+J25 -> 0.17285492 | K27: =J27+K25 -> 0.19604225 | L27: =K27+L25 -> 0.21849404 | M27: =L27+M25 -> 0.24038003 | N27: =M27+N25 -> 0.26183079
B28: Bitcoin Transaction Yield (BiTY) | C28: BTC | D28: Annual % | E28: =((1+$E$11)*$E$7)+($E$7*E18) -> 0.017692308 | F28: =((1+$E$11)*$E$7)+($E$7*F18) -> 0.01591716 | G28: =((1+$E$11)*$E$7)+($E$7*G18) -> 0.014551661 | H28: =((1+$E$11)*$E$7)+($E$7*H18) -> 0.013501278 | I28: =((1+$E$11)*$E$7)+($E$7*I18) -> 0.012693291 | J28: =((1+$E$11)*$E$7)+($E$7*J18) -> 0.012071762 | K28: =((1+$E$11)*$E$7)+($E$7*K18) -> 0.011593663 | L28: =((1+$E$11)*$E$7)+($E$7*L18) -> 0.011225895 | ... N28: =((1+$E$11)*$E$7)+($E$7*N18) -> 0.010725382
D29: Annual Average % | I29: =AVERAGE(E28:I28) -> 0.01487114 | N29: =AVERAGE(E28:N28) -> 0.013091539
D30: Cumulative % | E30: =E28 -> 0.017692308 | F30: =E30+F28 -> 0.033609467 | G30: =F30+G28 -> 0.048161129 | H30: =G30+H28 -> 0.061662407 | I30: =H30+I28 -> 0.074355698 | J30: =I30+J28 -> 0.08642746 | K30: =J30+K28 -> 0.098021123 | L30: =K30+L28 -> 0.10924702 | M30: =L30+M28 -> 0.12019001 | N30: =M30+N28 -> 0.13091539
B32: Stable Receiver / Fiat Lender | C32: Test Case | D32: ="10 BTC / "&TEXT($E$4*10, "$###0.00,,")&"M USD" -> 10 BTC / $1.00M USD | E32: Year 1 | F32: Year 2 | G32: Year 3 | H32: Year 4 | I32: Year 5 | J32: Year 6 | K32: Year 7 | L32: Year 8 | M32: Year 9 | N32: Year 10
B34: Bitcoin Liquidity Yield (BiLY) | C34: BTC | D34: Total Annual % | E34: =E39*$E$4/E$15 -> 0.11538462 | F34: =F39*$E$4/F$15 -> 0.088757396 | G34: =G39*$E$4/G$15 -> 0.06827492 | H34: =H39*$E$4/H$15 -> 0.052519169 | I34: =I39*$E$4/I$15 -> 0.040399361 | J34: =J39*$E$4/J$15 -> 0.031076432 | K34: =K39*$E$4/K$15 -> 0.023904947 | L34: =L39*$E$4/L$15 -> 0.018388421 | ... N34: =N39*$E$4/N$15 -> 0.010880723
D35: Total Annual Average % | I35: =AVERAGE(E34:I34) -> 0.073067093 | N35: =AVERAGE(E34:N34) -> 0.046373092
D36: Cumulative % | E36: =E$17*(E34/E$19) -> 0.11538462 | F36: =F$17*(F34/F$19) -> 0.20414201 | G36: =G$17*(G34/G$19) -> 0.27241693 | H36: =H$17*(H34/H$19) -> 0.3249361 | I36: =I$17*(I34/I$19) -> 0.36533546 | J36: =J$17*(J34/J$19) -> 0.39641189 | K36: =K$17*(K34/K$19) -> 0.42031684 | L36: =L$17*(L34/L$19) -> 0.43870526 | ... N36: =N$17*(N34/N$19) -> 0.46373092
D37: Test Case Annual | E37: =10*E34 -> 1.1538462 | F37: =10*F34 -> 0.88757396 | G37: =10*G34 -> 0.6827492 | H37: =10*H34 -> 0.52519169 | I37: =10*I34 -> 0.40399361 | J37: =10*J34 -> 0.31076432 | K37: =10*K34 -> 0.23904947 | L37: =10*L34 -> 0.18388421 | ... N37: =10*N34 -> 0.10880723
D38: Test Case Cumulative | E38: =10*E36 -> 1.1538462 | F38: =10*F36 -> 2.0414201 | G38: =10*G36 -> 2.7241693 | H38: =10*H36 -> 3.249361 | I38: =10*I36 -> 3.6533546 | J38: =10*J36 -> 3.9641189 | K38: =10*K36 -> 4.2031684 | L38: =10*L36 -> 4.3870526 | ... N38: =10*N36 -> 4.6373092
C39: USD Simple | D39: Annual % | E39: =E8 -> 0.15 | F39: =E39 -> 0.15 | G39: =F39 -> 0.15 | H39: =G39 -> 0.15 | I39: =H39 -> 0.15 | J39: =I39 -> 0.15 | K39: =J39 -> 0.15 | L39: =K39 -> 0.15 | M39: =L39 -> 0.15 | N39: =M39 -> 0.15
D40: Test Case Annual | E40: =E37*E$15 -> 150000 | F40: =F37*F$15 -> 150000 | G40: =G37*G$15 -> 150000 | H40: =H37*H$15 -> 150000 | I40: =I37*I$15 -> 150000 | J40: =J37*J$15 -> 150000 | K40: =K37*K$15 -> 150000 | L40: =L37*L$15 -> 150000 | ... N40: =N37*N$15 -> 150000
D41: Test Case Cumulative | E41: =E40 -> 150000 | F41: =E41+F40 -> 300000 | G41: =F41+G40 -> 450000 | H41: =G41+H40 -> 600000 | I41: =H41+I40 -> 750000 | J41: =I41+J40 -> 900000 | K41: =J41+K40 -> 1050000 | L41: =K41+L40 -> 1200000 | M41: =L41+M40 -> 1350000 | N41: =M41+N40 -> 1500000
C42: USD Compounded | D42: Annual % | E42: =E36*E$15/$E$4 -> 0.15 | F42: =F36*F$15/$E$4-E42 -> 0.195 | G42: =G36*G$15/$E$4-F42-E42 -> 0.2535 | H42: =H36*H$15/$E$4-G42-F42-E42 -> 0.32955 | I42: =I36*I$15/$E$4-H42-G42-F42-E42 -> 0.428415 | J42: =J36*J$15/$E$4-I42-H42-G42-F42-E42 -> 0.5569395 | K42: =K36*K$15/$E$4-J42-I42-H42-G42-F42-E42 -> 0.72402135 | L42: =L36*L$15/$E$4-K42-J42-I42-H42-G42-F42-E42 -> 0.94122775 | M42: =M36*M$15/$E$4-L42-K42-J42-I42-H42-G42-F42-E42 -> 1.2235961 | N42: =N36*N$15/$E$4-M42-L42-K42-J42-I42-H42-G42-F42-E42 -> 1.5906749
D43: Annual Average % | I43: =AVERAGE(E42:I42) -> 0.271293 | N43: =AVERAGE(E42:N42) -> 0.63929246
D44: Test Case Annual | E44: =E46 -> 150000 | F44: =F46-E46 -> 195000 | G44: =G46-F46 -> 253500 | H44: =H46-G46 -> 329550 | I44: =I46-H46 -> 428415 | J44: =J46-I46 -> 556939.5 | K44: =K46-J46 -> 724021.35 | L44: =L46-K46 -> 941227.75 | M44: =M46-L46 -> 1223596.1 | N44: =N46-M46 -> 1590674.9
D45: Test Case Annual Average | I45: =AVERAGE(E44:I44) -> 271293 | N45: =AVERAGE(E44:N44) -> 639292.46
D46: Test Case Cumulative | E46: =E38*E$15 -> 150000 | F46: =F38*F$15 -> 345000 | G46: =G38*G$15 -> 598500 | H46: =H38*H$15 -> 928050 | I46: =I38*I$15 -> 1356465 | J46: =J38*J$15 -> 1913404.5 | K46: =K38*K$15 -> 2637425.9 | L46: =L38*L$15 -> 3578653.6 | ... N46: =N38*N$15 -> 6392924.6
B48: Stable Balancer / Lightning Service Provider | C48: Test Case | D48: ="10 BTC / "&TEXT($E$4*10, "$###0.00,,")&"M USD" -> 10 BTC / $1.00M USD | E48: Year 1 | F48: Year 2 | G48: Year 3 | H48: Year 4 | I48: Year 5 | J48: Year 6 | K48: Year 7 | L48: Year 8 | M48: Year 9 | N48: Year 10
B50: Bitcoin Liquidity Yield (BiLY) | C50: BTC | D50: Annual % | E50: =E55*$E$4/E$15 -> 0.038461538 | F50: =F55*$E$4/F$15 -> 0.029585799 | G50: =G55*$E$4/G$15 -> 0.022758307 | H50: =H55*$E$4/H$15 -> 0.01750639 | I50: =I55*$E$4/I$15 -> 0.013466454 | J50: =J55*$E$4/J$15 -> 0.010358811 | K50: =K55*$E$4/K$15 -> 0.0079683158 | L50: =L55*$E$4/L$15 -> 0.0061294737 | ... N50: =N55*$E$4/N$15 -> 0.0036269075
D51: Annual Average % | I51: =AVERAGE(E50:I50) -> 0.024355698 | N51: =AVERAGE(E50:N50) -> 0.015457697
D52: Cumulative % | E52: =E$17*(E50/E$19) -> 0.038461538 | F52: =F$17*(F50/F$19) -> 0.068047337 | G52: =G$17*(G50/G$19) -> 0.090805644 | H52: =H$17*(H50/H$19) -> 0.10831203 | I52: =I$17*(I50/I$19) -> 0.12177849 | J52: =J$17*(J50/J$19) -> 0.1321373 | K52: =K$17*(K50/K$19) -> 0.14010561 | L52: =L$17*(L50/L$19) -> 0.14623509 | ... N52: =N$17*(N50/N$19) -> 0.15457697
D53: Test Case Annual | E53: =10*E50 -> 0.38461538 | F53: =10*F50 -> 0.29585799 | G53: =10*G50 -> 0.22758307 | H53: =10*H50 -> 0.1750639 | I53: =10*I50 -> 0.13466454 | J53: =10*J50 -> 0.10358811 | K53: =10*K50 -> 0.079683158 | L53: =10*L50 -> 0.061294737 | ... N53: =10*N50 -> 0.036269075
D54: Test Case Cumulative | E54: =10*E52 -> 0.38461538 | F54: =10*F52 -> 0.68047337 | G54: =10*G52 -> 0.90805644 | H54: =10*H52 -> 1.0831203 | I54: =10*I52 -> 1.2177849 | J54: =10*J52 -> 1.321373 | K54: =10*K52 -> 1.4010561 | L54: =10*L52 -> 1.4623509 | ... N54: =10*N52 -> 1.5457697
C55: USD Simple | D55: Annual % | E55: =$E9+($E$10*$E$11) -> 0.05 | F55: =$E9+($E$10*$E$11) -> 0.05 | G55: =$E9+($E$10*$E$11) -> 0.05 | H55: =$E9+($E$10*$E$11) -> 0.05 | I55: =$E9+($E$10*$E$11) -> 0.05 | J55: =$E9+($E$10*$E$11) -> 0.05 | K55: =$E9+($E$10*$E$11) -> 0.05 | L55: =$E9+($E$10*$E$11) -> 0.05 | ... N55: =$E9+($E$10*$E$11) -> 0.05
D56: Test Case Annual | E56: =E53*E$15 -> 50000 | F56: =F53*F$15 -> 50000 | G56: =G53*G$15 -> 50000 | H56: =H53*H$15 -> 50000 | I56: =I53*I$15 -> 50000 | J56: =J53*J$15 -> 50000 | K56: =K53*K$15 -> 50000 | L56: =L53*L$15 -> 50000 | ... N56: =N53*N$15 -> 50000
D57: Test Case Cumulative | E57: =E56 -> 50000 | F57: =E57+F56 -> 100000 | G57: =F57+G56 -> 150000 | H57: =G57+H56 -> 200000 | I57: =H57+I56 -> 250000 | J57: =I57+J56 -> 300000 | K57: =J57+K56 -> 350000 | L57: =K57+L56 -> 400000 | M57: =L57+M56 -> 450000 | N57: =M57+N56 -> 500000
C58: USD Compounded | D58: Annual % | E58: =E52*E$15/$E$4 -> 0.05 | F58: =F52*F$15/$E$4-E58 -> 0.065 | G58: =G52*G$15/$E$4-F58-E58 -> 0.0845 | H58: =H52*H$15/$E$4-G58-F58-E58 -> 0.10985 | I58: =I52*I$15/$E$4-H58-G58-F58-E58 -> 0.142805 | J58: =J52*J$15/$E$4-I58-H58-G58-F58-E58 -> 0.1856465 | K58: =K52*K$15/$E$4-J58-I58-H58-G58-F58-E58 -> 0.24134045 | L58: =L52*L$15/$E$4-K58-J58-I58-H58-G58-F58-E58 -> 0.31374258 | M58: =M52*M$15/$E$4-L58-K58-J58-I58-H58-G58-F58-E58 -> 0.40786536 | N58: =N52*N$15/$E$4-M58-L58-K58-J58-I58-H58-G58-F58-E58 -> 0.53022497
D59: Annual Average % | I59: =AVERAGE(E58:I58) -> 0.090431 | N59: =AVERAGE(E58:N58) -> 0.21309749
D60: Test Case Annual | E60: =E62 -> 50000 | F60: =F62-E62 -> 65000 | G60: =G62-F62 -> 84500 | H60: =H62-G62 -> 109850 | I60: =I62-H62 -> 142805 | J60: =J62-I62 -> 185646.5 | K60: =K62-J62 -> 241340.45 | L60: =L62-K62 -> 313742.58 | M60: =M62-L62 -> 407865.36 | N60: =N62-M62 -> 530224.97
D61: Test Case Annual Average | I61: =AVERAGE(E60:I60) -> 90431 | N61: =AVERAGE(E60:N60) -> 213097.49
D62: Test Case Cumulative | E62: =E54*E$15 -> 50000 | F62: =F54*F$15 -> 115000 | G62: =G54*G$15 -> 199500 | H62: =H54*H$15 -> 309350 | I62: =I54*I$15 -> 452155 | J62: =J54*J$15 -> 637801.5 | K62: =K54*K$15 -> 879141.95 | L62: =L54*L$15 -> 1192884.5 | ... N62: =N54*N$15 -> 2130974.9
B64: Stable Provider / Bitcoin Borrower | C64: Test Case | D64: ="10 BTC / "&TEXT($E$4*10, "$###0.00,,")&"M USD" -> 10 BTC / $1.00M USD | E64: Year 1 | F64: Year 2 | G64: Year 3 | H64: Year 4 | I64: Year 5 | J64: Year 6 | K64: Year 7 | L64: Year 8 | M64: Year 9 | N64: Year 10
B66: Bitcoin Growth Yield (BiGY) | C66: BTC | D66: Total Annual % | E66: =E$23 -> 0.23076923 | F66: =F$23 -> 0.17751479 | G66: =G$23 -> 0.13654984 | H66: =H$23 -> 0.10503834 | I66: =I$23 -> 0.080798722 | J66: =J$23 -> 0.062152863 | K66: =K$23 -> 0.047809895 | L66: =L$23 -> 0.036776842 | ... N66: =N$23 -> 0.021761445
D67: Total Annual Average % | I67: =AVERAGE(E66:I66) -> 0.14613419 | N67: =AVERAGE(E66:N66) -> 0.092746185
D68: Cumulative % | E68: =E$17*(E66/E$19) -> 0.23076923 | F68: =F$17*(F66/F$19) -> 0.40828402 | G68: =G$17*(G66/G$19) -> 0.54483386 | H68: =H$17*(H66/H$19) -> 0.6498722 | I68: =I$17*(I66/I$19) -> 0.73067093 | J68: =J$17*(J66/J$19) -> 0.79282379 | K68: =K$17*(K66/K$19) -> 0.84063368 | L68: =L$17*(L66/L$19) -> 0.87741053 | ... N68: =N$17*(N66/N$19) -> 0.92746185
D69: Test Case Annual | E69: =10*E66 -> 2.3076923 | F69: =10*F66 -> 1.7751479 | G69: =10*G66 -> 1.3654984 | H69: =10*H66 -> 1.0503834 | I69: =10*I66 -> 0.80798722 | J69: =10*J66 -> 0.62152863 | K69: =10*K66 -> 0.47809895 | L69: =10*L66 -> 0.36776842 | ... N69: =10*N66 -> 0.21761445
D70: Test Case Cumulative | E70: =10*E68 -> 2.3076923 | F70: =10*F68 -> 4.0828402 | G70: =10*G68 -> 5.4483386 | H70: =10*H68 -> 6.498722 | I70: =10*I68 -> 7.3067093 | J70: =10*J68 -> 7.9282379 | K70: =10*K68 -> 8.4063368 | L70: =10*L68 -> 8.7741053 | ... N70: =10*N68 -> 9.2746185
C71: USD Simple | D71: Annual % | E71: =E66*E$15/$E$4 -> 0.3 | F71: =F66*F$15/$E$4 -> 0.3 | G71: =G66*G$15/$E$4 -> 0.3 | H71: =H66*H$15/$E$4 -> 0.3 | I71: =I66*I$15/$E$4 -> 0.3 | J71: =J66*J$15/$E$4 -> 0.3 | K71: =K66*K$15/$E$4 -> 0.3 | L71: =L66*L$15/$E$4 -> 0.3 | ... N71: =N66*N$15/$E$4 -> 0.3
D72: Test Case Annual | E72: =E69*E$15 -> 300000 | F72: =F69*F$15 -> 300000 | G72: =G69*G$15 -> 300000 | H72: =H69*H$15 -> 300000 | I72: =I69*I$15 -> 300000 | J72: =J69*J$15 -> 300000 | K72: =K69*K$15 -> 300000 | L72: =L69*L$15 -> 300000 | ... N72: =N69*N$15 -> 300000
D73: Test Case Cumulative | E73: =E72 -> 300000 | F73: =E73+F72 -> 600000 | G73: =F73+G72 -> 900000 | H73: =G73+H72 -> 1200000 | I73: =H73+I72 -> 1500000 | J73: =I73+J72 -> 1800000 | K73: =J73+K72 -> 2100000 | L73: =K73+L72 -> 2400000 | M73: =L73+M72 -> 2700000 | N73: =M73+N72 -> 3000000
C74: USD Compounded | D74: Annual % | E74: =E68*E$15/$E$4 -> 0.3 | F74: =F68*F$15/$E$4-E74 -> 0.39 | G74: =G68*G$15/$E$4-F74-E74 -> 0.507 | H74: =H68*H$15/$E$4-G74-F74-E74 -> 0.6591 | I74: =I68*I$15/$E$4-H74-G74-F74-E74 -> 0.85683 | J74: =J68*J$15/$E$4-I74-H74-G74-F74-E74 -> 1.113879 | K74: =K68*K$15/$E$4-J74-I74-H74-G74-F74-E74 -> 1.4480427 | L74: =L68*L$15/$E$4-K74-J74-I74-H74-G74-F74-E74 -> 1.8824555 | M74: =M68*M$15/$E$4-L74-K74-J74-I74-H74-G74-F74-E74 -> 2.4471922 | N74: =N68*N$15/$E$4-M74-L74-K74-J74-I74-H74-G74-F74-E74 -> 3.1813498
D75: Annual Average % | I75: =AVERAGE(E74:I74) -> 0.542586 | N75: =AVERAGE(E74:N74) -> 1.2785849
D76: Test Case Annual | E76: =E78 -> 300000 | F76: =F78-E78 -> 390000 | G76: =G78-F78 -> 507000 | H76: =H78-G78 -> 659100 | I76: =I78-H78 -> 856830 | J76: =J78-I78 -> 1113879 | K76: =K78-J78 -> 1448042.7 | L76: =L78-K78 -> 1882455.5 | M76: =M78-L78 -> 2447192.2 | N76: =N78-M78 -> 3181349.8
D77: Test Case Annual Average | I77: =AVERAGE(E76:I76) -> 542586 | N77: =AVERAGE(E76:N76) -> 1278584.9
D78: Test Case Cumulative | E78: =E70*E$15 -> 300000 | F78: =F70*F$15 -> 690000 | G78: =G70*G$15 -> 1197000 | H78: =H70*H$15 -> 1856100 | I78: =I70*I$15 -> 2712930 | J78: =J70*J$15 -> 3826809 | K78: =K70*K$15 -> 5274851.7 | L78: =L70*L$15 -> 7157307.2 | ... N78: =N70*N$15 -> 12785849
B79: Bitcoin Liquidity Yield (BiLY) | C79: BTC | D79: Annual % | E79: =E$25 -> 0.035384615 | F79: =F$25 -> 0.03183432 | G79: =G$25 -> 0.029103323 | H79: =H$25 -> 0.027002556 | I79: =I$25 -> 0.025386581 | J79: =J$25 -> 0.024143524 | K79: =K$25 -> 0.023187326 | L79: =L$25 -> 0.022451789 | ... N79: =N$25 -> 0.021450763
D80: Annual Average % | I80: =AVERAGE(E79:I79) -> 0.029742279 | N80: =AVERAGE(E79:N79) -> 0.026183079
D81: Cumulative % | E81: =E$27 -> 0.035384615 | F81: =F$27 -> 0.067218935 | G81: =G$27 -> 0.096322258 | H81: =H$27 -> 0.12332481 | I81: =I$27 -> 0.1487114 | J81: =J$27 -> 0.17285492 | K81: =K$27 -> 0.19604225 | L81: =L$27 -> 0.21849404 | ... N81: =N$27 -> 0.26183079
D82: Test Case Annual | E82: =10*E79 -> 0.35384615 | F82: =10*F79 -> 0.3183432 | G82: =10*G79 -> 0.29103323 | H82: =10*H79 -> 0.27002556 | I82: =10*I79 -> 0.25386581 | J82: =10*J79 -> 0.24143524 | K82: =10*K79 -> 0.23187326 | L82: =10*L79 -> 0.22451789 | ... N82: =10*N79 -> 0.21450763
D83: Test Case Cumulative | E83: =10*E81 -> 0.35384615 | F83: =10*F81 -> 0.67218935 | G83: =10*G81 -> 0.96322258 | H83: =10*H81 -> 1.2332481 | I83: =10*I81 -> 1.487114 | J83: =10*J81 -> 1.7285492 | K83: =10*K81 -> 1.9604225 | L83: =10*L81 -> 2.1849404 | ... N83: =10*N81 -> 2.6183079
C84: USD Simple | D84: Annual % | E84: =E79*E$15/$E$4 -> 0.046 | F84: =F79*F$15/$E$4 -> 0.0538 | G84: =G79*G$15/$E$4 -> 0.06394 | H84: =H79*H$15/$E$4 -> 0.077122 | I84: =I79*I$15/$E$4 -> 0.0942586 | J84: =J79*J$15/$E$4 -> 0.11653618 | K84: =K79*K$15/$E$4 -> 0.14549703 | L84: =L79*L$15/$E$4 -> 0.18314614 | ... N84: =N79*N$15/$E$4 -> 0.29571698
D85: Annual Average % | I85: =AVERAGE(E84:I84) -> 0.06702412 | N85: =AVERAGE(E84:N84) -> 0.13081069
D86: Test Case Annual | E86: =E82*E$15 -> 46000 | F86: =F82*F$15 -> 53800 | G86: =G82*G$15 -> 63940 | H86: =H82*H$15 -> 77122 | I86: =I82*I$15 -> 94258.6 | J86: =J82*J$15 -> 116536.18 | K86: =K82*K$15 -> 145497.03 | L86: =L82*L$15 -> 183146.14 | ... N86: =N82*N$15 -> 295716.98
D87: Test Case Annual Average | I87: =AVERAGE(E86:I86) -> 67024.12 | N87: =AVERAGE(E86:N86) -> 130810.69
D88: Test Case Cumulative | E88: =E86 -> 46000 | F88: =E88+F86 -> 99800 | G88: =F88+G86 -> 163740 | H88: =G88+H86 -> 240862 | I88: =H88+I86 -> 335120.6 | J88: =I88+J86 -> 451656.78 | K88: =J88+K86 -> 597153.81 | L88: =K88+L86 -> 780299.96 | M88: =L88+M86 -> 1012389.9 | N88: =M88+N86 -> 1308106.9
C89: USD Compounded | D89: Annual % | E89: =E81*E$15/$E$4 -> 0.046 | F89: =F81*F$15/$E$4-E89 -> 0.0676 | G89: =G81*G$15/$E$4-F89-E89 -> 0.09802 | H89: =H81*H$15/$E$4-G89-F89-E89 -> 0.140608 | I89: =I81*I$15/$E$4-H89-G89-F89-E89 -> 0.199927 | J89: =J81*J$15/$E$4-I89-H89-G89-F89-E89 -> 0.28218268 | K89: =K81*K$15/$E$4-J89-I89-H89-G89-F89-E89 -> 0.39579834 | L89: =L81*L$15/$E$4-K89-J89-I89-H89-G89-F89-E89 -> 0.55218695 | M89: =M81*M$15/$E$4-L89-K89-J89-I89-H89-G89-F89-E89 -> 0.76678688 | N89: =N81*N$15/$E$4-M89-L89-K89-J89-I89-H89-G89-F89-E89 -> 1.0604499
D90: Annual Average % | I90: =AVERAGE(E89:I89) -> 0.110431 | N90: =AVERAGE(E89:N89) -> 0.36095598
D91: Test Case Annual | E91: =E93 -> 46000 | F91: =F93-E93 -> 67600 | G91: =G93-F93 -> 98020 | H91: =H93-G93 -> 140608 | I91: =I93-H93 -> 199927 | J91: =J93-I93 -> 282182.68 | K91: =K93-J93 -> 395798.34 | L91: =L93-K93 -> 552186.95 | M91: =M93-L93 -> 766786.88 | N91: =N93-M93 -> 1060449.9
D92: Test Case Annual Average | I92: =AVERAGE(E91:I91) -> 110431 | N92: =AVERAGE(E91:N91) -> 360955.98
D93: Test Case Cumulative | E93: =E83*E$15 -> 46000 | F93: =F83*F$15 -> 113600 | G93: =G83*G$15 -> 211620 | H93: =H83*H$15 -> 352228 | I93: =I83*I$15 -> 552155 | J93: =J83*J$15 -> 834337.68 | K93: =K83*K$15 -> 1230136 | L93: =L83*L$15 -> 1782323 | ... N93: =N83*N$15 -> 3609559.8
B94: Bitcoin Transaction Yield (BiTY) | C94: BTC | D94: Annual % | E94: =E$28 -> 0.017692308 | F94: =F$28 -> 0.01591716 | G94: =G$28 -> 0.014551661 | H94: =H$28 -> 0.013501278 | I94: =I$28 -> 0.012693291 | J94: =J$28 -> 0.012071762 | K94: =K$28 -> 0.011593663 | L94: =L$28 -> 0.011225895 | ... N94: =N$28 -> 0.010725382
D95: Annual Average % | I95: =AVERAGE(E94:I94) -> 0.01487114 | N95: =AVERAGE(E94:N94) -> 0.013091539
D96: Cumulative % | E96: =E$30 -> 0.017692308 | F96: =F$30 -> 0.033609467 | G96: =G$30 -> 0.048161129 | H96: =H$30 -> 0.061662407 | I96: =I$30 -> 0.074355698 | J96: =J$30 -> 0.08642746 | K96: =K$30 -> 0.098021123 | L96: =L$30 -> 0.10924702 | ... N96: =N$30 -> 0.13091539
D97: Test Case Annual | E97: =10*E94 -> 0.17692308 | F97: =10*F94 -> 0.1591716 | G97: =10*G94 -> 0.14551661 | H97: =10*H94 -> 0.13501278 | I97: =10*I94 -> 0.12693291 | J97: =10*J94 -> 0.12071762 | K97: =10*K94 -> 0.11593663 | L97: =10*L94 -> 0.11225895 | ... N97: =10*N94 -> 0.10725382
D98: Test Case Cumulative | E98: =10*E96 -> 0.17692308 | F98: =10*F96 -> 0.33609467 | G98: =10*G96 -> 0.48161129 | H98: =10*H96 -> 0.61662407 | I98: =10*I96 -> 0.74355698 | J98: =10*J96 -> 0.8642746 | K98: =10*K96 -> 0.98021123 | L98: =10*L96 -> 1.0924702 | ... N98: =10*N96 -> 1.3091539
C99: USD Simple | D99: Annual % | E99: =E94*E$15/$E$4 -> 0.023 | F99: =F94*F$15/$E$4 -> 0.0269 | G99: =G94*G$15/$E$4 -> 0.03197 | H99: =H94*H$15/$E$4 -> 0.038561 | I99: =I94*I$15/$E$4 -> 0.0471293 | J99: =J94*J$15/$E$4 -> 0.05826809 | K99: =K94*K$15/$E$4 -> 0.072748517 | L99: =L94*L$15/$E$4 -> 0.091573072 | ... N99: =N94*N$15/$E$4 -> 0.14785849
D100: Annual Average % | I100: =AVERAGE(E99:I99) -> 0.03351206 | N100: =AVERAGE(E99:N99) -> 0.065405346
D101: Test Case Annual | E101: =E97*E$15 -> 23000 | F101: =F97*F$15 -> 26900 | G101: =G97*G$15 -> 31970 | H101: =H97*H$15 -> 38561 | I101: =I97*I$15 -> 47129.3 | J101: =J97*J$15 -> 58268.09 | K101: =K97*K$15 -> 72748.517 | L101: =L97*L$15 -> 91573.072 | ... N101: =N97*N$15 -> 147858.49
D102: Test Case Annual Average | I102: =AVERAGE(E101:I101) -> 33512.06 | N102: =AVERAGE(E101:N101) -> 65405.346
D103: Test Case Cumulative | E103: =E101 -> 23000 | F103: =E103+F101 -> 49900 | G103: =F103+G101 -> 81870 | H103: =G103+H101 -> 120431 | I103: =H103+I101 -> 167560.3 | J103: =I103+J101 -> 225828.39 | K103: =J103+K101 -> 298576.91 | L103: =K103+L101 -> 390149.98 | M103: =L103+M101 -> 506194.97 | N103: =M103+N101 -> 654053.46
C104: USD Compounded | D104: Annual % | E104: =E96*E$15/$E$4 -> 0.023 | F104: =F96*F$15/$E$4-E104 -> 0.0338 | G104: =G96*G$15/$E$4-F104-E104 -> 0.04901 | H104: =H96*H$15/$E$4-G104-F104-E104 -> 0.070304 | I104: =I96*I$15/$E$4-H104-G104-F104-E104 -> 0.0999635 | J104: =J96*J$15/$E$4-I104-H104-G104-F104-E104 -> 0.14109134 | K104: =K96*K$15/$E$4-J104-I104-H104-G104-F104-E104 -> 0.19789917 | L104: =L96*L$15/$E$4-K104-J104-I104-H104-G104-F104-E104 -> 0.27609347 | M104: =M96*M$15/$E$4-L104-K104-J104-I104-H104-G104-F104-E104 -> 0.38339344 | N104: =N96*N$15/$E$4-M104-L104-K104-J104-I104-H104-G104-F104-E104 -> 0.53022497
D105: Annual Average % | I105: =AVERAGE(E104:I104) -> 0.0552155 | N105: =AVERAGE(E104:N104) -> 0.18047799
D106: Test Case Annual | E106: =E108 -> 23000 | F106: =F108-E108 -> 33800 | G106: =G108-F108 -> 49010 | H106: =H108-G108 -> 70304 | I106: =I108-H108 -> 99963.5 | J106: =J108-I108 -> 141091.34 | K106: =K108-J108 -> 197899.17 | L106: =L108-K108 -> 276093.47 | M106: =M108-L108 -> 383393.44 | N106: =N108-M108 -> 530224.97
D107: Test Case Annual Average | I107: =AVERAGE(E106:I106) -> 55215.5 | N107: =AVERAGE(E106:N106) -> 180477.99
D108: Test Case Cumulative | E108: =E98*E$15 -> 23000 | F108: =F98*F$15 -> 56800 | G108: =G98*G$15 -> 105810 | H108: =H98*H$15 -> 176114 | I108: =I98*I$15 -> 276077.5 | J108: =J98*J$15 -> 417168.84 | K108: =K98*K$15 -> 615068.01 | L108: =L98*L$15 -> 891161.48 | ... N108: =N98*N$15 -> 1804779.9
B109: Total Yield | C109: BTC | D109: Annual % | E109: =E66+E79+E94-E34-E50 -> 0.13 | F109: =F66+F79+F94-F34-F50 -> 0.10692308 | G109: =G66+G79+G94-G34-G50 -> 0.089171598 | H109: =H66+H79+H94-H34-H50 -> 0.075516614 | I109: =I66+I79+I94-I34-I50 -> 0.06501278 | J109: =J66+J79+J94-J34-J50 -> 0.056932907 | K109: =K66+K79+K94-K34-K50 -> 0.050717621 | L109: =L66+L79+L94-L34-L50 -> 0.045936632 | ... N109: =N66+N79+N94-N34-N50 -> 0.03942996
...

Sheet YIELD_BURNDOWN
B2: Bitcoin Lightning Credit Derivatives A permissionless, decentralized and distributed strategy for ultra-high yields using leveraged bitcoin growth and lightning transaction fee exposure | C2: Bitcoin Yield Estimate Variables | F2: Bitcoin Compound Annual Growth Rate Calculator
C4: Bitcoin USD Price Start | D4: 100000 | F4: Start Price | I4: 57885.44
F5: Start Date | I5: 44519
F6: End Price | I6: 89588.18
F7: End Date | I7: 45980
F8: Compound Annual Growth Rate | I8: =(I6/I4)^(1/DATEDIF(I5,I7,"Y"))-1 -> 0.11537356
B10: Bitcoin Yield Estimate 10 Year Burndown Summary | D10: Year 1 | E10: Year 2 | F10: Year 3 | G10: Year 4 | H10: Year 5 | I10: Year 6 | J10: Year 7 | K10: Year 8 | L10: Year 9 | M10: Year 10
B11: Bitcoin Compound Annual Growth Rate (CAGR) | C11: Measure
B12: 0.2 | C12: Bitcoin USD Price | D12: =($D$4 * $B12) + $D$4 -> 120000 | E12: =(D12 * $B12) + D12 -> 144000 | F12: =(E12 * $B12) + E12 -> 172800 | G12: =(F12 * $B12) + F12 -> 207360 | H12: =(G12 * $B12) + G12 -> 248832 | I12: =(H12 * $B12) + H12 -> 298598.4 | J12: =(I12 * $B12) + I12 -> 358318.08 | K12: =(J12 * $B12) + J12 -> 429981.7 | L12: =(K12 * $B12) + K12 -> 515978.04 | M12: =(L12 * $B12) + L12 -> 619173.64
C13: Bitcoin USD Marketcap | D13: =D12*21000000 -> 2520000000000 | E13: =E12*21000000 -> 3024000000000 | F13: =F12*21000000 -> 3628800000000 | G13: =G12*21000000 -> 4354560000000 | H13: =H12*21000000 -> 5225472000000 | I13: =I12*21000000 -> 6.2705664e+12 | J13: =J12*21000000 -> 7524679680000 | K13: =K12*21000000 -> 9029615616000 | ... M13: =M12*21000000 -> 13002646487040
C14: Cumulative BTC Yield % | D14: =( ( D12 - $D$4 ) ) / D12 -> 0.16666667 | E14: =( ( E12 - $D$4 ) ) / E12 -> 0.30555556 | F14: =( ( F12 - $D$4 ) ) / F12 -> 0.4212963 | G14: =( ( G12 - $D$4 ) ) / G12 -> 0.51774691 | H14: =( ( H12 - $D$4 ) ) / H12 -> 0.59812243 | I14: =( ( I12 - $D$4 ) ) / I12 -> 0.66510202 | J14: =( ( J12 - $D$4 ) ) / J12 -> 0.72091835 | K14: =( ( K12 - $D$4 ) ) / K12 -> 0.76743196 | ... M14: =( ( M12 - $D$4 ) ) / M12 -> 0.83849442
C15: Remaining BTC Yield % | D15: =1-D14 -> 0.83333333 | E15: =1-E14 -> 0.69444444 | F15: =1-F14 -> 0.5787037 | G15: =1-G14 -> 0.48225309 | H15: =1-H14 -> 0.40187757 | I15: =1-I14 -> 0.33489798 | J15: =1-J14 -> 0.27908165 | K15: =1-K14 -> 0.23256804 | ... M15: =1-M14 -> 0.16150558
C16: Annual BTC Yield % | D16: =D14 -> 0.16666667 | E16: =E14-D14 -> 0.13888889 | F16: =F14-E14 -> 0.11574074 | G16: =G14-F14 -> 0.096450617 | H16: =H14-G14 -> 0.080375514 | I16: =I14-H14 -> 0.066979595 | J16: =J14-I14 -> 0.055816329 | K16: =K14-J14 -> 0.046513608 | L16: =L14-K14 -> 0.03876134 | M16: =M14-L14 -> 0.032301117
C17: Annual Average BTC Yield % | H17: =SUM(D16:H16)/5 -> 0.11962449 | M17: =SUM(D16:M16)/10 -> 0.083849442
B18: 0.25 | C18: Bitcoin USD Price | D18: =($D$4 * $B18) + $D$4 -> 125000 | E18: =(D18 * $B18) + D18 -> 156250 | F18: =(E18 * $B18) + E18 -> 195312.5 | G18: =(F18 * $B18) + F18 -> 244140.62 | H18: =(G18 * $B18) + G18 -> 305175.78 | I18: =(H18 * $B18) + H18 -> 381469.73 | J18: =(I18 * $B18) + I18 -> 476837.16 | K18: =(J18 * $B18) + J18 -> 596046.45 | L18: =(K18 * $B18) + K18 -> 745058.06 | M18: =(L18 * $B18) + L18 -> 931322.57
C19: Bitcoin USD Marketcap | D19: =D18*21000000 -> 2625000000000 | E19: =E18*21000000 -> 3281250000000 | F19: =F18*21000000 -> 4101562500000 | G19: =G18*21000000 -> 5126953125000 | H19: =H18*21000000 -> 6408691406250 | I19: =I18*21000000 -> 8.0108643e+12 | J19: =J18*21000000 -> 1.001358e+13 | K19: =K18*21000000 -> 1.2516975e+13 | ... M19: =M18*21000000 -> 1.9557774e+13
C20: Cumulative BTC Yield % | D20: =( ( D18 - $D$4 ) ) / D18 -> 0.2 | E20: =( ( E18 - $D$4 ) ) / E18 -> 0.36 | F20: =( ( F18 - $D$4 ) ) / F18 -> 0.488 | G20: =( ( G18 - $D$4 ) ) / G18 -> 0.5904 | H20: =( ( H18 - $D$4 ) ) / H18 -> 0.67232 | I20: =( ( I18 - $D$4 ) ) / I18 -> 0.737856 | J20: =( ( J18 - $D$4 ) ) / J18 -> 0.7902848 | K20: =( ( K18 - $D$4 ) ) / K18 -> 0.83222784 | ... M20: =( ( M18 - $D$4 ) ) / M18 -> 0.89262582
C21: Remaining BTC Yield % | D21: =1-D20 -> 0.8 | E21: =1-E20 -> 0.64 | F21: =1-F20 -> 0.512 | G21: =1-G20 -> 0.4096 | H21: =1-H20 -> 0.32768 | I21: =1-I20 -> 0.262144 | J21: =1-J20 -> 0.2097152 | K21: =1-K20 -> 0.16777216 | ... M21: =1-M20 -> 0.10737418
C22: Annual BTC Yield % | D22: =D20 -> 0.2 | E22: =E20-D20 -> 0.16 | F22: =F20-E20 -> 0.128 | G22: =G20-F20 -> 0.1024 | H22: =H20-G20 -> 0.08192 | I22: =I20-H20 -> 0.065536 | J22: =J20-I20 -> 0.0524288 | K22: =K20-J20 -> 0.04194304 | L22: =L20-K20 -> 0.033554432 | M22: =M20-L20 -> 0.026843546
C23: Annual Average BTC Yield % | H23: =SUM(D22:H22)/5 -> 0.134464 | M23: =SUM(D22:M22)/10 -> 0.089262582
B24: 0.3 | C24: Bitcoin USD Price | D24: =($D$4 * $B24) + $D$4 -> 130000 | E24: =(D24 * $B24) + D24 -> 169000 | F24: =(E24 * $B24) + E24 -> 219700 | G24: =(F24 * $B24) + F24 -> 285610 | H24: =(G24 * $B24) + G24 -> 371293 | I24: =(H24 * $B24) + H24 -> 482680.9 | J24: =(I24 * $B24) + I24 -> 627485.17 | K24: =(J24 * $B24) + J24 -> 815730.72 | L24: =(K24 * $B24) + K24 -> 1060449.9 | M24: =(L24 * $B24) + L24 -> 1378584.9
C25: Bitcoin USD Marketcap | D25: =D24*21000000 -> 2730000000000 | E25: =E24*21000000 -> 3549000000000 | F25: =F24*21000000 -> 4613700000000 | G25: =G24*21000000 -> 5997810000000 | H25: =H24*21000000 -> 7797153000000 | I25: =I24*21000000 -> 10136298900000 | J25: =J24*21000000 -> 13177188570000 | K25: =K24*21000000 -> 17130345141000 | ... M25: =M24*21000000 -> 28950283288290
C26: Cumulative BTC Yield % | D26: =( ( D24 - $D$4 ) ) / D24 -> 0.23076923 | E26: =( ( E24 - $D$4 ) ) / E24 -> 0.40828402 | F26: =( ( F24 - $D$4 ) ) / F24 -> 0.54483386 | G26: =( ( G24 - $D$4 ) ) / G24 -> 0.6498722 | H26: =( ( H24 - $D$4 ) ) / H24 -> 0.73067093 | I26: =( ( I24 - $D$4 ) ) / I24 -> 0.79282379 | J26: =( ( J24 - $D$4 ) ) / J24 -> 0.84063368 | K26: =( ( K24 - $D$4 ) ) / K24 -> 0.87741053 | ... M26: =( ( M24 - $D$4 ) ) / M24 -> 0.92746185
C27: Remaining BTC Yield % | D27: =1-D26 -> 0.76923077 | E27: =1-E26 -> 0.59171598 | F27: =1-F26 -> 0.45516614 | G27: =1-G26 -> 0.3501278 | H27: =1-H26 -> 0.26932907 | I27: =1-I26 -> 0.20717621 | J27: =1-J26 -> 0.15936632 | K27: =1-K26 -> 0.12258947 | ... M27: =1-M26 -> 0.07253815
C28: Annual BTC Yield % | D28: =D26 -> 0.23076923 | E28: =E26-D26 -> 0.17751479 | F28: =F26-E26 -> 0.13654984 | G28: =G26-F26 -> 0.10503834 | H28: =H26-G26 -> 0.080798722 | I28: =I26-H26 -> 0.062152863 | J28: =J26-I26 -> 0.047809895 | K28: =K26-J26 -> 0.036776842 | L28: =L26-K26 -> 0.028289879 | M28: =M26-L26 -> 0.021761445
C29: Annual Average BTC Yield % | H29: =SUM(D28:H28)/5 -> 0.14613419 | M29: =SUM(D28:M28)/10 -> 0.092746185
B30: 0.35 | C30: Bitcoin USD Price | D30: =($D$4 * $B30) + $D$4 -> 135000 | E30: =(D30 * $B30) + D30 -> 182250 | F30: =(E30 * $B30) + E30 -> 246037.5 | G30: =(F30 * $B30) + F30 -> 332150.62 | H30: =(G30 * $B30) + G30 -> 448403.34 | I30: =(H30 * $B30) + H30 -> 605344.51 | J30: =(I30 * $B30) + I30 -> 817215.09 | K30: =(J30 * $B30) + J30 -> 1103240.4 | L30: =(K30 * $B30) + K30 -> 1489374.5 | M30: =(L30 * $B30) + L30 -> 2010655.6
C31: Bitcoin USD Marketcap | D31: =D30*21000000 -> 2835000000000 | E31: =E30*21000000 -> 3827250000000 | F31: =F30*21000000 -> 5166787500000 | G31: =G30*21000000 -> 6975163125000 | H31: =H30*21000000 -> 9416470218750 | I31: =I30*21000000 -> 1.2712235e+13 | J31: =J30*21000000 -> 1.7161517e+13 | K31: =K30*21000000 -> 2.3168048e+13 | ... M31: =M30*21000000 -> 4.2223767e+13
C32: Cumulative BTC Yield % | D32: =( ( D30 - $D$4 ) ) / D30 -> 0.25925926 | E32: =( ( E30 - $D$4 ) ) / E30 -> 0.45130316 | F32: =( ( F30 - $D$4 ) ) / F30 -> 0.59355789 | G32: =( ( G30 - $D$4 ) ) / G30 -> 0.69893177 | H32: =( ( H30 - $D$4 ) ) / H30 -> 0.7769865 | I32: =( ( I30 - $D$4 ) ) / I30 -> 0.83480481 | J32: =( ( J30 - $D$4 ) ) / J30 -> 0.8776332 | K32: =( ( K30 - $D$4 ) ) / K30 -> 0.90935792 | ... M32: =( ( M30 - $D$4 ) ) / M30 -> 0.95026498
C33: Remaining BTC Yield % | D33: =1-D32 -> 0.74074074 | E33: =1-E32 -> 0.54869684 | F33: =1-F32 -> 0.40644211 | G33: =1-G32 -> 0.30106823 | H33: =1-H32 -> 0.2230135 | I33: =1-I32 -> 0.16519519 | J33: =1-J32 -> 0.1223668 | K33: =1-K32 -> 0.090642078 | ... M33: =1-M32 -> 0.049735022
C34: Annual BTC Yield % | D34: =D32 -> 0.25925926 | E34: =E32-D32 -> 0.1920439 | F34: =F32-E32 -> 0.14225474 | G34: =G32-F32 -> 0.10537388 | H34: =H32-G32 -> 0.078054726 | I34: =I32-H32 -> 0.057818315 | J34: =J32-I32 -> 0.042828382 | K34: =K32-J32 -> 0.031724727 | L34: =L32-K32 -> 0.023499798 | M34: =M32-L32 -> 0.017407258
C35: Annual Average BTC Yield % | H35: =SUM(D34:H34)/5 -> 0.1553973 | M35: =SUM(D34:M34)/10 -> 0.095026498
B36: 0.4 | C36: Bitcoin USD Price | D36: =($D$4 * $B36) + $D$4 -> 140000 | E36: =(D36 * $B36) + D36 -> 196000 | F36: =(E36 * $B36) + E36 -> 274400 | G36: =(F36 * $B36) + F36 -> 384160 | H36: =(G36 * $B36) + G36 -> 537824 | I36: =(H36 * $B36) + H36 -> 752953.6 | J36: =(I36 * $B36) + I36 -> 1054135 | K36: =(J36 * $B36) + J36 -> 1475789.1 | L36: =(K36 * $B36) + K36 -> 2066104.7 | M36: =(L36 * $B36) + L36 -> 2892546.5
C37: Bitcoin USD Marketcap | D37: =D36*21000000 -> 2940000000000 | E37: =E36*21000000 -> 4116000000000 | F37: =F36*21000000 -> 5762400000000 | G37: =G36*21000000 -> 8067360000000 | H37: =H36*21000000 -> 11294304000000 | I37: =I36*21000000 -> 15812025600000 | J37: =J36*21000000 -> 22136835840000 | K37: =K36*21000000 -> 3.099157e+13 | ... M37: =M36*21000000 -> 6.0743478e+13
C38: Cumulative BTC Yield % | D38: =( ( D36 - $D$4 ) ) / D36 -> 0.28571429 | E38: =( ( E36 - $D$4 ) ) / E36 -> 0.48979592 | F38: =( ( F36 - $D$4 ) ) / F36 -> 0.63556851 | G38: =( ( G36 - $D$4 ) ) / G36 -> 0.7396918 | H38: =( ( H36 - $D$4 ) ) / H36 -> 0.81406557 | I38: =( ( I36 - $D$4 ) ) / I36 -> 0.86718969 | J38: =( ( J36 - $D$4 ) ) / J36 -> 0.90513549 | K38: =( ( K36 - $D$4 ) ) / K36 -> 0.93223964 | ... M38: =( ( M36 - $D$4 ) ) / M36 -> 0.96542839
C39: Remaining BTC Yield % | D39: =1-D38 -> 0.71428571 | E39: =1-E38 -> 0.51020408 | F39: =1-F38 -> 0.36443149 | G39: =1-G38 -> 0.2603082 | H39: =1-H38 -> 0.18593443 | I39: =1-I38 -> 0.13281031 | J39: =1-J38 -> 0.094864506 | K39: =1-K38 -> 0.067760362 | ... M39: =1-M38 -> 0.034571613
C40: Annual BTC Yield % | D40: =D38 -> 0.28571429 | E40: =E38-D38 -> 0.20408163 | F40: =F38-E38 -> 0.14577259 | G40: =G38-F38 -> 0.10412328 | H40: =H38-G38 -> 0.074373773 | I40: =I38-H38 -> 0.053124123 | J40: =J38-I38 -> 0.037945802 | K40: =K38-J38 -> 0.027104145 | L40: =L38-K38 -> 0.019360103 | M40: =M38-L38 -> 0.013828645
C41: Annual Average BTC Yield % | H41: =SUM(D40:H40)/5 -> 0.16281311 | M41: =SUM(D40:M40)/10 -> 0.096542839

Sheet BTC_MORTGAGE
B2: Bitcoin Lightning Mortgage Bitcoin collateral with price drawdown liquidation protection for leveraged Bitcoin growth and Lightning transaction exposure | E2: Test Case | F2: Bitcoin Investor | G2: Fiat Investor | H2: Service Provider | I2: Bitcoin Investor
F3: Stable Provider | G3: Stable Receiver | H3: Stable Receiver | I3: Total Down Payment | J3: Total Debt | K3: High-Interest Debt | L3: Low-Interest Debt | M3: Total Debt-to-Value
B4: Service | C4: Annual ETF Fee | D4: Annual Loan Fee | E4: BTC Total | F4: BTC Principal | G4: BTC Bond/Pref | H4: BTC Loan | I4: BTC Principal % | J4: BTC Debt % | K4: Bond/Pref-to-Value % | L4: Loan-to-Value % | M4: Debt-to-Value %
B5: ="Bitcoin Long " & E5 & "X" -> Bitcoin Long 2X | C5: 0.025 | D5: N/A | E5: 2 | F5: 1 | G5: =F5 -> 1 | H5: =E5-F5-G5 -> 0 | I5: =F5/E5 -> 0.5 | J5: =1-I5 -> 0.5 | K5: =G5/F5 -> 1 | L5: =H5/F5 -> 0 | M5: =K5+L5 -> 1
B6: ="Bitcoin Long " & E6 & "X" -> Bitcoin Long 2.5X | C6: 0.025 | D6: 0.075 | E6: 2.5 | F6: 1 | G6: =F6 -> 1 | H6: =E6-F6-G6 -> 0.5 | I6: =F6/E6 -> 0.4 | J6: =1-I6 -> 0.6 | K6: =G6/F6 -> 1 | L6: =H6/F6 -> 0.5 | M6: =K6+L6 -> 1.5
B7: ="Bitcoin Long " & E7 & "X" -> Bitcoin Long 3X | C7: 0.025 | D7: 0.075 | E7: 3 | F7: 1 | G7: =F7 -> 1 | H7: =E7-F7-G7 -> 1 | I7: =F7/E7 -> 0.33333333 | J7: =1-I7 -> 0.66666667 | K7: =G7/F7 -> 1 | L7: =H7/F7 -> 1 | M7: =K7+L7 -> 2
B8: ="Bitcoin Long " & E8 & "X" -> Bitcoin Long 3.5X | C8: 0.025 | D8: 0.075 | E8: 3.5 | F8: 1 | G8: =F8 -> 1 | H8: =E8-F8-G8 -> 1.5 | I8: =F8/E8 -> 0.28571429 | J8: =1-I8 -> 0.71428571 | K8: =G8/F8 -> 1 | L8: =H8/F8 -> 1.5 | M8: =K8+L8 -> 2.5
B9: ="Bitcoin Long " & E9 & "X" -> Bitcoin Long 4X | C9: 0.025 | D9: 0.075 | E9: 4 | F9: 1 | G9: =F9 -> 1 | H9: =E9-F9-G9 -> 2 | I9: =F9/E9 -> 0.25 | J9: =1-I9 -> 0.75 | K9: =G9/F9 -> 1 | L9: =H9/F9 -> 2 | M9: =K9+L9 -> 3
B10: ="Bitcoin Long " & E10 & "X" -> Bitcoin Long 4.5X | C10: 0.025 | D10: 0.075 | E10: 4.5 | F10: 1 | G10: =F10 -> 1 | H10: =E10-F10-G10 -> 2.5 | I10: =F10/E10 -> 0.22222222 | J10: =1-I10 -> 0.77777778 | K10: =G10/F10 -> 1 | L10: =H10/F10 -> 2.5 | M10: =K10+L10 -> 3.5
B11: ="Bitcoin Long " & E11 & "X" -> Bitcoin Long 5X | C11: 0.025 | D11: 0.075 | E11: 5 | F11: 1 | G11: =F11 -> 1 | H11: =E11-F11-G11 -> 3 | I11: =F11/E11 -> 0.2 | J11: =1-I11 -> 0.8 | K11: =G11/F11 -> 1 | L11: =H11/F11 -> 3 | M11: =K11+L11 -> 4
B12: ="Bitcoin Long " & E12 & "X" -> Bitcoin Long 5.5X | C12: 0.025 | D12: 0.075 | E12: 5.5 | F12: 1 | G12: =F12 -> 1 | H12: =E12-F12-G12 -> 3.5 | I12: =F12/E12 -> 0.18181818 | J12: =1-I12 -> 0.81818182 | K12: =G12/F12 -> 1 | L12: =H12/F12 -> 3.5 | M12: =K12+L12 -> 4.5
B13: ="Bitcoin Long " & E13 & "X" -> Bitcoin Long 6X | C13: 0.025 | D13: 0.075 | E13: 6 | F13: 1 | G13: =F13 -> 1 | H13: =E13-F13-G13 -> 4 | I13: =F13/E13 -> 0.16666667 | J13: =1-I13 -> 0.83333333 | K13: =G13/F13 -> 1 | L13: =H13/F13 -> 4 | M13: =K13+L13 -> 5
B14: ="Bitcoin Long " & E14 & "X" -> Bitcoin Long 6.5X | C14: 0.025 | D14: 0.075 | E14: 6.5 | F14: 1 | G14: =F14 -> 1 | H14: =E14-F14-G14 -> 4.5 | I14: =F14/E14 -> 0.15384615 | J14: =1-I14 -> 0.84615385 | K14: =G14/F14 -> 1 | L14: =H14/F14 -> 4.5 | M14: =K14+L14 -> 5.5
B15: ="Bitcoin Long " & E15 & "X" -> Bitcoin Long 7X | C15: 0.025 | D15: 0.075 | E15: 7 | F15: 1 | G15: =F15 -> 1 | H15: =E15-F15-G15 -> 5 | I15: =F15/E15 -> 0.14285714 | J15: =1-I15 -> 0.85714286 | K15: =G15/F15 -> 1 | L15: =H15/F15 -> 5 | M15: =K15+L15 -> 6
B16: ="Bitcoin Long " & E16 & "X" -> Bitcoin Long 7.5X | C16: 0.025 | D16: 0.075 | E16: 7.5 | F16: 1 | G16: =F16 -> 1 | H16: =E16-F16-G16 -> 5.5 | I16: =F16/E16 -> 0.13333333 | J16: =1-I16 -> 0.86666667 | K16: =G16/F16 -> 1 | L16: =H16/F16 -> 5.5 | M16: =K16+L16 -> 6.5
B17: ="Bitcoin Long " & E17 & "X" -> Bitcoin Long 8X | C17: 0.025 | D17: 0.075 | E17: 8 | F17: 1 | G17: =F17 -> 1 | H17: =E17-F17-G17 -> 6 | I17: =F17/E17 -> 0.125 | J17: =1-I17 -> 0.875 | K17: =G17/F17 -> 1 | L17: =H17/F17 -> 6 | M17: =K17+L17 -> 7
... B41: ="Bitcoin Long " & E41 & "X" -> Bitcoin Long 20X | C41: 0.025 | D41: 0.075 | E41: 20 | F41: 1 | G41: =F41 -> 1 | H41: =E41-F41-G41 -> 18 | I41: =F41/E41 -> 0.05 | J41: =1-I41 -> 0.95 | K41: =G41/F41 -> 1 | L41: =H41/F41 -> 18 | M41: =K41+L41 -> 19

Sheet DC2
C1: Bitcoin Lightning Credit Derivatives
C2: A global, permissionless, decentralized and distributed strategy for ultra-high yields using leveraged Bitcoin growth, liquidity and transaction leasing exposure
C3: Feature | D3: Digital Credit 1.0 | E3: Digital Credit 2.0 | F3: Explainer
C4: Treasury Model | D4: Bitcoin Treasury 1.0, 1.5, 2.0 | E4: Bitcoin Treasury 2.0 | F4: Bitcoin Treasury 2.0 (BT 2.0) is implemented by Bitcoin-native companies with laser focus on bitcoin yield strategies to earn bitcoin revenue instead of through common share dilution.
C5: Capital Provisioning | D5: Centralized and Permissioned | E5: Decentralized and Permissionless | F5: Bitcoiners can permissionlessly provide bitcoin capital to global credit markets and earn true bitcoin yield by participating in the worldwide bitcoin credit market revolution. An example of the power in decentralized and distributed capital means that individuals in the United States can effortlessly provide capital to credit instruments created in Europe.
C6: Capital Risk | D6: Concentrated | E6: Distributed | F6: A distributed approach enables many different bitcoin volatility risk profiles between individuals. Anyone can opt-out providing capital at any time if the bitcoin price underperforms beyond their comfort level however with built-in bitcoin price drawdown liquidation protection only credit obligations are required to maintain the capital position.
C7: Bitcoin Yield Distribution | D7: Concentrated | E7: Distributed | F7: Bitcoin Growth Yield is the Bitcoin Compound Annual Growth Rate from leasing the credit (stable bitcoin) liquidity position. Bitcoin Liquidity Yield is the Lightning fees obtained from leasing the credit (stable bitcoin) and capital (volatile bitcoin) liquidity positions. Bitcoin Transaction Yield is the Lightning fees obtained from routing fees in the credit (stable bitcoin) and capital (volatile bitcoin) liquidity positions Capital Providers receive 100% of the Bitcoin Yield with fiat-denominated fees deducted thus eliminating the need to dilute common shareholders.
B8: Credit Obligation Funding Strategy | D8: Common Shareholders | E8: Capital Providers
C9: Service Revenue | D9: None | E9: Bitcoin-Denominated Service Fees
C10: Service Infrastructure | D10: Traditional Finance | E10: Streaming Finance using the Bitcoin Lightning Network | F10: While there remains a small overhead of credit-based products built using Traditional Finance such as bonds, preferred shares, and loans the majority of the effort is bitcoinizing those Real World Liabilities (RWL) using bitcoin-backed products and services on the Lightning Network with Lightning Stable Channels as a mechanism to balance bitcoin stable to fiat with bitcoin volatile using leverage.
B11: Bitcoin Total Value Locked Growth Rate | D11: 1X = 1 BTC buy adds 1 BTC to TVL | E11: 2X = 1 BTC buy adds 2 BTC to TVL 3X = 1 BTC buy adds 1.5 BTC to TVL | F11: Bitcoin TVL is increased at a faster rate due to the decentralized capital participation model. A BTC & LN Long 2X position commands a double growth rate increase to the purchased bitcoin while a BTC & LN Long 3X position commands a 50% growth rate increase to the purchased bitcoin due to the reduction of capital.

Sheet SUMMARY
B2: Bitcoin Lightning Credit Derivatives | R2: X: @KyleHutch_
B3: A global, permissionless, decentralized and distributed strategy for ultra-high yields using leveraged Bitcoin growth, liquidity and transaction leasing exposure | R3: 46071
B5: A M P L I F Y Y O U R B I T C O I N | C5: O N T H E L I G H T N I N G N E T W O R K | F5: A N N U A L I Z E D B I T C O I N Y I E L D | H5: F I A T G R O W T H | L5: B T C L I Q U I D I T Y | P5: B T C T R A N S A C T I O N
H6: 0.29 | L6: 0.02 | P6: 0.01
B8: C A P I T A L L E V E R A G E | F8: 2 X | H8: 2 . 5 X | J8: 3 X | L8: 3 . 5 X | N8: 4 X | P8: 4 . 5 X | R8: 5 X
B9: L E A S E T O C A P I T A L | D9: S E C U R I T Y | F9: 1 | H9: 1 | J9: 1 | L9: 1 | N9: 1 | P9: 1 | R9: 1
D10: D E B T | F10: 0 | H10: 0.5 | J10: 1 | L10: 1.5 | N10: 2 | P10: 2.5 | R10: 3
B11: B I T C O I N L E A S I N G Y I E L D A N N U A L I Z E D B T C 5 Y E A R A V E R A G E | D11: G R O W T H | F11: ='2X'!I24 -> 0.14401374 | H11: ='2.5X'!I24 -> 0.21602061 | J11: ='3X'!I24 -> 0.28802748 | L11: ='3.5X'!I24 -> 0.36003435 | N11: ='4X'!I24 -> 0.43204122 | P11: ='4.5X'!I24 -> 0.5040481 | R11: ='5X'!I24 -> 0.57605497
D12: L I Q U I D I T Y | F12: ='2X'!I26 -> 0.029931982 | H12: ='2.5X'!I26 -> 0.039931982 | J12: ='3X'!I26 -> 0.049931982 | L12: ='3.5X'!I26 -> 0.059931982 | N12: ='4X'!I26 -> 0.069931982 | P12: ='4.5X'!I26 -> 0.079931982 | R12: ='5X'!I26 -> 0.089931982
D13: T R A N S A C T I O N | F13: ='2X'!I29 -> 0.014965991 | H13: ='2.5X'!I29 -> 0.019965991 | J13: ='3X'!I29 -> 0.024965991 | L13: ='3.5X'!I29 -> 0.029965991 | N13: ='4X'!I29 -> 0.034965991 | P13: ='4.5X'!I29 -> 0.039965991 | R13: ='5X'!I29 -> 0.044965991
D14: G R O S S T O T A L | F14: =SUM(F11:F13) -> 0.18891171 | H14: =SUM(H11:H13) -> 0.27591859 | J14: =SUM(J11:J13) -> 0.36292546 | L14: =SUM(L11:L13) -> 0.44993233 | N14: =SUM(N11:N13) -> 0.5369392 | P14: =SUM(P11:P13) -> 0.62394607 | R14: =SUM(R11:R13) -> 0.71095294
D15: N E T T O T A L | F15: ='2X'!I110 -> 0.11442185 | H15: ='2.5X'!I110 -> 0.18280625 | J15: ='3X'!I110 -> 0.25119066 | L15: ='3.5X'!I110 -> 0.31957506 | N15: ='4X'!I110 -> 0.38795947 | P15: ='4.5X'!I110 -> 0.45634387 | R15: ='5X'!I110 -> 0.52472827
B16: B I T C O I N L E A S I N G Y I E L D A N N U A L I Z E D B T C 10 Y E A R A V E R A G E | D16: G R O W T H | F16: ='2X'!N24 -> 0.092163847 | H16: ='2.5X'!N24 -> 0.13824577 | J16: ='3X'!N24 -> 0.18432769 | L16: ='3.5X'!N24 -> 0.23040962 | N16: ='4X'!N24 -> 0.27649154 | P16: ='4.5X'!N24 -> 0.32257347 | R16: ='5X'!N24 -> 0.36865539
D17: L I Q U I D I T Y | F17: ='2X'!N26 -> 0.026356127 | H17: ='2.5X'!N26 -> 0.036356127 | J17: ='3X'!N26 -> 0.046356127 | L17: ='3.5X'!N26 -> 0.056356127 | N17: ='4X'!N26 -> 0.066356127 | P17: ='4.5X'!N26 -> 0.076356127 | R17: ='5X'!N26 -> 0.086356127
D18: T R A N S A C T I O N | F18: ='2X'!N29 -> 0.013178064 | H18: ='2.5X'!N29 -> 0.018178064 | J18: ='3X'!N29 -> 0.023178064 | L18: ='3.5X'!N29 -> 0.028178064 | N18: ='4X'!N29 -> 0.033178064 | P18: ='4.5X'!N29 -> 0.038178064 | R18: ='5X'!N29 -> 0.043178064
D19: G R O S S T O T A L | F19: =SUM(F16:F18) -> 0.13169804 | H19: =SUM(H16:H18) -> 0.19277996 | J19: =SUM(J16:J18) -> 0.25386189 | L19: =SUM(L16:L18) -> 0.31494381 | N19: =SUM(N16:N18) -> 0.37602573 | P19: =SUM(P16:P18) -> 0.43710766 | R19: =SUM(R16:R18) -> 0.49818958
D20: N E T T O T A L | F20: ='2X'!N110 -> 0.084027083 | H20: ='2.5X'!N110 -> 0.13319127 | J20: ='3X'!N110 -> 0.18235545 | L20: ='3.5X'!N110 -> 0.23151964 | N20: ='4X'!N110 -> 0.28068382 | P20: ='4.5X'!N110 -> 0.32984801 | R20: ='5X'!N110 -> 0.37901219
B21: B I T C O I N L E A S I N G F E E S A N N U A L I Z E D F I A T | D21: S E C U R I T Y | F21: 0.1 | H21: 0.1 | J21: 0.1 | L21: 0.1 | N21: 0.1 | P21: 0.1 | R21: 0.1
D22: S E R V I C E | F22: 0.05 | H22: 0.05 | J22: 0.05 | L22: 0.05 | N22: 0.05 | P22: 0.05 | R22: 0.05
D23: D E B T | F23: 0 | H23: 0.075 | J23: 0.075 | L23: 0.075 | N23: 0.075 | P23: 0.075 | R23: 0.075

Sheet 2X
B2: Bitcoin Lightning Credit Derivatives A permissionless, decentralized and distributed strategy for ultra-high yields using leveraged bitcoin growth and lightning transaction fee exposure | D2: Bitcoin Yield Estimate Variables BiGY = Bitcoin Growth Yield (CAGR) BiLY = Bitcoin Liquidity Yield BiTY = Bitcoin Transaction Yield | G2: Bitcoin Yield Estimate 5 Year Summary SR = Stable Receiver SB = Stable Balancer SP = Stable Provider | K2: Lightning Bank 5 Year Revenue Summary TVL = Total Value Locked
K3: Bitcoin TVL | L3: Measure | M3: BTC | N3: USD
D4: Bitcoin USD Price Start | E4: 100000 | G4: SR USD Comp. | H4: Annual Avg. % | I4: =I43 -> 0.17740036 | K4: =C127 -> 20000 | L4: Annual Avg. | M4: =I128 -> 248.29955 | N4: =M4*$I$15 -> 88700178
D5: Annual Bitcoin Growth Yield % | E5: =SUMMARY!H6 -> 0.29 | G5: SP BiGY BTC | H5: Annual Avg. % | I5: =I67 -> 0.14401374 | K5: =C127 -> 20000 | L5: Cumulative | M5: =I129 -> 1241.4978 | N5: =M5*$I$15 -> 4.4350089e+08
D6: Annual Bitcoin Liquidity Yield % | E6: =SUMMARY!L6 -> 0.02 | G6: SP BiLY BTC | H6: Annual Avg. % | I6: =I80 -> 0.029931982 | K6: =C130 -> 400000 | L6: Annual Avg. | M6: =I131 -> 4965.9911 | N6: =M6*$I$15 -> 1.7740036e+09
D7: Annual Bitcoin Transaction Yield % | E7: =SUMMARY!P6 -> 0.01 | G7: SP BiTY BTC | H7: Annual Avg. % | I7: =I95 -> 0.014965991 | K7: =C130 -> 400000 | L7: Cumulative | M7: =I132 -> 24829.955 | N7: =M7*$I$15 -> 8.8700178e+09
D8: Stable Receiver Security Annual USD % | E8: =SUMMARY!F21 -> 0.1 | G8: SP BiLY SR BTC | H8: Annual Avg. % | I8: =-I35 -> -0.049659911 | K8: =C133 -> 1000000 | L8: Annual Avg. | M8: =I134 -> 12414.978 | N8: =M8*$I$15 -> 4435008905
D9: Stable Balancer Security Annual USD % | E9: =SUMMARY!F22 -> 0.05 | G9: SP BiLY SB BTC | H9: Annual Avg. % | I9: =-I51 -> -0.024829955 | K9: =C133 -> 1000000 | L9: Cumulative | M9: =I135 -> 62074.889 | N9: =M9*$I$15 -> 2.2175045e+10
D10: Stable Balancer Debt Annual USD % | E10: =SUMMARY!F23 -> 0 | G10: SP Total BTC | H10: Annual Avg. % | I10: =I110 -> 0.11442185
D11: Stable Provider Debt-to-Value % | E11: =SUMMARY!F10 -> 0
B13: Yield Estimate Calculator | C13: Unit of Account | D13: Measure | E13: Year 1 | F13: Year 2 | G13: Year 3 | H13: Year 4 | I13: Year 5 | J13: Year 6 | K13: Year 7 | L13: Year 8 | M13: Year 9 | N13: Year 10
B15: Bitcoin | C15: USD | D15: Price | E15: =($E$4 * $E$5) + $E$4 -> 129000 | F15: =(E15 * $E$5) + E15 -> 166410 | G15: =(F15 * $E$5) + F15 -> 214668.9 | H15: =(G15 * $E$5) + G15 -> 276922.88 | I15: =(H15 * $E$5) + H15 -> 357230.52 | J15: =(I15 * $E$5) + I15 -> 460827.37 | K15: =(J15 * $E$5) + J15 -> 594467.3 | L15: =(K15 * $E$5) + K15 -> 766862.82 | M15: =(L15 * $E$5) + L15 -> 989253.04 | N15: =(M15 * $E$5) + M15 -> 1276136.4
D16: Marketcap | E16: =E15*21000000 -> 2709000000000 | F16: =F15*21000000 -> 3494610000000 | G16: =G15*21000000 -> 4508046900000 | H16: =H15*21000000 -> 5815380501000 | I16: =I15*21000000 -> 7.5018408e+12 | J16: =J15*21000000 -> 9.6773747e+12 | K16: =K15*21000000 -> 1.2483813e+13 | L16: =L15*21000000 -> 1.6104119e+13 | ... N16: =N15*21000000 -> 2.6798865e+13
B17: Bitcoin Growth Yield (BiGY) | C17: BTC | D17: Stable Security Cumulative % | E17: =(E15-$E4)/E15 -> 0.2248062 | F17: =(F15-$E4)/F15 -> 0.39907457 | G17: =(G15-$E4)/G15 -> 0.53416634 | H17: =(H15-$E4)/H15 -> 0.63888863 | I17: =(I15-$E4)/I15 -> 0.72006871 | J17: =(J15-$E4)/J15 -> 0.782999 | K17: =(K15-$E4)/K15 -> 0.83178217 | L17: =(L15-$E4)/L15 -> 0.86959858 | ... N17: =(N15-$E4)/N15 -> 0.92163847
D18: Stable Security Remaining % | E18: =1-E17 -> 0.7751938 | F18: =1-F17 -> 0.60092543 | G18: =1-G17 -> 0.46583366 | H18: =1-H17 -> 0.36111137 | I18: =1-I17 -> 0.27993129 | J18: =1-J17 -> 0.217001 | K18: =1-K17 -> 0.16821783 | L18: =1-L17 -> 0.13040142 | ... N18: =1-N17 -> 0.078361528
D19: Stable Security Annual % | E19: =E17 -> 0.2248062 | F19: =F17-E17 -> 0.17426837 | G19: =G17-F17 -> 0.13509176 | H19: =H17-G17 -> 0.1047223 | I19: =I17-H17 -> 0.081180075 | J19: =J17-I17 -> 0.06293029 | K19: =K17-J17 -> 0.048783171 | L19: =L17-K17 -> 0.037816412 | M19: =M17-L17 -> 0.029315048 | N19: =N17-M17 -> 0.022724843
D20: Stable Security Annual Average % | I20: =AVERAGE(E19:I19) -> 0.14401374 | N20: =AVERAGE(E19:N19) -> 0.092163847
D21: Stable Debt Annual % | E21: =$E$11*E19 -> 0 | F21: =$E$11*F19 -> 0 | G21: =$E$11*G19 -> 0 | H21: =$E$11*H19 -> 0 | I21: =$E$11*I19 -> 0 | J21: =$E$11*J19 -> 0 | K21: =$E$11*K19 -> 0 | L21: =$E$11*L19 -> 0 | ... N21: =$E$11*N19 -> 0
D22: Stable Debt Annual Avg. % | I22: =AVERAGE(E21:I21) -> 0 | N22: =AVERAGE(E21:N21) -> 0
D23: Total Annual % | E23: =E19+E21 -> 0.2248062 | F23: =F19+F21 -> 0.17426837 | G23: =G19+G21 -> 0.13509176 | H23: =H19+H21 -> 0.1047223 | I23: =I19+I21 -> 0.081180075 | J23: =J19+J21 -> 0.06293029 | K23: =K19+K21 -> 0.048783171 | L23: =L19+L21 -> 0.037816412 | ... N23: =N19+N21 -> 0.022724843
D24: Total Annual Average % | I24: =AVERAGE(E23:I23) -> 0.14401374 | N24: =AVERAGE(E23:N23) -> 0.092163847
B25: Bitcoin Liquidity Yield (BiLY) | C25: BTC | D25: Annual % | E25: =((1+$E$11)*$E$6)+($E$6*E18) -> 0.035503876 | F25: =((1+$E$11)*$E$6)+($E$6*F18) -> 0.032018509 | G25: =((1+$E$11)*$E$6)+($E$6*G18) -> 0.029316673 | H25: =((1+$E$11)*$E$6)+($E$6*H18) -> 0.027222227 | I25: =((1+$E$11)*$E$6)+($E$6*I18) -> 0.025598626 | J25: =((1+$E$11)*$E$6)+($E$6*J18) -> 0.02434002 | K25: =((1+$E$11)*$E$6)+($E$6*K18) -> 0.023364357 | L25: =((1+$E$11)*$E$6)+($E$6*L18) -> 0.022608028 | ... N25: =((1+$E$11)*$E$6)+($E$6*N18) -> 0.021567231
D26: Annual Average % | I26: =AVERAGE(E25:I25) -> 0.029931982 | N26: =AVERAGE(E25:N25) -> 0.026356127
D27: Cumulative % | E27: =E25 -> 0.035503876 | F27: =E27+F25 -> 0.067522384 | G27: =F27+G25 -> 0.096839058 | H27: =G27+H25 -> 0.12406129 | I27: =H27+I25 -> 0.14965991 | J27: =I27+J25 -> 0.17399993 | K27: =J27+K25 -> 0.19736429 | L27: =K27+L25 -> 0.21997232 | M27: =L27+M25 -> 0.24199404 | N27: =M27+N25 -> 0.26356127
B28: Bitcoin Transaction Yield (BiTY) | C28: BTC | D28: Annual % | E28: =((1+$E$11)*$E$7)+($E$7*E18) -> 0.017751938 | F28: =((1+$E$11)*$E$7)+($E$7*F18) -> 0.016009254 | G28: =((1+$E$11)*$E$7)+($E$7*G18) -> 0.014658337 | H28: =((1+$E$11)*$E$7)+($E$7*H18) -> 0.013611114 | I28: =((1+$E$11)*$E$7)+($E$7*I18) -> 0.012799313 | J28: =((1+$E$11)*$E$7)+($E$7*J18) -> 0.01217001 | K28: =((1+$E$11)*$E$7)+($E$7*K18) -> 0.011682178 | L28: =((1+$E$11)*$E$7)+($E$7*L18) -> 0.011304014 | ... N28: =((1+$E$11)*$E$7)+($E$7*N18) -> 0.010783615
D29: Annual Average % | I29: =AVERAGE(E28:I28) -> 0.014965991 | N29: =AVERAGE(E28:N28) -> 0.013178064
D30: Cumulative % | E30: =E28 -> 0.017751938 | F30: =E30+F28 -> 0.033761192 | G30: =F30+G28 -> 0.048419529 | H30: =G30+H28 -> 0.062030643 | I30: =H30+I28 -> 0.074829955 | J30: =I30+J28 -> 0.086999965 | K30: =J30+K28 -> 0.098682144 | L30: =K30+L28 -> 0.10998616 | M30: =L30+M28 -> 0.12099702 | N30: =M30+N28 -> 0.13178064
B32: Stable Receiver / Fiat Lender | C32: Test Case | D32: ="10 BTC / "&TEXT($E$4*10, "$###0.00,,")&"M USD" -> 10 BTC / $1.00M USD | E32: Year 1 | F32: Year 2 | G32: Year 3 | H32: Year 4 | I32: Year 5 | J32: Year 6 | K32: Year 7 | L32: Year 8 | M32: Year 9 | N32: Year 10
B34: Bitcoin Liquidity Yield (BiLY) | C34: BTC | D34: Total Annual % | E34: =E39*$E$4/E$15 -> 0.07751938 | F34: =F39*$E$4/F$15 -> 0.060092543 | G34: =G39*$E$4/G$15 -> 0.046583366 | H34: =H39*$E$4/H$15 -> 0.036111137 | I34: =I39*$E$4/I$15 -> 0.027993129 | J34: =J39*$E$4/J$15 -> 0.0217001 | K34: =K39*$E$4/K$15 -> 0.016821783 | L34: =L39*$E$4/L$15 -> 0.013040142 | ... N34: =N39*$E$4/N$15 -> 0.0078361528
D35: Total Annual Average % | I35: =AVERAGE(E34:I34) -> 0.049659911 | N35: =AVERAGE(E34:N34) -> 0.031780637
D36: Cumulative % | E36: =E$17*(E34/E$19) -> 0.07751938 | F36: =F$17*(F34/F$19) -> 0.13761192 | G36: =G$17*(G34/G$19) -> 0.18419529 | H36: =H$17*(H34/H$19) -> 0.22030643 | I36: =I$17*(I34/I$19) -> 0.24829955 | J36: =J$17*(J34/J$19) -> 0.26999965 | K36: =K$17*(K34/K$19) -> 0.28682144 | L36: =L$17*(L34/L$19) -> 0.29986158 | ... N36: =N$17*(N34/N$19) -> 0.31780637
D37: Test Case Annual | E37: =10*E34 -> 0.7751938 | F37: =10*F34 -> 0.60092543 | G37: =10*G34 -> 0.46583366 | H37: =10*H34 -> 0.36111137 | I37: =10*I34 -> 0.27993129 | J37: =10*J34 -> 0.217001 | K37: =10*K34 -> 0.16821783 | L37: =10*L34 -> 0.13040142 | ... N37: =10*N34 -> 0.078361528
D38: Test Case Cumulative | E38: =10*E36 -> 0.7751938 | F38: =10*F36 -> 1.3761192 | G38: =10*G36 -> 1.8419529 | H38: =10*H36 -> 2.2030643 | I38: =10*I36 -> 2.4829955 | J38: =10*J36 -> 2.6999965 | K38: =10*K36 -> 2.8682144 | L38: =10*L36 -> 2.9986158 | ... N38: =10*N36 -> 3.1780637
C39: USD Simple | D39: Annual % | E39: =E8 -> 0.1 | F39: =E39 -> 0.1 | G39: =F39 -> 0.1 | H39: =G39 -> 0.1 | I39: =H39 -> 0.1 | J39: =I39 -> 0.1 | K39: =J39 -> 0.1 | L39: =K39 -> 0.1 | M39: =L39 -> 0.1 | N39: =M39 -> 0.1
D40: Test Case Annual | E40: =E37*E$15 -> 100000 | F40: =F37*F$15 -> 100000 | G40: =G37*G$15 -> 100000 | H40: =H37*H$15 -> 100000 | I40: =I37*I$15 -> 100000 | J40: =J37*J$15 -> 100000 | K40: =K37*K$15 -> 100000 | L40: =L37*L$15 -> 100000 | ... N40: =N37*N$15 -> 100000
D41: Test Case Cumulative | E41: =E40 -> 100000 | F41: =E41+F40 -> 200000 | G41: =F41+G40 -> 300000 | H41: =G41+H40 -> 400000 | I41: =H41+I40 -> 500000 | J41: =I41+J40 -> 600000 | K41: =J41+K40 -> 700000 | L41: =K41+L40 -> 800000 | M41: =L41+M40 -> 900000 | N41: =M41+N40 -> 1000000
C42: USD Compounded | D42: Annual % | E42: =E36*E$15/$E$4 -> 0.1 | F42: =F36*F$15/$E$4-E42 -> 0.129 | G42: =G36*G$15/$E$4-F42-E42 -> 0.16641 | H42: =H36*H$15/$E$4-G42-F42-E42 -> 0.2146689 | I42: =I36*I$15/$E$4-H42-G42-F42-E42 -> 0.27692288 | J42: =J36*J$15/$E$4-I42-H42-G42-F42-E42 -> 0.35723052 | K42: =K36*K$15/$E$4-J42-I42-H42-G42-F42-E42 -> 0.46082737 | L42: =L36*L$15/$E$4-K42-J42-I42-H42-G42-F42-E42 -> 0.5944673 | M42: =M36*M$15/$E$4-L42-K42-J42-I42-H42-G42-F42-E42 -> 0.76686282 | N42: =N36*N$15/$E$4-M42-L42-K42-J42-I42-H42-G42-F42-E42 -> 0.98925304
D43: Annual Average % | I43: =AVERAGE(E42:I42) -> 0.17740036 | N43: =AVERAGE(E42:N42) -> 0.40556428
D44: Test Case Annual | E44: =E46 -> 100000 | F44: =F46-E46 -> 129000 | G44: =G46-F46 -> 166410 | H44: =H46-G46 -> 214668.9 | I44: =I46-H46 -> 276922.88 | J44: =J46-I46 -> 357230.52 | K44: =K46-J46 -> 460827.37 | L44: =L46-K46 -> 594467.3 | M44: =M46-L46 -> 766862.82 | N44: =N46-M46 -> 989253.04
D45: Test Case Annual Average | I45: =AVERAGE(E44:I44) -> 177400.36 | N45: =AVERAGE(E44:N44) -> 405564.28
D46: Test Case Cumulative | E46: =E38*E$15 -> 100000 | F46: =F38*F$15 -> 229000 | G46: =G38*G$15 -> 395410 | H46: =H38*H$15 -> 610078.9 | I46: =I38*I$15 -> 887001.78 | J46: =J38*J$15 -> 1244232.3 | K46: =K38*K$15 -> 1705059.7 | L46: =L38*L$15 -> 2299527 | ... N46: =N38*N$15 -> 4055642.8
B48: Stable Balancer / Lightning Service Provider | C48: Test Case | D48: ="10 BTC / "&TEXT($E$4*10, "$###0.00,,")&"M USD" -> 10 BTC / $1.00M USD | E48: Year 1 | F48: Year 2 | G48: Year 3 | H48: Year 4 | I48: Year 5 | J48: Year 6 | K48: Year 7 | L48: Year 8 | M48: Year 9 | N48: Year 10
B50: Bitcoin Liquidity Yield (BiLY) | C50: BTC | D50: Annual % | E50: =E55*$E$4/E$15 -> 0.03875969 | F50: =F55*$E$4/F$15 -> 0.030046271 | G50: =G55*$E$4/G$15 -> 0.023291683 | H50: =H55*$E$4/H$15 -> 0.018055568 | I50: =I55*$E$4/I$15 -> 0.013996565 | J50: =J55*$E$4/J$15 -> 0.01085005 | K50: =K55*$E$4/K$15 -> 0.0084108915 | L50: =L55*$E$4/L$15 -> 0.006520071 | ... N50: =N55*$E$4/N$15 -> 0.0039180764
D51: Annual Average % | I51: =AVERAGE(E50:I50) -> 0.024829955 | N51: =AVERAGE(E50:N50) -> 0.015890318
D52: Cumulative % | E52: =E$17*(E50/E$19) -> 0.03875969 | F52: =F$17*(F50/F$19) -> 0.068805961 | G52: =G$17*(G50/G$19) -> 0.092097644 | H52: =H$17*(H50/H$19) -> 0.11015321 | I52: =I$17*(I50/I$19) -> 0.12414978 | J52: =J$17*(J50/J$19) -> 0.13499983 | K52: =K$17*(K50/K$19) -> 0.14341072 | L52: =L$17*(L50/L$19) -> 0.14993079 | ... N52: =N$17*(N50/N$19) -> 0.15890318
D53: Test Case Annual | E53: =10*E50 -> 0.3875969 | F53: =10*F50 -> 0.30046271 | G53: =10*G50 -> 0.23291683 | H53: =10*H50 -> 0.18055568 | I53: =10*I50 -> 0.13996565 | J53: =10*J50 -> 0.1085005 | K53: =10*K50 -> 0.084108915 | L53: =10*L50 -> 0.06520071 | ... N53: =10*N50 -> 0.039180764
D54: Test Case Cumulative | E54: =10*E52 -> 0.3875969 | F54: =10*F52 -> 0.68805961 | G54: =10*G52 -> 0.92097644 | H54: =10*H52 -> 1.1015321 | I54: =10*I52 -> 1.2414978 | J54: =10*J52 -> 1.3499983 | K54: =10*K52 -> 1.4341072 | L54: =10*L52 -> 1.4993079 | ... N54: =10*N52 -> 1.5890318
C55: USD Simple | D55: Annual % | E55: =$E9+($E$10*$E$11) -> 0.05 | F55: =$E9+($E$10*$E$11) -> 0.05 | G55: =$E9+($E$10*$E$11) -> 0.05 | H55: =$E9+($E$10*$E$11) -> 0.05 | I55: =$E9+($E$10*$E$11) -> 0.05 | J55: =$E9+($E$10*$E$11) -> 0.05 | K55: =$E9+($E$10*$E$11) -> 0.05 | L55: =$E9+($E$10*$E$11) -> 0.05 | ... N55: =$E9+($E$10*$E$11) -> 0.05
D56: Test Case Annual | E56: =E53*E$15 -> 50000 | F56: =F53*F$15 -> 50000 | G56: =G53*G$15 -> 50000 | H56: =H53*H$15 -> 50000 | I56: =I53*I$15 -> 50000 | J56: =J53*J$15 -> 50000 | K56: =K53*K$15 -> 50000 | L56: =L53*L$15 -> 50000 | ... N56: =N53*N$15 -> 50000
D57: Test Case Cumulative | E57: =E56 -> 50000 | F57: =E57+F56 -> 100000 | G57: =F57+G56 -> 150000 | H57: =G57+H56 -> 200000 | I57: =H57+I56 -> 250000 | J57: =I57+J56 -> 300000 | K57: =J57+K56 -> 350000 | L57: =K57+L56 -> 400000 | M57: =L57+M56 -> 450000 | N57: =M57+N56 -> 500000
C58: USD Compounded | D58: Annual % | E58: =E52*E$15/$E$4 -> 0.05 | F58: =F52*F$15/$E$4-E58 -> 0.0645 | G58: =G52*G$15/$E$4-F58-E58 -> 0.083205 | H58: =H52*H$15/$E$4-G58-F58-E58 -> 0.10733445 | I58: =I52*I$15/$E$4-H58-G58-F58-E58 -> 0.13846144 | J58: =J52*J$15/$E$4-I58-H58-G58-F58-E58 -> 0.17861526 | K58: =K52*K$15/$E$4-J58-I58-H58-G58-F58-E58 -> 0.23041368 | L58: =L52*L$15/$E$4-K58-J58-I58-H58-G58-F58-E58 -> 0.29723365 | M58: =M52*M$15/$E$4-L58-K58-J58-I58-H58-G58-F58-E58 -> 0.38343141 | N58: =N52*N$15/$E$4-M58-L58-K58-J58-I58-H58-G58-F58-E58 -> 0.49462652
D59: Annual Average % | I59: =AVERAGE(E58:I58) -> 0.088700178 | N59: =AVERAGE(E58:N58) -> 0.20278214
D60: Test Case Annual | E60: =E62 -> 50000 | F60: =F62-E62 -> 64500 | G60: =G62-F62 -> 83205 | H60: =H62-G62 -> 107334.45 | I60: =I62-H62 -> 138461.44 | J60: =J62-I62 -> 178615.26 | K60: =K62-J62 -> 230413.68 | L60: =L62-K62 -> 297233.65 | M60: =M62-L62 -> 383431.41 | N60: =N62-M62 -> 494626.52
D61: Test Case Annual Average | I61: =AVERAGE(E60:I60) -> 88700.178 | N61: =AVERAGE(E60:N60) -> 202782.14
D62: Test Case Cumulative | E62: =E54*E$15 -> 50000 | F62: =F54*F$15 -> 114500 | G62: =G54*G$15 -> 197705 | H62: =H54*H$15 -> 305039.45 | I62: =I54*I$15 -> 443500.89 | J62: =J54*J$15 -> 622116.15 | K62: =K54*K$15 -> 852529.83 | L62: =L54*L$15 -> 1149763.5 | ... N62: =N54*N$15 -> 2027821.4
B64: Stable Provider / Bitcoin Borrower | C64: Test Case | D64: ="10 BTC / "&TEXT($E$4*10, "$###0.00,,")&"M USD" -> 10 BTC / $1.00M USD | E64: Year 1 | F64: Year 2 | G64: Year 3 | H64: Year 4 | I64: Year 5 | J64: Year 6 | K64: Year 7 | L64: Year 8 | M64: Year 9 | N64: Year 10
B66: Bitcoin Growth Yield (BiGY) | C66: BTC | D66: Total Annual % | E66: =E$23 -> 0.2248062 | F66: =F$23 -> 0.17426837 | G66: =G$23 -> 0.13509176 | H66: =H$23 -> 0.1047223 | I66: =I$23 -> 0.081180075 | J66: =J$23 -> 0.06293029 | K66: =K$23 -> 0.048783171 | L66: =L$23 -> 0.037816412 | ... N66: =N$23 -> 0.022724843
D67: Total Annual Average % | I67: =AVERAGE(E66:I66) -> 0.14401374 | N67: =AVERAGE(E66:N66) -> 0.092163847
D68: Cumulative % | E68: =E$17*(E66/E$19) -> 0.2248062 | F68: =F$17*(F66/F$19) -> 0.39907457 | G68: =G$17*(G66/G$19) -> 0.53416634 | H68: =H$17*(H66/H$19) -> 0.63888863 | I68: =I$17*(I66/I$19) -> 0.72006871 | J68: =J$17*(J66/J$19) -> 0.782999 | K68: =K$17*(K66/K$19) -> 0.83178217 | L68: =L$17*(L66/L$19) -> 0.86959858 | ... N68: =N$17*(N66/N$19) -> 0.92163847
D69: Test Case Annual | E69: =10*E66 -> 2.248062 | F69: =10*F66 -> 1.7426837 | G69: =10*G66 -> 1.3509176 | H69: =10*H66 -> 1.047223 | I69: =10*I66 -> 0.81180075 | J69: =10*J66 -> 0.6293029 | K69: =10*K66 -> 0.48783171 | L69: =10*L66 -> 0.37816412 | ... N69: =10*N66 -> 0.22724843
D70: Test Case Cumulative | E70: =10*E68 -> 2.248062 | F70: =10*F68 -> 3.9907457 | G70: =10*G68 -> 5.3416634 | H70: =10*H68 -> 6.3888863 | I70: =10*I68 -> 7.2006871 | J70: =10*J68 -> 7.82999 | K70: =10*K68 -> 8.3178217 | L70: =10*L68 -> 8.6959858 | ... N70: =10*N68 -> 9.2163847
C71: USD Simple | D71: Annual % | E71: =E66*E$15/$E$4 -> 0.29 | F71: =F66*F$15/$E$4 -> 0.29 | G71: =G66*G$15/$E$4 -> 0.29 | H71: =H66*H$15/$E$4 -> 0.29 | I71: =I66*I$15/$E$4 -> 0.29 | J71: =J66*J$15/$E$4 -> 0.29 | K71: =K66*K$15/$E$4 -> 0.29 | L71: =L66*L$15/$E$4 -> 0.29 | ... N71: =N66*N$15/$E$4 -> 0.29
D72: Test Case Annual | E72: =E69*E$15 -> 290000 | F72: =F69*F$15 -> 290000 | G72: =G69*G$15 -> 290000 | H72: =H69*H$15 -> 290000 | I72: =I69*I$15 -> 290000 | J72: =J69*J$15 -> 290000 | K72: =K69*K$15 -> 290000 | L72: =L69*L$15 -> 290000 | ... N72: =N69*N$15 -> 290000
D73: Test Case Cumulative | E73: =E72 -> 290000 | F73: =E73+F72 -> 580000 | G73: =F73+G72 -> 870000 | H73: =G73+H72 -> 1160000 | I73: =H73+I72 -> 1450000 | J73: =I73+J72 -> 1740000 | K73: =J73+K72 -> 2030000 | L73: =K73+L72 -> 2320000 | M73: =L73+M72 -> 2610000 | N73: =M73+N72 -> 2900000
C74: USD Compounded | D74: Annual % | E74: =E68*E$15/$E$4 -> 0.29 | F74: =F68*F$15/$E$4-E74 -> 0.3741 | G74: =G68*G$15/$E$4-F74-E74 -> 0.482589 | H74: =H68*H$15/$E$4-G74-F74-E74 -> 0.62253981 | I74: =I68*I$15/$E$4-H74-G74-F74-E74 -> 0.80307635 | J74: =J68*J$15/$E$4-I74-H74-G74-F74-E74 -> 1.0359685 | K74: =K68*K$15/$E$4-J74-I74-H74-G74-F74-E74 -> 1.3363994 | L74: =L68*L$15/$E$4-K74-J74-I74-H74-G74-F74-E74 -> 1.7239552 | M74: =M68*M$15/$E$4-L74-K74-J74-I74-H74-G74-F74-E74 -> 2.2239022 | N74: =N68*N$15/$E$4-M74-L74-K74-J74-I74-H74-G74-F74-E74 -> 2.8688338
D75: Annual Average % | I75: =AVERAGE(E74:I74) -> 0.51446103 | N75: =AVERAGE(E74:N74) -> 1.1761364
D76: Test Case Annual | E76: =E78 -> 290000 | F76: =F78-E78 -> 374100 | G76: =G78-F78 -> 482589 | H76: =H78-G78 -> 622539.81 | I76: =I78-H78 -> 803076.35 | J76: =J78-I78 -> 1035968.5 | K76: =K78-J78 -> 1336399.4 | L76: =L78-K78 -> 1723955.2 | M76: =M78-L78 -> 2223902.2 | N76: =N78-M78 -> 2868833.8
D77: Test Case Annual Average | I77: =AVERAGE(E76:I76) -> 514461.03 | N77: =AVERAGE(E76:N76) -> 1176136.4
D78: Test Case Cumulative | E78: =E70*E$15 -> 290000 | F78: =F70*F$15 -> 664100 | G78: =G70*G$15 -> 1146689 | H78: =H70*H$15 -> 1769228.8 | I78: =I70*I$15 -> 2572305.2 | J78: =J70*J$15 -> 3608273.7 | K78: =K70*K$15 -> 4944673 | L78: =L70*L$15 -> 6668628.2 | ... N78: =N70*N$15 -> 11761364
B79: Bitcoin Liquidity Yield (BiLY) | C79: BTC | D79: Annual % | E79: =E$25 -> 0.035503876 | F79: =F$25 -> 0.032018509 | G79: =G$25 -> 0.029316673 | H79: =H$25 -> 0.027222227 | I79: =I$25 -> 0.025598626 | J79: =J$25 -> 0.02434002 | K79: =K$25 -> 0.023364357 | L79: =L$25 -> 0.022608028 | ... N79: =N$25 -> 0.021567231
D80: Annual Average % | I80: =AVERAGE(E79:I79) -> 0.029931982 | N80: =AVERAGE(E79:N79) -> 0.026356127
D81: Cumulative % | E81: =E$27 -> 0.035503876 | F81: =F$27 -> 0.067522384 | G81: =G$27 -> 0.096839058 | H81: =H$27 -> 0.12406129 | I81: =I$27 -> 0.14965991 | J81: =J$27 -> 0.17399993 | K81: =K$27 -> 0.19736429 | L81: =L$27 -> 0.21997232 | ... N81: =N$27 -> 0.26356127
D82: Test Case Annual | E82: =10*E79 -> 0.35503876 | F82: =10*F79 -> 0.32018509 | G82: =10*G79 -> 0.29316673 | H82: =10*H79 -> 0.27222227 | I82: =10*I79 -> 0.25598626 | J82: =10*J79 -> 0.2434002 | K82: =10*K79 -> 0.23364357 | L82: =10*L79 -> 0.22608028 | ... N82: =10*N79 -> 0.21567231
D83: Test Case Cumulative | E83: =10*E81 -> 0.35503876 | F83: =10*F81 -> 0.67522384 | G83: =10*G81 -> 0.96839058 | H83: =10*H81 -> 1.2406129 | I83: =10*I81 -> 1.4965991 | J83: =10*J81 -> 1.7399993 | K83: =10*K81 -> 1.9736429 | L83: =10*L81 -> 2.1997232 | ... N83: =10*N81 -> 2.6356127
C84: USD Simple | D84: Annual % | E84: =E79*E$15/$E$4 -> 0.0458 | F84: =F79*F$15/$E$4 -> 0.053282 | G84: =G79*G$15/$E$4 -> 0.06293378 | H84: =H79*H$15/$E$4 -> 0.075384576 | I84: =I79*I$15/$E$4 -> 0.091446103 | J84: =J79*J$15/$E$4 -> 0.11216547 | K84: =K79*K$15/$E$4 -> 0.13889346 | L84: =L79*L$15/$E$4 -> 0.17337256 | ... N84: =N79*N$15/$E$4 -> 0.27522728
D85: Annual Average % | I85: =AVERAGE(E84:I84) -> 0.065769292 | N85: =AVERAGE(E84:N84) -> 0.12463558
D86: Test Case Annual | E86: =E82*E$15 -> 45800 | F86: =F82*F$15 -> 53282 | G86: =G82*G$15 -> 62933.78 | H86: =H82*H$15 -> 75384.576 | I86: =I82*I$15 -> 91446.103 | J86: =J82*J$15 -> 112165.47 | K86: =K82*K$15 -> 138893.46 | L86: =L82*L$15 -> 173372.56 | ... N86: =N82*N$15 -> 275227.28
D87: Test Case Annual Average | I87: =AVERAGE(E86:I86) -> 65769.292 | N87: =AVERAGE(E86:N86) -> 124635.58
D88: Test Case Cumulative | E88: =E86 -> 45800 | F88: =E88+F86 -> 99082 | G88: =F88+G86 -> 162015.78 | H88: =G88+H86 -> 237400.36 | I88: =H88+I86 -> 328846.46 | J88: =I88+J86 -> 441011.93 | K88: =J88+K86 -> 579905.39 | L88: =K88+L86 -> 753277.96 | M88: =L88+M86 -> 971128.56 | N88: =M88+N86 -> 1246355.8
C89: USD Compounded | D89: Annual % | E89: =E81*E$15/$E$4 -> 0.0458 | F89: =F81*F$15/$E$4-E89 -> 0.066564 | G89: =G81*G$15/$E$4-F89-E89 -> 0.09551934 | H89: =H81*H$15/$E$4-G89-F89-E89 -> 0.13567074 | I89: =I81*I$15/$E$4-H89-G89-F89-E89 -> 0.19107679 | J89: =J81*J$15/$E$4-I89-H89-G89-F89-E89 -> 0.26720843 | K89: =K81*K$15/$E$4-J89-I89-H89-G89-F89-E89 -> 0.37142686 | L89: =L81*L$15/$E$4-K89-J89-I89-H89-G89-F89-E89 -> 0.51361975 | M89: =M81*M$15/$E$4-L89-K89-J89-I89-H89-G89-F89-E89 -> 0.70704752 | N89: =N81*N$15/$E$4-M89-L89-K89-J89-I89-H89-G89-F89-E89 -> 0.96946798
D90: Annual Average % | I90: =AVERAGE(E89:I89) -> 0.10692617 | N90: =AVERAGE(E89:N89) -> 0.33634014
D91: Test Case Annual | E91: =E93 -> 45800 | F91: =F93-E93 -> 66564 | G91: =G93-F93 -> 95519.34 | H91: =H93-G93 -> 135670.74 | I91: =I93-H93 -> 191076.79 | J91: =J93-I93 -> 267208.43 | K91: =K93-J93 -> 371426.86 | L91: =L93-K93 -> 513619.75 | M91: =M93-L93 -> 707047.52 | N91: =N93-M93 -> 969467.98
D92: Test Case Annual Average | I92: =AVERAGE(E91:I91) -> 106926.17 | N92: =AVERAGE(E91:N91) -> 336340.14
D93: Test Case Cumulative | E93: =E83*E$15 -> 45800 | F93: =F83*F$15 -> 112364 | G93: =G83*G$15 -> 207883.34 | H93: =H83*H$15 -> 343554.08 | I93: =I83*I$15 -> 534630.87 | J93: =J83*J$15 -> 801839.3 | K93: =K83*K$15 -> 1173266.2 | L93: =L83*L$15 -> 1686885.9 | ... N93: =N83*N$15 -> 3363401.4
B94: Bitcoin Transaction Yield (BiTY) | C94: BTC | D94: Annual % | E94: =E$28 -> 0.017751938 | F94: =F$28 -> 0.016009254 | G94: =G$28 -> 0.014658337 | H94: =H$28 -> 0.013611114 | I94: =I$28 -> 0.012799313 | J94: =J$28 -> 0.01217001 | K94: =K$28 -> 0.011682178 | L94: =L$28 -> 0.011304014 | ... N94: =N$28 -> 0.010783615
D95: Annual Average % | I95: =AVERAGE(E94:I94) -> 0.014965991 | N95: =AVERAGE(E94:N94) -> 0.013178064
D96: Cumulative % | E96: =E$30 -> 0.017751938 | F96: =F$30 -> 0.033761192 | G96: =G$30 -> 0.048419529 | H96: =H$30 -> 0.062030643 | I96: =I$30 -> 0.074829955 | J96: =J$30 -> 0.086999965 | K96: =K$30 -> 0.098682144 | L96: =L$30 -> 0.10998616 | ... N96: =N$30 -> 0.13178064
D97: Test Case Annual | E97: =10*E94 -> 0.17751938 | F97: =10*F94 -> 0.16009254 | G97: =10*G94 -> 0.14658337 | H97: =10*H94 -> 0.13611114 | I97: =10*I94 -> 0.12799313 | J97: =10*J94 -> 0.1217001 | K97: =10*K94 -> 0.11682178 | L97: =10*L94 -> 0.11304014 | ... N97: =10*N94 -> 0.10783615
D98: Test Case Cumulative | E98: =10*E96 -> 0.17751938 | F98: =10*F96 -> 0.33761192 | G98: =10*G96 -> 0.48419529 | H98: =10*H96 -> 0.62030643 | I98: =10*I96 -> 0.74829955 | J98: =10*J96 -> 0.86999965 | K98: =10*K96 -> 0.98682144 | L98: =10*L96 -> 1.0998616 | ... N98: =10*N96 -> 1.3178064
C99: USD Simple | D99: Annual % | E99: =E94*E$15/$E$4 -> 0.0229 | F99: =F94*F$15/$E$4 -> 0.026641 | G99: =G94*G$15/$E$4 -> 0.03146689 | H99: =H94*H$15/$E$4 -> 0.037692288 | I99: =I94*I$15/$E$4 -> 0.045723052 | J99: =J94*J$15/$E$4 -> 0.056082737 | K99: =K94*K$15/$E$4 -> 0.06944673 | L99: =L94*L$15/$E$4 -> 0.086686282 | ... N99: =N94*N$15/$E$4 -> 0.13761364
D100: Annual Average % | I100: =AVERAGE(E99:I99) -> 0.032884646 | N100: =AVERAGE(E99:N99) -> 0.062317792
D101: Test Case Annual | E101: =E97*E$15 -> 22900 | F101: =F97*F$15 -> 26641 | G101: =G97*G$15 -> 31466.89 | H101: =H97*H$15 -> 37692.288 | I101: =I97*I$15 -> 45723.052 | J101: =J97*J$15 -> 56082.737 | K101: =K97*K$15 -> 69446.73 | L101: =L97*L$15 -> 86686.282 | ... N101: =N97*N$15 -> 137613.64
D102: Test Case Annual Average | I102: =AVERAGE(E101:I101) -> 32884.646 | N102: =AVERAGE(E101:N101) -> 62317.792
D103: Test Case Cumulative | E103: =E101 -> 22900 | F103: =E103+F101 -> 49541 | G103: =F103+G101 -> 81007.89 | H103: =G103+H101 -> 118700.18 | I103: =H103+I101 -> 164423.23 | J103: =I103+J101 -> 220505.97 | K103: =J103+K101 -> 289952.7 | L103: =K103+L101 -> 376638.98 | M103: =L103+M101 -> 485564.28 | N103: =M103+N101 -> 623177.92
C104: USD Compounded | D104: Annual % | E104: =E96*E$15/$E$4 -> 0.0229 | F104: =F96*F$15/$E$4-E104 -> 0.033282 | G104: =G96*G$15/$E$4-F104-E104 -> 0.04775967 | H104: =H96*H$15/$E$4-G104-F104-E104 -> 0.067835372 | I104: =I96*I$15/$E$4-H104-G104-F104-E104 -> 0.095538394 | J104: =J96*J$15/$E$4-I104-H104-G104-F104-E104 -> 0.13360421 | K104: =K96*K$15/$E$4-J104-I104-H104-G104-F104-E104 -> 0.18571343 | L104: =L96*L$15/$E$4-K104-J104-I104-H104-G104-F104-E104 -> 0.25680987 | M104: =M96*M$15/$E$4-L104-K104-J104-I104-H104-G104-F104-E104 -> 0.35352376 | N104: =N96*N$15/$E$4-M104-L104-K104-J104-I104-H104-G104-F104-E104 -> 0.48473399
D105: Annual Average % | I105: =AVERAGE(E104:I104) -> 0.053463087 | N105: =AVERAGE(E104:N104) -> 0.16817007
D106: Test Case Annual | E106: =E108 -> 22900 | F106: =F108-E108 -> 33282 | G106: =G108-F108 -> 47759.67 | H106: =H108-G108 -> 67835.372 | I106: =I108-H108 -> 95538.394 | J106: =J108-I108 -> 133604.21 | K106: =K108-J108 -> 185713.43 | L106: =L108-K108 -> 256809.87 | M106: =M108-L108 -> 353523.76 | N106: =N108-M108 -> 484733.99
D107: Test Case Annual Average | I107: =AVERAGE(E106:I106) -> 53463.087 | N107: =AVERAGE(E106:N106) -> 168170.07
D108: Test Case Cumulative | E108: =E98*E$15 -> 22900 | F108: =F98*F$15 -> 56182 | G108: =G98*G$15 -> 103941.67 | H108: =H98*H$15 -> 171777.04 | I108: =I98*I$15 -> 267315.44 | J108: =J98*J$15 -> 400919.65 | K108: =K98*K$15 -> 586633.08 | L108: =L98*L$15 -> 843442.95 | ... N108: =N98*N$15 -> 1681700.7
B109: Total Yield | C109: BTC | D109: Annual % | E109: =E66+E79+E94-E34-E50 -> 0.16178295 | F109: =F66+F79+F94-F34-F50 -> 0.13215732 | G109: =G66+G79+G94-G34-G50 -> 0.10919172 | H109: =H66+H79+H94-H34-H50 -> 0.091388932 | I109: =I66+I79+I94-I34-I50 -> 0.07758832 | J109: =J66+J79+J94-J34-J50 -> 0.06689017 | K109: =K66+K79+K94-K34-K50 -> 0.058597031 | L109: =L66+L79+L94-L34-L50 -> 0.052168241 | ... N109: =N66+N79+N94-N34-N50 -> 0.04332146
...

Sheet 2.5X
B2: Bitcoin Lightning Credit Derivatives A permissionless, decentralized and distributed strategy for ultra-high yields using leveraged bitcoin growth and lightning transaction fee exposure | D2: Bitcoin Yield Estimate Variables BiGY = Bitcoin Growth Yield (CAGR) BiLY = Bitcoin Liquidity Yield BiTY = Bitcoin Transaction Yield | G2: Bitcoin Yield Estimate 5 Year Summary SR = Stable Receiver SB = Stable Balancer SP = Stable Provider | K2: Lightning Bank 5 Year Revenue Summary TVL = Total Value Locked
K3: Bitcoin TVL | L3: Measure | M3: BTC | N3: USD
D4: Bitcoin USD Price Start | E4: 100000 | G4: SR USD Comp. | H4: Annual Avg. % | I4: =I43 -> 0.17740036 | K4: =C127 -> 20000 | L4: Annual Avg. | M4: =I128 -> 347.61938 | N4: =M4*$I$15 -> 1.2418025e+08
D5: Annual Bitcoin Growth Yield % | E5: =SUMMARY!H6 -> 0.29 | G5: SP BiGY BTC | H5: Annual Avg. % | I5: =I67 -> 0.21602061 | K5: =C127 -> 20000 | L5: Cumulative | M5: =I129 -> 1738.0969 | N5: =M5*$I$15 -> 6.2090125e+08
D6: Annual Bitcoin Liquidity Yield % | E6: =SUMMARY!L6 -> 0.02 | G6: SP BiLY BTC | H6: Annual Avg. % | I6: =I80 -> 0.039931982 | K6: =C130 -> 400000 | L6: Annual Avg. | M6: =I131 -> 6952.3875 | N6: =M6*$I$15 -> 2.483605e+09
D7: Annual Bitcoin Transaction Yield % | E7: =SUMMARY!P6 -> 0.01 | G7: SP BiTY BTC | H7: Annual Avg. % | I7: =I95 -> 0.019965991 | K7: =C130 -> 400000 | L7: Cumulative | M7: =I132 -> 34761.938 | N7: =M7*$I$15 -> 1.2418025e+10
D8: Stable Receiver Security Annual USD % | E8: =SUMMARY!H21 -> 0.1 | G8: SP BiLY SR BTC | H8: Annual Avg. % | I8: =-I35 -> -0.049659911 | K8: =C133 -> 1000000 | L8: Annual Avg. | M8: =I134 -> 17380.969 | N8: =M8*$I$15 -> 6209012467
D9: Stable Balancer Security Annual USD % | E9: =SUMMARY!H22 -> 0.05 | G9: SP BiLY SB BTC | H9: Annual Avg. % | I9: =-I51 -> -0.043452422 | K9: =C133 -> 1000000 | L9: Cumulative | M9: =I135 -> 86904.844 | N9: =M9*$I$15 -> 3.1045062e+10
D10: Stable Balancer Debt Annual USD % | E10: =SUMMARY!H23 -> 0.075 | G10: SP Total BTC | H10: Annual Avg. % | I10: =I110 -> 0.18280625
D11: Stable Provider Debt-to-Value % | E11: =SUMMARY!H10 -> 0.5
B13: Yield Estimate Calculator | C13: Unit of Account | D13: Measure | E13: Year 1 | F13: Year 2 | G13: Year 3 | H13: Year 4 | I13: Year 5 | J13: Year 6 | K13: Year 7 | L13: Year 8 | M13: Year 9 | N13: Year 10
B15: Bitcoin | C15: USD | D15: Price | E15: =($E$4 * $E$5) + $E$4 -> 129000 | F15: =(E15 * $E$5) + E15 -> 166410 | G15: =(F15 * $E$5) + F15 -> 214668.9 | H15: =(G15 * $E$5) + G15 -> 276922.88 | I15: =(H15 * $E$5) + H15 -> 357230.52 | J15: =(I15 * $E$5) + I15 -> 460827.37 | K15: =(J15 * $E$5) + J15 -> 594467.3 | L15: =(K15 * $E$5) + K15 -> 766862.82 | M15: =(L15 * $E$5) + L15 -> 989253.04 | N15: =(M15 * $E$5) + M15 -> 1276136.4
D16: Marketcap | E16: =E15*21000000 -> 2709000000000 | F16: =F15*21000000 -> 3494610000000 | G16: =G15*21000000 -> 4508046900000 | H16: =H15*21000000 -> 5815380501000 | I16: =I15*21000000 -> 7.5018408e+12 | J16: =J15*21000000 -> 9.6773747e+12 | K16: =K15*21000000 -> 1.2483813e+13 | L16: =L15*21000000 -> 1.6104119e+13 | ... N16: =N15*21000000 -> 2.6798865e+13
B17: Bitcoin Growth Yield (BiGY) | C17: BTC | D17: Stable Security Cumulative % | E17: =(E15-$E4)/E15 -> 0.2248062 | F17: =(F15-$E4)/F15 -> 0.39907457 | G17: =(G15-$E4)/G15 -> 0.53416634 | H17: =(H15-$E4)/H15 -> 0.63888863 | I17: =(I15-$E4)/I15 -> 0.72006871 | J17: =(J15-$E4)/J15 -> 0.782999 | K17: =(K15-$E4)/K15 -> 0.83178217 | L17: =(L15-$E4)/L15 -> 0.86959858 | ... N17: =(N15-$E4)/N15 -> 0.92163847
D18: Stable Security Remaining % | E18: =1-E17 -> 0.7751938 | F18: =1-F17 -> 0.60092543 | G18: =1-G17 -> 0.46583366 | H18: =1-H17 -> 0.36111137 | I18: =1-I17 -> 0.27993129 | J18: =1-J17 -> 0.217001 | K18: =1-K17 -> 0.16821783 | L18: =1-L17 -> 0.13040142 | ... N18: =1-N17 -> 0.078361528
D19: Stable Security Annual % | E19: =E17 -> 0.2248062 | F19: =F17-E17 -> 0.17426837 | G19: =G17-F17 -> 0.13509176 | H19: =H17-G17 -> 0.1047223 | I19: =I17-H17 -> 0.081180075 | J19: =J17-I17 -> 0.06293029 | K19: =K17-J17 -> 0.048783171 | L19: =L17-K17 -> 0.037816412 | M19: =M17-L17 -> 0.029315048 | N19: =N17-M17 -> 0.022724843
D20: Stable Security Annual Average % | I20: =AVERAGE(E19:I19) -> 0.14401374 | N20: =AVERAGE(E19:N19) -> 0.092163847
D21: Stable Debt Annual % | E21: =$E$11*E19 -> 0.1124031 | F21: =$E$11*F19 -> 0.087134187 | G21: =$E$11*G19 -> 0.067545881 | H21: =$E$11*H19 -> 0.052361148 | I21: =$E$11*I19 -> 0.040590037 | J21: =$E$11*J19 -> 0.031465145 | K21: =$E$11*K19 -> 0.024391585 | L21: =$E$11*L19 -> 0.018908206 | ... N21: =$E$11*N19 -> 0.011362422
D22: Stable Debt Annual Avg. % | I22: =AVERAGE(E21:I21) -> 0.072006871 | N22: =AVERAGE(E21:N21) -> 0.046081924
D23: Total Annual % | E23: =E19+E21 -> 0.3372093 | F23: =F19+F21 -> 0.26140256 | G23: =G19+G21 -> 0.20263764 | H23: =H19+H21 -> 0.15708344 | I23: =I19+I21 -> 0.12177011 | J23: =J19+J21 -> 0.094395436 | K23: =K19+K21 -> 0.073174756 | L23: =L19+L21 -> 0.056724617 | ... N23: =N19+N21 -> 0.034087265
D24: Total Annual Average % | I24: =AVERAGE(E23:I23) -> 0.21602061 | N24: =AVERAGE(E23:N23) -> 0.13824577
B25: Bitcoin Liquidity Yield (BiLY) | C25: BTC | D25: Annual % | E25: =((1+$E$11)*$E$6)+($E$6*E18) -> 0.045503876 | F25: =((1+$E$11)*$E$6)+($E$6*F18) -> 0.042018509 | G25: =((1+$E$11)*$E$6)+($E$6*G18) -> 0.039316673 | H25: =((1+$E$11)*$E$6)+($E$6*H18) -> 0.037222227 | I25: =((1+$E$11)*$E$6)+($E$6*I18) -> 0.035598626 | J25: =((1+$E$11)*$E$6)+($E$6*J18) -> 0.03434002 | K25: =((1+$E$11)*$E$6)+($E$6*K18) -> 0.033364357 | L25: =((1+$E$11)*$E$6)+($E$6*L18) -> 0.032608028 | ... N25: =((1+$E$11)*$E$6)+($E$6*N18) -> 0.031567231
D26: Annual Average % | I26: =AVERAGE(E25:I25) -> 0.039931982 | N26: =AVERAGE(E25:N25) -> 0.036356127
D27: Cumulative % | E27: =E25 -> 0.045503876 | F27: =E27+F25 -> 0.087522384 | G27: =F27+G25 -> 0.12683906 | H27: =G27+H25 -> 0.16406129 | I27: =H27+I25 -> 0.19965991 | J27: =I27+J25 -> 0.23399993 | K27: =J27+K25 -> 0.26736429 | L27: =K27+L25 -> 0.29997232 | M27: =L27+M25 -> 0.33199404 | N27: =M27+N25 -> 0.36356127
B28: Bitcoin Transaction Yield (BiTY) | C28: BTC | D28: Annual % | E28: =((1+$E$11)*$E$7)+($E$7*E18) -> 0.022751938 | F28: =((1+$E$11)*$E$7)+($E$7*F18) -> 0.021009254 | G28: =((1+$E$11)*$E$7)+($E$7*G18) -> 0.019658337 | H28: =((1+$E$11)*$E$7)+($E$7*H18) -> 0.018611114 | I28: =((1+$E$11)*$E$7)+($E$7*I18) -> 0.017799313 | J28: =((1+$E$11)*$E$7)+($E$7*J18) -> 0.01717001 | K28: =((1+$E$11)*$E$7)+($E$7*K18) -> 0.016682178 | L28: =((1+$E$11)*$E$7)+($E$7*L18) -> 0.016304014 | ... N28: =((1+$E$11)*$E$7)+($E$7*N18) -> 0.015783615
D29: Annual Average % | I29: =AVERAGE(E28:I28) -> 0.019965991 | N29: =AVERAGE(E28:N28) -> 0.018178064
D30: Cumulative % | E30: =E28 -> 0.022751938 | F30: =E30+F28 -> 0.043761192 | G30: =F30+G28 -> 0.063419529 | H30: =G30+H28 -> 0.082030643 | I30: =H30+I28 -> 0.099829955 | J30: =I30+J28 -> 0.11699997 | K30: =J30+K28 -> 0.13368214 | L30: =K30+L28 -> 0.14998616 | M30: =L30+M28 -> 0.16599702 | N30: =M30+N28 -> 0.18178064
B32: Stable Receiver / Fiat Lender | C32: Test Case | D32: ="10 BTC / "&TEXT($E$4*10, "$###0.00,,")&"M USD" -> 10 BTC / $1.00M USD | E32: Year 1 | F32: Year 2 | G32: Year 3 | H32: Year 4 | I32: Year 5 | J32: Year 6 | K32: Year 7 | L32: Year 8 | M32: Year 9 | N32: Year 10
B34: Bitcoin Liquidity Yield (BiLY) | C34: BTC | D34: Total Annual % | E34: =E39*$E$4/E$15 -> 0.07751938 | F34: =F39*$E$4/F$15 -> 0.060092543 | G34: =G39*$E$4/G$15 -> 0.046583366 | H34: =H39*$E$4/H$15 -> 0.036111137 | I34: =I39*$E$4/I$15 -> 0.027993129 | J34: =J39*$E$4/J$15 -> 0.0217001 | K34: =K39*$E$4/K$15 -> 0.016821783 | L34: =L39*$E$4/L$15 -> 0.013040142 | ... N34: =N39*$E$4/N$15 -> 0.0078361528
D35: Total Annual Average % | I35: =AVERAGE(E34:I34) -> 0.049659911 | N35: =AVERAGE(E34:N34) -> 0.031780637
D36: Cumulative % | E36: =E$17*(E34/E$19) -> 0.07751938 | F36: =F$17*(F34/F$19) -> 0.13761192 | G36: =G$17*(G34/G$19) -> 0.18419529 | H36: =H$17*(H34/H$19) -> 0.22030643 | I36: =I$17*(I34/I$19) -> 0.24829955 | J36: =J$17*(J34/J$19) -> 0.26999965 | K36: =K$17*(K34/K$19) -> 0.28682144 | L36: =L$17*(L34/L$19) -> 0.29986158 | ... N36: =N$17*(N34/N$19) -> 0.31780637
D37: Test Case Annual | E37: =10*E34 -> 0.7751938 | F37: =10*F34 -> 0.60092543 | G37: =10*G34 -> 0.46583366 | H37: =10*H34 -> 0.36111137 | I37: =10*I34 -> 0.27993129 | J37: =10*J34 -> 0.217001 | K37: =10*K34 -> 0.16821783 | L37: =10*L34 -> 0.13040142 | ... N37: =10*N34 -> 0.078361528
D38: Test Case Cumulative | E38: =10*E36 -> 0.7751938 | F38: =10*F36 -> 1.3761192 | G38: =10*G36 -> 1.8419529 | H38: =10*H36 -> 2.2030643 | I38: =10*I36 -> 2.4829955 | J38: =10*J36 -> 2.6999965 | K38: =10*K36 -> 2.8682144 | L38: =10*L36 -> 2.9986158 | ... N38: =10*N36 -> 3.1780637
C39: USD Simple | D39: Annual % | E39: =E8 -> 0.1 | F39: =E39 -> 0.1 | G39: =F39 -> 0.1 | H39: =G39 -> 0.1 | I39: =H39 -> 0.1 | J39: =I39 -> 0.1 | K39: =J39 -> 0.1 | L39: =K39 -> 0.1 | M39: =L39 -> 0.1 | N39: =M39 -> 0.1
D40: Test Case Annual | E40: =E37*E$15 -> 100000 | F40: =F37*F$15 -> 100000 | G40: =G37*G$15 -> 100000 | H40: =H37*H$15 -> 100000 | I40: =I37*I$15 -> 100000 | J40: =J37*J$15 -> 100000 | K40: =K37*K$15 -> 100000 | L40: =L37*L$15 -> 100000 | ... N40: =N37*N$15 -> 100000
D41: Test Case Cumulative | E41: =E40 -> 100000 | F41: =E41+F40 -> 200000 | G41: =F41+G40 -> 300000 | H41: =G41+H40 -> 400000 | I41: =H41+I40 -> 500000 | J41: =I41+J40 -> 600000 | K41: =J41+K40 -> 700000 | L41: =K41+L40 -> 800000 | M41: =L41+M40 -> 900000 | N41: =M41+N40 -> 1000000
C42: USD Compounded | D42: Annual % | E42: =E36*E$15/$E$4 -> 0.1 | F42: =F36*F$15/$E$4-E42 -> 0.129 | G42: =G36*G$15/$E$4-F42-E42 -> 0.16641 | H42: =H36*H$15/$E$4-G42-F42-E42 -> 0.2146689 | I42: =I36*I$15/$E$4-H42-G42-F42-E42 -> 0.27692288 | J42: =J36*J$15/$E$4-I42-H42-G42-F42-E42 -> 0.35723052 | K42: =K36*K$15/$E$4-J42-I42-H42-G42-F42-E42 -> 0.46082737 | L42: =L36*L$15/$E$4-K42-J42-I42-H42-G42-F42-E42 -> 0.5944673 | M42: =M36*M$15/$E$4-L42-K42-J42-I42-H42-G42-F42-E42 -> 0.76686282 | N42: =N36*N$15/$E$4-M42-L42-K42-J42-I42-H42-G42-F42-E42 -> 0.98925304
D43: Annual Average % | I43: =AVERAGE(E42:I42) -> 0.17740036 | N43: =AVERAGE(E42:N42) -> 0.40556428
D44: Test Case Annual | E44: =E46 -> 100000 | F44: =F46-E46 -> 129000 | G44: =G46-F46 -> 166410 | H44: =H46-G46 -> 214668.9 | I44: =I46-H46 -> 276922.88 | J44: =J46-I46 -> 357230.52 | K44: =K46-J46 -> 460827.37 | L44: =L46-K46 -> 594467.3 | M44: =M46-L46 -> 766862.82 | N44: =N46-M46 -> 989253.04
D45: Test Case Annual Average | I45: =AVERAGE(E44:I44) -> 177400.36 | N45: =AVERAGE(E44:N44) -> 405564.28
D46: Test Case Cumulative | E46: =E38*E$15 -> 100000 | F46: =F38*F$15 -> 229000 | G46: =G38*G$15 -> 395410 | H46: =H38*H$15 -> 610078.9 | I46: =I38*I$15 -> 887001.78 | J46: =J38*J$15 -> 1244232.3 | K46: =K38*K$15 -> 1705059.7 | L46: =L38*L$15 -> 2299527 | ... N46: =N38*N$15 -> 4055642.8
B48: Stable Balancer / Lightning Service Provider | C48: Test Case | D48: ="10 BTC / "&TEXT($E$4*10, "$###0.00,,")&"M USD" -> 10 BTC / $1.00M USD | E48: Year 1 | F48: Year 2 | G48: Year 3 | H48: Year 4 | I48: Year 5 | J48: Year 6 | K48: Year 7 | L48: Year 8 | M48: Year 9 | N48: Year 10
B50: Bitcoin Liquidity Yield (BiLY) | C50: BTC | D50: Annual % | E50: =E55*$E$4/E$15 -> 0.067829457 | F50: =F55*$E$4/F$15 -> 0.052580975 | G50: =G55*$E$4/G$15 -> 0.040760446 | H50: =H55*$E$4/H$15 -> 0.031597245 | I50: =I55*$E$4/I$15 -> 0.024493988 | J50: =J55*$E$4/J$15 -> 0.018987588 | K50: =K55*$E$4/K$15 -> 0.01471906 | L50: =L55*$E$4/L$15 -> 0.011410124 | ... N50: =N55*$E$4/N$15 -> 0.0068566337
D51: Annual Average % | I51: =AVERAGE(E50:I50) -> 0.043452422 | N51: =AVERAGE(E50:N50) -> 0.027808057
D52: Cumulative % | E52: =E$17*(E50/E$19) -> 0.067829457 | F52: =F$17*(F50/F$19) -> 0.12041043 | G52: =G$17*(G50/G$19) -> 0.16117088 | H52: =H$17*(H50/H$19) -> 0.19276812 | I52: =I$17*(I50/I$19) -> 0.21726211 | J52: =J$17*(J50/J$19) -> 0.2362497 | K52: =K$17*(K50/K$19) -> 0.25096876 | L52: =L$17*(L50/L$19) -> 0.26237888 | ... N52: =N$17*(N50/N$19) -> 0.27808057
D53: Test Case Annual | E53: =10*E50 -> 0.67829457 | F53: =10*F50 -> 0.52580975 | G53: =10*G50 -> 0.40760446 | H53: =10*H50 -> 0.31597245 | I53: =10*I50 -> 0.24493988 | J53: =10*J50 -> 0.18987588 | K53: =10*K50 -> 0.1471906 | L53: =10*L50 -> 0.11410124 | ... N53: =10*N50 -> 0.068566337
D54: Test Case Cumulative | E54: =10*E52 -> 0.67829457 | F54: =10*F52 -> 1.2041043 | G54: =10*G52 -> 1.6117088 | H54: =10*H52 -> 1.9276812 | I54: =10*I52 -> 2.1726211 | J54: =10*J52 -> 2.362497 | K54: =10*K52 -> 2.5096876 | L54: =10*L52 -> 2.6237888 | ... N54: =10*N52 -> 2.7808057
C55: USD Simple | D55: Annual % | E55: =$E9+($E$10*$E$11) -> 0.0875 | F55: =$E9+($E$10*$E$11) -> 0.0875 | G55: =$E9+($E$10*$E$11) -> 0.0875 | H55: =$E9+($E$10*$E$11) -> 0.0875 | I55: =$E9+($E$10*$E$11) -> 0.0875 | J55: =$E9+($E$10*$E$11) -> 0.0875 | K55: =$E9+($E$10*$E$11) -> 0.0875 | L55: =$E9+($E$10*$E$11) -> 0.0875 | ... N55: =$E9+($E$10*$E$11) -> 0.0875
D56: Test Case Annual | E56: =E53*E$15 -> 87500 | F56: =F53*F$15 -> 87500 | G56: =G53*G$15 -> 87500 | H56: =H53*H$15 -> 87500 | I56: =I53*I$15 -> 87500 | J56: =J53*J$15 -> 87500 | K56: =K53*K$15 -> 87500 | L56: =L53*L$15 -> 87500 | ... N56: =N53*N$15 -> 87500
D57: Test Case Cumulative | E57: =E56 -> 87500 | F57: =E57+F56 -> 175000 | G57: =F57+G56 -> 262500 | H57: =G57+H56 -> 350000 | I57: =H57+I56 -> 437500 | J57: =I57+J56 -> 525000 | K57: =J57+K56 -> 612500 | L57: =K57+L56 -> 700000 | M57: =L57+M56 -> 787500 | N57: =M57+N56 -> 875000
C58: USD Compounded | D58: Annual % | E58: =E52*E$15/$E$4 -> 0.0875 | F58: =F52*F$15/$E$4-E58 -> 0.112875 | G58: =G52*G$15/$E$4-F58-E58 -> 0.14560875 | H58: =H52*H$15/$E$4-G58-F58-E58 -> 0.18783529 | I58: =I52*I$15/$E$4-H58-G58-F58-E58 -> 0.24230752 | J58: =J52*J$15/$E$4-I58-H58-G58-F58-E58 -> 0.3125767 | K58: =K52*K$15/$E$4-J58-I58-H58-G58-F58-E58 -> 0.40322395 | L58: =L52*L$15/$E$4-K58-J58-I58-H58-G58-F58-E58 -> 0.52015889 | M58: =M52*M$15/$E$4-L58-K58-J58-I58-H58-G58-F58-E58 -> 0.67100497 | N58: =N52*N$15/$E$4-M58-L58-K58-J58-I58-H58-G58-F58-E58 -> 0.86559641
D59: Annual Average % | I59: =AVERAGE(E58:I58) -> 0.15522531 | N59: =AVERAGE(E58:N58) -> 0.35486875
D60: Test Case Annual | E60: =E62 -> 87500 | F60: =F62-E62 -> 112875 | G60: =G62-F62 -> 145608.75 | H60: =H62-G62 -> 187835.29 | I60: =I62-H62 -> 242307.52 | J60: =J62-I62 -> 312576.7 | K60: =K62-J62 -> 403223.95 | L60: =L62-K62 -> 520158.89 | M60: =M62-L62 -> 671004.97 | N60: =N62-M62 -> 865596.41
D61: Test Case Annual Average | I61: =AVERAGE(E60:I60) -> 155225.31 | N61: =AVERAGE(E60:N60) -> 354868.75
D62: Test Case Cumulative | E62: =E54*E$15 -> 87500 | F62: =F54*F$15 -> 200375 | G62: =G54*G$15 -> 345983.75 | H62: =H54*H$15 -> 533819.04 | I62: =I54*I$15 -> 776126.56 | J62: =J54*J$15 -> 1088703.3 | K62: =K54*K$15 -> 1491927.2 | L62: =L54*L$15 -> 2012086.1 | ... N62: =N54*N$15 -> 3548687.5
B64: Stable Provider / Bitcoin Borrower | C64: Test Case | D64: ="10 BTC / "&TEXT($E$4*10, "$###0.00,,")&"M USD" -> 10 BTC / $1.00M USD | E64: Year 1 | F64: Year 2 | G64: Year 3 | H64: Year 4 | I64: Year 5 | J64: Year 6 | K64: Year 7 | L64: Year 8 | M64: Year 9 | N64: Year 10
B66: Bitcoin Growth Yield (BiGY) | C66: BTC | D66: Total Annual % | E66: =E$23 -> 0.3372093 | F66: =F$23 -> 0.26140256 | G66: =G$23 -> 0.20263764 | H66: =H$23 -> 0.15708344 | I66: =I$23 -> 0.12177011 | J66: =J$23 -> 0.094395436 | K66: =K$23 -> 0.073174756 | L66: =L$23 -> 0.056724617 | ... N66: =N$23 -> 0.034087265
D67: Total Annual Average % | I67: =AVERAGE(E66:I66) -> 0.21602061 | N67: =AVERAGE(E66:N66) -> 0.13824577
D68: Cumulative % | E68: =E$17*(E66/E$19) -> 0.3372093 | F68: =F$17*(F66/F$19) -> 0.59861186 | G68: =G$17*(G66/G$19) -> 0.80124951 | H68: =H$17*(H66/H$19) -> 0.95833295 | I68: =I$17*(I66/I$19) -> 1.0801031 | J68: =J$17*(J66/J$19) -> 1.1744985 | K68: =K$17*(K66/K$19) -> 1.2476733 | L68: =L$17*(L66/L$19) -> 1.3043979 | ... N68: =N$17*(N66/N$19) -> 1.3824577
D69: Test Case Annual | E69: =10*E66 -> 3.372093 | F69: =10*F66 -> 2.6140256 | G69: =10*G66 -> 2.0263764 | H69: =10*H66 -> 1.5708344 | I69: =10*I66 -> 1.2177011 | J69: =10*J66 -> 0.94395436 | K69: =10*K66 -> 0.73174756 | L69: =10*L66 -> 0.56724617 | ... N69: =10*N66 -> 0.34087265
D70: Test Case Cumulative | E70: =10*E68 -> 3.372093 | F70: =10*F68 -> 5.9861186 | G70: =10*G68 -> 8.0124951 | H70: =10*H68 -> 9.5833295 | I70: =10*I68 -> 10.801031 | J70: =10*J68 -> 11.744985 | K70: =10*K68 -> 12.476733 | L70: =10*L68 -> 13.043979 | ... N70: =10*N68 -> 13.824577
C71: USD Simple | D71: Annual % | E71: =E66*E$15/$E$4 -> 0.435 | F71: =F66*F$15/$E$4 -> 0.435 | G71: =G66*G$15/$E$4 -> 0.435 | H71: =H66*H$15/$E$4 -> 0.435 | I71: =I66*I$15/$E$4 -> 0.435 | J71: =J66*J$15/$E$4 -> 0.435 | K71: =K66*K$15/$E$4 -> 0.435 | L71: =L66*L$15/$E$4 -> 0.435 | ... N71: =N66*N$15/$E$4 -> 0.435
D72: Test Case Annual | E72: =E69*E$15 -> 435000 | F72: =F69*F$15 -> 435000 | G72: =G69*G$15 -> 435000 | H72: =H69*H$15 -> 435000 | I72: =I69*I$15 -> 435000 | J72: =J69*J$15 -> 435000 | K72: =K69*K$15 -> 435000 | L72: =L69*L$15 -> 435000 | ... N72: =N69*N$15 -> 435000
D73: Test Case Cumulative | E73: =E72 -> 435000 | F73: =E73+F72 -> 870000 | G73: =F73+G72 -> 1305000 | H73: =G73+H72 -> 1740000 | I73: =H73+I72 -> 2175000 | J73: =I73+J72 -> 2610000 | K73: =J73+K72 -> 3045000 | L73: =K73+L72 -> 3480000 | M73: =L73+M72 -> 3915000 | N73: =M73+N72 -> 4350000
C74: USD Compounded | D74: Annual % | E74: =E68*E$15/$E$4 -> 0.435 | F74: =F68*F$15/$E$4-E74 -> 0.56115 | G74: =G68*G$15/$E$4-F74-E74 -> 0.7238835 | H74: =H68*H$15/$E$4-G74-F74-E74 -> 0.93380971 | I74: =I68*I$15/$E$4-H74-G74-F74-E74 -> 1.2046145 | J74: =J68*J$15/$E$4-I74-H74-G74-F74-E74 -> 1.5539527 | K74: =K68*K$15/$E$4-J74-I74-H74-G74-F74-E74 -> 2.004599 | L74: =L68*L$15/$E$4-K74-J74-I74-H74-G74-F74-E74 -> 2.5859328 | M74: =M68*M$15/$E$4-L74-K74-J74-I74-H74-G74-F74-E74 -> 3.3358533 | N74: =N68*N$15/$E$4-M74-L74-K74-J74-I74-H74-G74-F74-E74 -> 4.3032507
D75: Annual Average % | I75: =AVERAGE(E74:I74) -> 0.77169155 | N75: =AVERAGE(E74:N74) -> 1.7642046
D76: Test Case Annual | E76: =E78 -> 435000 | F76: =F78-E78 -> 561150 | G76: =G78-F78 -> 723883.5 | H76: =H78-G78 -> 933809.71 | I76: =I78-H78 -> 1204614.5 | J76: =J78-I78 -> 1553952.7 | K76: =K78-J78 -> 2004599 | L76: =L78-K78 -> 2585932.8 | M76: =M78-L78 -> 3335853.3 | N76: =N78-M78 -> 4303250.7
D77: Test Case Annual Average | I77: =AVERAGE(E76:I76) -> 771691.55 | N77: =AVERAGE(E76:N76) -> 1764204.6
D78: Test Case Cumulative | E78: =E70*E$15 -> 435000 | F78: =F70*F$15 -> 996150 | G78: =G70*G$15 -> 1720033.5 | H78: =H70*H$15 -> 2653843.2 | I78: =I70*I$15 -> 3858457.7 | J78: =J70*J$15 -> 5412410.5 | K78: =K70*K$15 -> 7417009.5 | L78: =L70*L$15 -> 10002942 | ... N78: =N70*N$15 -> 17642046
B79: Bitcoin Liquidity Yield (BiLY) | C79: BTC | D79: Annual % | E79: =E$25 -> 0.045503876 | F79: =F$25 -> 0.042018509 | G79: =G$25 -> 0.039316673 | H79: =H$25 -> 0.037222227 | I79: =I$25 -> 0.035598626 | J79: =J$25 -> 0.03434002 | K79: =K$25 -> 0.033364357 | L79: =L$25 -> 0.032608028 | ... N79: =N$25 -> 0.031567231
D80: Annual Average % | I80: =AVERAGE(E79:I79) -> 0.039931982 | N80: =AVERAGE(E79:N79) -> 0.036356127
D81: Cumulative % | E81: =E$27 -> 0.045503876 | F81: =F$27 -> 0.087522384 | G81: =G$27 -> 0.12683906 | H81: =H$27 -> 0.16406129 | I81: =I$27 -> 0.19965991 | J81: =J$27 -> 0.23399993 | K81: =K$27 -> 0.26736429 | L81: =L$27 -> 0.29997232 | ... N81: =N$27 -> 0.36356127
D82: Test Case Annual | E82: =10*E79 -> 0.45503876 | F82: =10*F79 -> 0.42018509 | G82: =10*G79 -> 0.39316673 | H82: =10*H79 -> 0.37222227 | I82: =10*I79 -> 0.35598626 | J82: =10*J79 -> 0.3434002 | K82: =10*K79 -> 0.33364357 | L82: =10*L79 -> 0.32608028 | ... N82: =10*N79 -> 0.31567231
D83: Test Case Cumulative | E83: =10*E81 -> 0.45503876 | F83: =10*F81 -> 0.87522384 | G83: =10*G81 -> 1.2683906 | H83: =10*H81 -> 1.6406129 | I83: =10*I81 -> 1.9965991 | J83: =10*J81 -> 2.3399993 | K83: =10*K81 -> 2.6736429 | L83: =10*L81 -> 2.9997232 | ... N83: =10*N81 -> 3.6356127
C84: USD Simple | D84: Annual % | E84: =E79*E$15/$E$4 -> 0.0587 | F84: =F79*F$15/$E$4 -> 0.069923 | G84: =G79*G$15/$E$4 -> 0.08440067 | H84: =H79*H$15/$E$4 -> 0.10307686 | I84: =I79*I$15/$E$4 -> 0.12716915 | J84: =J79*J$15/$E$4 -> 0.15824821 | K84: =K79*K$15/$E$4 -> 0.19834019 | L84: =L79*L$15/$E$4 -> 0.25005885 | ... N84: =N79*N$15/$E$4 -> 0.40284093
D85: Annual Average % | I85: =AVERAGE(E84:I84) -> 0.088653938 | N85: =AVERAGE(E84:N84) -> 0.17695338
D86: Test Case Annual | E86: =E82*E$15 -> 58700 | F86: =F82*F$15 -> 69923 | G86: =G82*G$15 -> 84400.67 | H86: =H82*H$15 -> 103076.86 | I86: =I82*I$15 -> 127169.15 | J86: =J82*J$15 -> 158248.21 | K86: =K82*K$15 -> 198340.19 | L86: =L82*L$15 -> 250058.85 | ... N86: =N82*N$15 -> 402840.93
D87: Test Case Annual Average | I87: =AVERAGE(E86:I86) -> 88653.938 | N87: =AVERAGE(E86:N86) -> 176953.38
D88: Test Case Cumulative | E88: =E86 -> 58700 | F88: =E88+F86 -> 128623 | G88: =F88+G86 -> 213023.67 | H88: =G88+H86 -> 316100.53 | I88: =H88+I86 -> 443269.69 | J88: =I88+J86 -> 601517.9 | K88: =J88+K86 -> 799858.09 | L88: =K88+L86 -> 1049916.9 | M88: =L88+M86 -> 1366692.8 | N88: =M88+N86 -> 1769533.8
C89: USD Compounded | D89: Annual % | E89: =E81*E$15/$E$4 -> 0.0587 | F89: =F81*F$15/$E$4-E89 -> 0.086946 | G89: =G81*G$15/$E$4-F89-E89 -> 0.12663801 | H89: =H81*H$15/$E$4-G89-F89-E89 -> 0.18203923 | I89: =I81*I$15/$E$4-H89-G89-F89-E89 -> 0.25892289 | J89: =J81*J$15/$E$4-I89-H89-G89-F89-E89 -> 0.36508959 | K89: =K81*K$15/$E$4-J89-I89-H89-G89-F89-E89 -> 0.51105755 | L89: =L81*L$15/$E$4-K89-J89-I89-H89-G89-F89-E89 -> 0.71098289 | M89: =M81*M$15/$E$4-L89-K89-J89-I89-H89-G89-F89-E89 -> 0.983885 | N89: =N81*N$15/$E$4-M89-L89-K89-J89-I89-H89-G89-F89-E89 -> 1.3552767
D90: Annual Average % | I90: =AVERAGE(E89:I89) -> 0.14264923 | N90: =AVERAGE(E89:N89) -> 0.46395378
D91: Test Case Annual | E91: =E93 -> 58700 | F91: =F93-E93 -> 86946 | G91: =G93-F93 -> 126638.01 | H91: =H93-G93 -> 182039.23 | I91: =I93-H93 -> 258922.89 | J91: =J93-I93 -> 365089.59 | K91: =K93-J93 -> 511057.55 | L91: =L93-K93 -> 710982.89 | M91: =M93-L93 -> 983885 | N91: =N93-M93 -> 1355276.7
D92: Test Case Annual Average | I92: =AVERAGE(E91:I91) -> 142649.23 | N92: =AVERAGE(E91:N91) -> 463953.78
D93: Test Case Cumulative | E93: =E83*E$15 -> 58700 | F93: =F83*F$15 -> 145646 | G93: =G83*G$15 -> 272284.01 | H93: =H83*H$15 -> 454323.24 | I93: =I83*I$15 -> 713246.13 | J93: =J83*J$15 -> 1078335.7 | K93: =K83*K$15 -> 1589393.3 | L93: =L83*L$15 -> 2300376.2 | ... N93: =N83*N$15 -> 4639537.8
B94: Bitcoin Transaction Yield (BiTY) | C94: BTC | D94: Annual % | E94: =E$28 -> 0.022751938 | F94: =F$28 -> 0.021009254 | G94: =G$28 -> 0.019658337 | H94: =H$28 -> 0.018611114 | I94: =I$28 -> 0.017799313 | J94: =J$28 -> 0.01717001 | K94: =K$28 -> 0.016682178 | L94: =L$28 -> 0.016304014 | ... N94: =N$28 -> 0.015783615
D95: Annual Average % | I95: =AVERAGE(E94:I94) -> 0.019965991 | N95: =AVERAGE(E94:N94) -> 0.018178064
D96: Cumulative % | E96: =E$30 -> 0.022751938 | F96: =F$30 -> 0.043761192 | G96: =G$30 -> 0.063419529 | H96: =H$30 -> 0.082030643 | I96: =I$30 -> 0.099829955 | J96: =J$30 -> 0.11699997 | K96: =K$30 -> 0.13368214 | L96: =L$30 -> 0.14998616 | ... N96: =N$30 -> 0.18178064
D97: Test Case Annual | E97: =10*E94 -> 0.22751938 | F97: =10*F94 -> 0.21009254 | G97: =10*G94 -> 0.19658337 | H97: =10*H94 -> 0.18611114 | I97: =10*I94 -> 0.17799313 | J97: =10*J94 -> 0.1717001 | K97: =10*K94 -> 0.16682178 | L97: =10*L94 -> 0.16304014 | ... N97: =10*N94 -> 0.15783615
D98: Test Case Cumulative | E98: =10*E96 -> 0.22751938 | F98: =10*F96 -> 0.43761192 | G98: =10*G96 -> 0.63419529 | H98: =10*H96 -> 0.82030643 | I98: =10*I96 -> 0.99829955 | J98: =10*J96 -> 1.1699997 | K98: =10*K96 -> 1.3368214 | L98: =10*L96 -> 1.4998616 | ... N98: =10*N96 -> 1.8178064
C99: USD Simple | D99: Annual % | E99: =E94*E$15/$E$4 -> 0.02935 | F99: =F94*F$15/$E$4 -> 0.0349615 | G99: =G94*G$15/$E$4 -> 0.042200335 | H99: =H94*H$15/$E$4 -> 0.051538432 | I99: =I94*I$15/$E$4 -> 0.063584577 | J99: =J94*J$15/$E$4 -> 0.079124105 | K99: =K94*K$15/$E$4 -> 0.099170095 | L99: =L94*L$15/$E$4 -> 0.12502942 | ... N99: =N94*N$15/$E$4 -> 0.20142046
D100: Annual Average % | I100: =AVERAGE(E99:I99) -> 0.044326969 | N100: =AVERAGE(E99:N99) -> 0.088476689
D101: Test Case Annual | E101: =E97*E$15 -> 29350 | F101: =F97*F$15 -> 34961.5 | G101: =G97*G$15 -> 42200.335 | H101: =H97*H$15 -> 51538.432 | I101: =I97*I$15 -> 63584.577 | J101: =J97*J$15 -> 79124.105 | K101: =K97*K$15 -> 99170.095 | L101: =L97*L$15 -> 125029.42 | ... N101: =N97*N$15 -> 201420.46
D102: Test Case Annual Average | I102: =AVERAGE(E101:I101) -> 44326.969 | N102: =AVERAGE(E101:N101) -> 88476.689
D103: Test Case Cumulative | E103: =E101 -> 29350 | F103: =E103+F101 -> 64311.5 | G103: =F103+G101 -> 106511.83 | H103: =G103+H101 -> 158050.27 | I103: =H103+I101 -> 221634.84 | J103: =I103+J101 -> 300758.95 | K103: =J103+K101 -> 399929.04 | L103: =K103+L101 -> 524958.47 | M103: =L103+M101 -> 683346.42 | N103: =M103+N101 -> 884766.89
C104: USD Compounded | D104: Annual % | E104: =E96*E$15/$E$4 -> 0.02935 | F104: =F96*F$15/$E$4-E104 -> 0.043473 | G104: =G96*G$15/$E$4-F104-E104 -> 0.063319005 | H104: =H96*H$15/$E$4-G104-F104-E104 -> 0.091019614 | I104: =I96*I$15/$E$4-H104-G104-F104-E104 -> 0.12946145 | J104: =J96*J$15/$E$4-I104-H104-G104-F104-E104 -> 0.18254479 | K104: =K96*K$15/$E$4-J104-I104-H104-G104-F104-E104 -> 0.25552877 | L104: =L96*L$15/$E$4-K104-J104-I104-H104-G104-F104-E104 -> 0.35549145 | M104: =M96*M$15/$E$4-L104-K104-J104-I104-H104-G104-F104-E104 -> 0.4919425 | N104: =N96*N$15/$E$4-M104-L104-K104-J104-I104-H104-G104-F104-E104 -> 0.67763833
D105: Annual Average % | I105: =AVERAGE(E104:I104) -> 0.071324613 | N105: =AVERAGE(E104:N104) -> 0.23197689
D106: Test Case Annual | E106: =E108 -> 29350 | F106: =F108-E108 -> 43473 | G106: =G108-F108 -> 63319.005 | H106: =H108-G108 -> 91019.614 | I106: =I108-H108 -> 129461.45 | J106: =J108-I108 -> 182544.79 | K106: =K108-J108 -> 255528.77 | L106: =L108-K108 -> 355491.45 | M106: =M108-L108 -> 491942.5 | N106: =N108-M108 -> 677638.33
D107: Test Case Annual Average | I107: =AVERAGE(E106:I106) -> 71324.613 | N107: =AVERAGE(E106:N106) -> 231976.89
D108: Test Case Cumulative | E108: =E98*E$15 -> 29350 | F108: =F98*F$15 -> 72823 | G108: =G98*G$15 -> 136142.01 | H108: =H98*H$15 -> 227161.62 | I108: =I98*I$15 -> 356623.07 | J108: =J98*J$15 -> 539167.86 | K108: =K98*K$15 -> 794696.63 | L108: =L98*L$15 -> 1150188.1 | ... N108: =N98*N$15 -> 2319768.9
B109: Total Yield | C109: BTC | D109: Annual % | E109: =E66+E79+E94-E34-E50 -> 0.26011628 | F109: =F66+F79+F94-F34-F50 -> 0.21175681 | G109: =G66+G79+G94-G34-G50 -> 0.17426884 | H109: =H66+H79+H94-H34-H50 -> 0.1452084 | I109: =I66+I79+I94-I34-I50 -> 0.12268093 | J109: =J66+J79+J94-J34-J50 -> 0.10521778 | K109: =K66+K79+K94-K34-K50 -> 0.091680448 | L109: =L66+L79+L94-L34-L50 -> 0.081186394 | ... N109: =N66+N79+N94-N34-N50 -> 0.066745324
...

Sheet 3X
B2: Bitcoin Lightning Credit Derivatives A permissionless, decentralized and distributed strategy for ultra-high yields using leveraged bitcoin growth and lightning transaction fee exposure | D2: Bitcoin Yield Estimate Variables BiGY = Bitcoin Growth Yield (CAGR) BiLY = Bitcoin Liquidity Yield BiTY = Bitcoin Transaction Yield | G2: Bitcoin Yield Estimate 5 Year Summary SR = Stable Receiver SB = Stable Balancer SP = Stable Provider | K2: Lightning Bank 5 Year Revenue Summary TVL = Total Value Locked
K3: Bitcoin TVL | L3: Measure | M3: BTC | N3: USD
D4: Bitcoin USD Price Start | E4: 100000 | G4: SR USD Comp. | H4: Annual Avg. % | I4: =I43 -> 0.17740036 | K4: =C127 -> 20000 | L4: Annual Avg. | M4: =I128 -> 413.83259 | N4: =M4*$I$15 -> 1.4783363e+08
D5: Annual Bitcoin Growth Yield % | E5: =SUMMARY!H6 -> 0.29 | G5: SP BiGY BTC | H5: Annual Avg. % | I5: =I67 -> 0.28802748 | K5: =C127 -> 20000 | L5: Cumulative | M5: =I129 -> 2069.163 | N5: =M5*$I$15 -> 7.3916815e+08
D6: Annual Bitcoin Liquidity Yield % | E6: =SUMMARY!L6 -> 0.02 | G6: SP BiLY BTC | H6: Annual Avg. % | I6: =I80 -> 0.049931982 | K6: =C130 -> 400000 | L6: Annual Avg. | M6: =I131 -> 8276.6518 | N6: =M6*$I$15 -> 2.9566726e+09
D7: Annual Bitcoin Transaction Yield % | E7: =SUMMARY!P6 -> 0.01 | G7: SP BiTY BTC | H7: Annual Avg. % | I7: =I95 -> 0.024965991 | K7: =C130 -> 400000 | L7: Cumulative | M7: =I132 -> 41383.259 | N7: =M7*$I$15 -> 1.4783363e+10
D8: Stable Receiver Security Annual USD % | E8: =SUMMARY!J21 -> 0.1 | G8: SP BiLY SR BTC | H8: Annual Avg. % | I8: =-I35 -> -0.049659911 | K8: =C133 -> 1000000 | L8: Annual Avg. | M8: =I134 -> 20691.63 | N8: =M8*$I$15 -> 7.3916815e+09
D9: Stable Balancer Security Annual USD % | E9: =SUMMARY!J22 -> 0.05 | G9: SP BiLY SB BTC | H9: Annual Avg. % | I9: =-I51 -> -0.062074889 | K9: =C133 -> 1000000 | L9: Cumulative | M9: =I135 -> 103458.15 | N9: =M9*$I$15 -> 3.6958408e+10
D10: Stable Balancer Debt Annual USD % | E10: =SUMMARY!J23 -> 0.075 | G10: SP Total BTC | H10: Annual Avg. % | I10: =I110 -> 0.25119066
D11: Stable Provider Debt-to-Value % | E11: =SUMMARY!J10 -> 1
B13: Yield Estimate Calculator | C13: Unit of Account | D13: Measure | E13: Year 1 | F13: Year 2 | G13: Year 3 | H13: Year 4 | I13: Year 5 | J13: Year 6 | K13: Year 7 | L13: Year 8 | M13: Year 9 | N13: Year 10
B15: Bitcoin | C15: USD | D15: Price | E15: =($E$4 * $E$5) + $E$4 -> 129000 | F15: =(E15 * $E$5) + E15 -> 166410 | G15: =(F15 * $E$5) + F15 -> 214668.9 | H15: =(G15 * $E$5) + G15 -> 276922.88 | I15: =(H15 * $E$5) + H15 -> 357230.52 | J15: =(I15 * $E$5) + I15 -> 460827.37 | K15: =(J15 * $E$5) + J15 -> 594467.3 | L15: =(K15 * $E$5) + K15 -> 766862.82 | M15: =(L15 * $E$5) + L15 -> 989253.04 | N15: =(M15 * $E$5) + M15 -> 1276136.4
D16: Marketcap | E16: =E15*21000000 -> 2709000000000 | F16: =F15*21000000 -> 3494610000000 | G16: =G15*21000000 -> 4508046900000 | H16: =H15*21000000 -> 5815380501000 | I16: =I15*21000000 -> 7.5018408e+12 | J16: =J15*21000000 -> 9.6773747e+12 | K16: =K15*21000000 -> 1.2483813e+13 | L16: =L15*21000000 -> 1.6104119e+13 | ... N16: =N15*21000000 -> 2.6798865e+13
B17: Bitcoin Growth Yield (BiGY) | C17: BTC | D17: Stable Security Cumulative % | E17: =(E15-$E4)/E15 -> 0.2248062 | F17: =(F15-$E4)/F15 -> 0.39907457 | G17: =(G15-$E4)/G15 -> 0.53416634 | H17: =(H15-$E4)/H15 -> 0.63888863 | I17: =(I15-$E4)/I15 -> 0.72006871 | J17: =(J15-$E4)/J15 -> 0.782999 | K17: =(K15-$E4)/K15 -> 0.83178217 | L17: =(L15-$E4)/L15 -> 0.86959858 | ... N17: =(N15-$E4)/N15 -> 0.92163847
D18: Stable Security Remaining % | E18: =1-E17 -> 0.7751938 | F18: =1-F17 -> 0.60092543 | G18: =1-G17 -> 0.46583366 | H18: =1-H17 -> 0.36111137 | I18: =1-I17 -> 0.27993129 | J18: =1-J17 -> 0.217001 | K18: =1-K17 -> 0.16821783 | L18: =1-L17 -> 0.13040142 | ... N18: =1-N17 -> 0.078361528
D19: Stable Security Annual % | E19: =E17 -> 0.2248062 | F19: =F17-E17 -> 0.17426837 | G19: =G17-F17 -> 0.13509176 | H19: =H17-G17 -> 0.1047223 | I19: =I17-H17 -> 0.081180075 | J19: =J17-I17 -> 0.06293029 | K19: =K17-J17 -> 0.048783171 | L19: =L17-K17 -> 0.037816412 | M19: =M17-L17 -> 0.029315048 | N19: =N17-M17 -> 0.022724843
D20: Stable Security Annual Average % | I20: =AVERAGE(E19:I19) -> 0.14401374 | N20: =AVERAGE(E19:N19) -> 0.092163847
D21: Stable Debt Annual % | E21: =$E$11*E19 -> 0.2248062 | F21: =$E$11*F19 -> 0.17426837 | G21: =$E$11*G19 -> 0.13509176 | H21: =$E$11*H19 -> 0.1047223 | I21: =$E$11*I19 -> 0.081180075 | J21: =$E$11*J19 -> 0.06293029 | K21: =$E$11*K19 -> 0.048783171 | L21: =$E$11*L19 -> 0.037816412 | ... N21: =$E$11*N19 -> 0.022724843
D22: Stable Debt Annual Avg. % | I22: =AVERAGE(E21:I21) -> 0.14401374 | N22: =AVERAGE(E21:N21) -> 0.092163847
D23: Total Annual % | E23: =E19+E21 -> 0.4496124 | F23: =F19+F21 -> 0.34853675 | G23: =G19+G21 -> 0.27018352 | H23: =H19+H21 -> 0.20944459 | I23: =I19+I21 -> 0.16236015 | J23: =J19+J21 -> 0.12586058 | K23: =K19+K21 -> 0.097566342 | L23: =L19+L21 -> 0.075632823 | ... N23: =N19+N21 -> 0.045449686
D24: Total Annual Average % | I24: =AVERAGE(E23:I23) -> 0.28802748 | N24: =AVERAGE(E23:N23) -> 0.18432769
B25: Bitcoin Liquidity Yield (BiLY) | C25: BTC | D25: Annual % | E25: =((1+$E$11)*$E$6)+($E$6*E18) -> 0.055503876 | F25: =((1+$E$11)*$E$6)+($E$6*F18) -> 0.052018509 | G25: =((1+$E$11)*$E$6)+($E$6*G18) -> 0.049316673 | H25: =((1+$E$11)*$E$6)+($E$6*H18) -> 0.047222227 | I25: =((1+$E$11)*$E$6)+($E$6*I18) -> 0.045598626 | J25: =((1+$E$11)*$E$6)+($E$6*J18) -> 0.04434002 | K25: =((1+$E$11)*$E$6)+($E$6*K18) -> 0.043364357 | L25: =((1+$E$11)*$E$6)+($E$6*L18) -> 0.042608028 | ... N25: =((1+$E$11)*$E$6)+($E$6*N18) -> 0.041567231
D26: Annual Average % | I26: =AVERAGE(E25:I25) -> 0.049931982 | N26: =AVERAGE(E25:N25) -> 0.046356127
D27: Cumulative % | E27: =E25 -> 0.055503876 | F27: =E27+F25 -> 0.10752238 | G27: =F27+G25 -> 0.15683906 | H27: =G27+H25 -> 0.20406129 | I27: =H27+I25 -> 0.24965991 | J27: =I27+J25 -> 0.29399993 | K27: =J27+K25 -> 0.33736429 | L27: =K27+L25 -> 0.37997232 | M27: =L27+M25 -> 0.42199404 | N27: =M27+N25 -> 0.46356127
B28: Bitcoin Transaction Yield (BiTY) | C28: BTC | D28: Annual % | E28: =((1+$E$11)*$E$7)+($E$7*E18) -> 0.027751938 | F28: =((1+$E$11)*$E$7)+($E$7*F18) -> 0.026009254 | G28: =((1+$E$11)*$E$7)+($E$7*G18) -> 0.024658337 | H28: =((1+$E$11)*$E$7)+($E$7*H18) -> 0.023611114 | I28: =((1+$E$11)*$E$7)+($E$7*I18) -> 0.022799313 | J28: =((1+$E$11)*$E$7)+($E$7*J18) -> 0.02217001 | K28: =((1+$E$11)*$E$7)+($E$7*K18) -> 0.021682178 | L28: =((1+$E$11)*$E$7)+($E$7*L18) -> 0.021304014 | ... N28: =((1+$E$11)*$E$7)+($E$7*N18) -> 0.020783615
D29: Annual Average % | I29: =AVERAGE(E28:I28) -> 0.024965991 | N29: =AVERAGE(E28:N28) -> 0.023178064
D30: Cumulative % | E30: =E28 -> 0.027751938 | F30: =E30+F28 -> 0.053761192 | G30: =F30+G28 -> 0.078419529 | H30: =G30+H28 -> 0.10203064 | I30: =H30+I28 -> 0.12482996 | J30: =I30+J28 -> 0.14699997 | K30: =J30+K28 -> 0.16868214 | L30: =K30+L28 -> 0.18998616 | M30: =L30+M28 -> 0.21099702 | N30: =M30+N28 -> 0.23178064
B32: Stable Receiver / Fiat Lender | C32: Test Case | D32: ="10 BTC / "&TEXT($E$4*10, "$###0.00,,")&"M USD" -> 10 BTC / $1.00M USD | E32: Year 1 | F32: Year 2 | G32: Year 3 | H32: Year 4 | I32: Year 5 | J32: Year 6 | K32: Year 7 | L32: Year 8 | M32: Year 9 | N32: Year 10
B34: Bitcoin Liquidity Yield (BiLY) | C34: BTC | D34: Total Annual % | E34: =E39*$E$4/E$15 -> 0.07751938 | F34: =F39*$E$4/F$15 -> 0.060092543 | G34: =G39*$E$4/G$15 -> 0.046583366 | H34: =H39*$E$4/H$15 -> 0.036111137 | I34: =I39*$E$4/I$15 -> 0.027993129 | J34: =J39*$E$4/J$15 -> 0.0217001 | K34: =K39*$E$4/K$15 -> 0.016821783 | L34: =L39*$E$4/L$15 -> 0.013040142 | ... N34: =N39*$E$4/N$15 -> 0.0078361528
D35: Total Annual Average % | I35: =AVERAGE(E34:I34) -> 0.049659911 | N35: =AVERAGE(E34:N34) -> 0.031780637
D36: Cumulative % | E36: =E$17*(E34/E$19) -> 0.07751938 | F36: =F$17*(F34/F$19) -> 0.13761192 | G36: =G$17*(G34/G$19) -> 0.18419529 | H36: =H$17*(H34/H$19) -> 0.22030643 | I36: =I$17*(I34/I$19) -> 0.24829955 | J36: =J$17*(J34/J$19) -> 0.26999965 | K36: =K$17*(K34/K$19) -> 0.28682144 | L36: =L$17*(L34/L$19) -> 0.29986158 | ... N36: =N$17*(N34/N$19) -> 0.31780637
D37: Test Case Annual | E37: =10*E34 -> 0.7751938 | F37: =10*F34 -> 0.60092543 | G37: =10*G34 -> 0.46583366 | H37: =10*H34 -> 0.36111137 | I37: =10*I34 -> 0.27993129 | J37: =10*J34 -> 0.217001 | K37: =10*K34 -> 0.16821783 | L37: =10*L34 -> 0.13040142 | ... N37: =10*N34 -> 0.078361528
D38: Test Case Cumulative | E38: =10*E36 -> 0.7751938 | F38: =10*F36 -> 1.3761192 | G38: =10*G36 -> 1.8419529 | H38: =10*H36 -> 2.2030643 | I38: =10*I36 -> 2.4829955 | J38: =10*J36 -> 2.6999965 | K38: =10*K36 -> 2.8682144 | L38: =10*L36 -> 2.9986158 | ... N38: =10*N36 -> 3.1780637
C39: USD Simple | D39: Annual % | E39: =E8 -> 0.1 | F39: =E39 -> 0.1 | G39: =F39 -> 0.1 | H39: =G39 -> 0.1 | I39: =H39 -> 0.1 | J39: =I39 -> 0.1 | K39: =J39 -> 0.1 | L39: =K39 -> 0.1 | M39: =L39 -> 0.1 | N39: =M39 -> 0.1
D40: Test Case Annual | E40: =E37*E$15 -> 100000 | F40: =F37*F$15 -> 100000 | G40: =G37*G$15 -> 100000 | H40: =H37*H$15 -> 100000 | I40: =I37*I$15 -> 100000 | J40: =J37*J$15 -> 100000 | K40: =K37*K$15 -> 100000 | L40: =L37*L$15 -> 100000 | ... N40: =N37*N$15 -> 100000
D41: Test Case Cumulative | E41: =E40 -> 100000 | F41: =E41+F40 -> 200000 | G41: =F41+G40 -> 300000 | H41: =G41+H40 -> 400000 | I41: =H41+I40 -> 500000 | J41: =I41+J40 -> 600000 | K41: =J41+K40 -> 700000 | L41: =K41+L40 -> 800000 | M41: =L41+M40 -> 900000 | N41: =M41+N40 -> 1000000
C42: USD Compounded | D42: Annual % | E42: =E36*E$15/$E$4 -> 0.1 | F42: =F36*F$15/$E$4-E42 -> 0.129 | G42: =G36*G$15/$E$4-F42-E42 -> 0.16641 | H42: =H36*H$15/$E$4-G42-F42-E42 -> 0.2146689 | I42: =I36*I$15/$E$4-H42-G42-F42-E42 -> 0.27692288 | J42: =J36*J$15/$E$4-I42-H42-G42-F42-E42 -> 0.35723052 | K42: =K36*K$15/$E$4-J42-I42-H42-G42-F42-E42 -> 0.46082737 | L42: =L36*L$15/$E$4-K42-J42-I42-H42-G42-F42-E42 -> 0.5944673 | M42: =M36*M$15/$E$4-L42-K42-J42-I42-H42-G42-F42-E42 -> 0.76686282 | N42: =N36*N$15/$E$4-M42-L42-K42-J42-I42-H42-G42-F42-E42 -> 0.98925304
D43: Annual Average % | I43: =AVERAGE(E42:I42) -> 0.17740036 | N43: =AVERAGE(E42:N42) -> 0.40556428
D44: Test Case Annual | E44: =E46 -> 100000 | F44: =F46-E46 -> 129000 | G44: =G46-F46 -> 166410 | H44: =H46-G46 -> 214668.9 | I44: =I46-H46 -> 276922.88 | J44: =J46-I46 -> 357230.52 | K44: =K46-J46 -> 460827.37 | L44: =L46-K46 -> 594467.3 | M44: =M46-L46 -> 766862.82 | N44: =N46-M46 -> 989253.04
D45: Test Case Annual Average | I45: =AVERAGE(E44:I44) -> 177400.36 | N45: =AVERAGE(E44:N44) -> 405564.28
D46: Test Case Cumulative | E46: =E38*E$15 -> 100000 | F46: =F38*F$15 -> 229000 | G46: =G38*G$15 -> 395410 | H46: =H38*H$15 -> 610078.9 | I46: =I38*I$15 -> 887001.78 | J46: =J38*J$15 -> 1244232.3 | K46: =K38*K$15 -> 1705059.7 | L46: =L38*L$15 -> 2299527 | ... N46: =N38*N$15 -> 4055642.8
B48: Stable Balancer / Lightning Service Provider | C48: Test Case | D48: ="10 BTC / "&TEXT($E$4*10, "$###0.00,,")&"M USD" -> 10 BTC / $1.00M USD | E48: Year 1 | F48: Year 2 | G48: Year 3 | H48: Year 4 | I48: Year 5 | J48: Year 6 | K48: Year 7 | L48: Year 8 | M48: Year 9 | N48: Year 10
B50: Bitcoin Liquidity Yield (BiLY) | C50: BTC | D50: Annual % | E50: =E55*$E$4/E$15 -> 0.096899225 | F50: =F55*$E$4/F$15 -> 0.075115678 | G50: =G55*$E$4/G$15 -> 0.058229208 | H50: =H55*$E$4/H$15 -> 0.045138921 | I50: =I55*$E$4/I$15 -> 0.034991411 | J50: =J55*$E$4/J$15 -> 0.027125125 | K50: =K55*$E$4/K$15 -> 0.021027229 | L50: =L55*$E$4/L$15 -> 0.016300177 | ... N50: =N55*$E$4/N$15 -> 0.009795191
D51: Annual Average % | I51: =AVERAGE(E50:I50) -> 0.062074889 | N51: =AVERAGE(E50:N50) -> 0.039725796
D52: Cumulative % | E52: =E$17*(E50/E$19) -> 0.096899225 | F52: =F$17*(F50/F$19) -> 0.1720149 | G52: =G$17*(G50/G$19) -> 0.23024411 | H52: =H$17*(H50/H$19) -> 0.27538303 | I52: =I$17*(I50/I$19) -> 0.31037444 | J52: =J$17*(J50/J$19) -> 0.33749957 | K52: =K$17*(K50/K$19) -> 0.3585268 | L52: =L$17*(L50/L$19) -> 0.37482697 | ... N52: =N$17*(N50/N$19) -> 0.39725796
D53: Test Case Annual | E53: =10*E50 -> 0.96899225 | F53: =10*F50 -> 0.75115678 | G53: =10*G50 -> 0.58229208 | H53: =10*H50 -> 0.45138921 | I53: =10*I50 -> 0.34991411 | J53: =10*J50 -> 0.27125125 | K53: =10*K50 -> 0.21027229 | L53: =10*L50 -> 0.16300177 | ... N53: =10*N50 -> 0.09795191
D54: Test Case Cumulative | E54: =10*E52 -> 0.96899225 | F54: =10*F52 -> 1.720149 | G54: =10*G52 -> 2.3024411 | H54: =10*H52 -> 2.7538303 | I54: =10*I52 -> 3.1037444 | J54: =10*J52 -> 3.3749957 | K54: =10*K52 -> 3.585268 | L54: =10*L52 -> 3.7482697 | ... N54: =10*N52 -> 3.9725796
C55: USD Simple | D55: Annual % | E55: =$E9+($E$10*$E$11) -> 0.125 | F55: =$E9+($E$10*$E$11) -> 0.125 | G55: =$E9+($E$10*$E$11) -> 0.125 | H55: =$E9+($E$10*$E$11) -> 0.125 | I55: =$E9+($E$10*$E$11) -> 0.125 | J55: =$E9+($E$10*$E$11) -> 0.125 | K55: =$E9+($E$10*$E$11) -> 0.125 | L55: =$E9+($E$10*$E$11) -> 0.125 | ... N55: =$E9+($E$10*$E$11) -> 0.125
D56: Test Case Annual | E56: =E53*E$15 -> 125000 | F56: =F53*F$15 -> 125000 | G56: =G53*G$15 -> 125000 | H56: =H53*H$15 -> 125000 | I56: =I53*I$15 -> 125000 | J56: =J53*J$15 -> 125000 | K56: =K53*K$15 -> 125000 | L56: =L53*L$15 -> 125000 | ... N56: =N53*N$15 -> 125000
D57: Test Case Cumulative | E57: =E56 -> 125000 | F57: =E57+F56 -> 250000 | G57: =F57+G56 -> 375000 | H57: =G57+H56 -> 500000 | I57: =H57+I56 -> 625000 | J57: =I57+J56 -> 750000 | K57: =J57+K56 -> 875000 | L57: =K57+L56 -> 1000000 | M57: =L57+M56 -> 1125000 | N57: =M57+N56 -> 1250000
C58: USD Compounded | D58: Annual % | E58: =E52*E$15/$E$4 -> 0.125 | F58: =F52*F$15/$E$4-E58 -> 0.16125 | G58: =G52*G$15/$E$4-F58-E58 -> 0.2080125 | H58: =H52*H$15/$E$4-G58-F58-E58 -> 0.26833612 | I58: =I52*I$15/$E$4-H58-G58-F58-E58 -> 0.3461536 | J58: =J52*J$15/$E$4-I58-H58-G58-F58-E58 -> 0.44653815 | K58: =K52*K$15/$E$4-J58-I58-H58-G58-F58-E58 -> 0.57603421 | L58: =L52*L$15/$E$4-K58-J58-I58-H58-G58-F58-E58 -> 0.74308413 | M58: =M52*M$15/$E$4-L58-K58-J58-I58-H58-G58-F58-E58 -> 0.95857853 | N58: =N52*N$15/$E$4-M58-L58-K58-J58-I58-H58-G58-F58-E58 -> 1.2365663
D59: Annual Average % | I59: =AVERAGE(E58:I58) -> 0.22175045 | N59: =AVERAGE(E58:N58) -> 0.50695535
D60: Test Case Annual | E60: =E62 -> 125000 | F60: =F62-E62 -> 161250 | G60: =G62-F62 -> 208012.5 | H60: =H62-G62 -> 268336.12 | I60: =I62-H62 -> 346153.6 | J60: =J62-I62 -> 446538.15 | K60: =K62-J62 -> 576034.21 | L60: =L62-K62 -> 743084.13 | M60: =M62-L62 -> 958578.53 | N60: =N62-M62 -> 1236566.3
D61: Test Case Annual Average | I61: =AVERAGE(E60:I60) -> 221750.45 | N61: =AVERAGE(E60:N60) -> 506955.35
D62: Test Case Cumulative | E62: =E54*E$15 -> 125000 | F62: =F54*F$15 -> 286250 | G62: =G54*G$15 -> 494262.5 | H62: =H54*H$15 -> 762598.62 | I62: =I54*I$15 -> 1108752.2 | J62: =J54*J$15 -> 1555290.4 | K62: =K54*K$15 -> 2131324.6 | L62: =L54*L$15 -> 2874408.7 | ... N62: =N54*N$15 -> 5069553.5
B64: Stable Provider / Bitcoin Borrower | C64: Test Case | D64: ="10 BTC / "&TEXT($E$4*10, "$###0.00,,")&"M USD" -> 10 BTC / $1.00M USD | E64: Year 1 | F64: Year 2 | G64: Year 3 | H64: Year 4 | I64: Year 5 | J64: Year 6 | K64: Year 7 | L64: Year 8 | M64: Year 9 | N64: Year 10
B66: Bitcoin Growth Yield (BiGY) | C66: BTC | D66: Total Annual % | E66: =E$23 -> 0.4496124 | F66: =F$23 -> 0.34853675 | G66: =G$23 -> 0.27018352 | H66: =H$23 -> 0.20944459 | I66: =I$23 -> 0.16236015 | J66: =J$23 -> 0.12586058 | K66: =K$23 -> 0.097566342 | L66: =L$23 -> 0.075632823 | ... N66: =N$23 -> 0.045449686
D67: Total Annual Average % | I67: =AVERAGE(E66:I66) -> 0.28802748 | N67: =AVERAGE(E66:N66) -> 0.18432769
D68: Cumulative % | E68: =E$17*(E66/E$19) -> 0.4496124 | F68: =F$17*(F66/F$19) -> 0.79814915 | G68: =G$17*(G66/G$19) -> 1.0683327 | H68: =H$17*(H66/H$19) -> 1.2777773 | I68: =I$17*(I66/I$19) -> 1.4401374 | J68: =J$17*(J66/J$19) -> 1.565998 | K68: =K$17*(K66/K$19) -> 1.6635643 | L68: =L$17*(L66/L$19) -> 1.7391972 | ... N68: =N$17*(N66/N$19) -> 1.8432769
D69: Test Case Annual | E69: =10*E66 -> 4.496124 | F69: =10*F66 -> 3.4853675 | G69: =10*G66 -> 2.7018352 | H69: =10*H66 -> 2.0944459 | I69: =10*I66 -> 1.6236015 | J69: =10*J66 -> 1.2586058 | K69: =10*K66 -> 0.97566342 | L69: =10*L66 -> 0.75632823 | ... N69: =10*N66 -> 0.45449686
D70: Test Case Cumulative | E70: =10*E68 -> 4.496124 | F70: =10*F68 -> 7.9814915 | G70: =10*G68 -> 10.683327 | H70: =10*H68 -> 12.777773 | I70: =10*I68 -> 14.401374 | J70: =10*J68 -> 15.65998 | K70: =10*K68 -> 16.635643 | L70: =10*L68 -> 17.391972 | ... N70: =10*N68 -> 18.432769
C71: USD Simple | D71: Annual % | E71: =E66*E$15/$E$4 -> 0.58 | F71: =F66*F$15/$E$4 -> 0.58 | G71: =G66*G$15/$E$4 -> 0.58 | H71: =H66*H$15/$E$4 -> 0.58 | I71: =I66*I$15/$E$4 -> 0.58 | J71: =J66*J$15/$E$4 -> 0.58 | K71: =K66*K$15/$E$4 -> 0.58 | L71: =L66*L$15/$E$4 -> 0.58 | ... N71: =N66*N$15/$E$4 -> 0.58
D72: Test Case Annual | E72: =E69*E$15 -> 580000 | F72: =F69*F$15 -> 580000 | G72: =G69*G$15 -> 580000 | H72: =H69*H$15 -> 580000 | I72: =I69*I$15 -> 580000 | J72: =J69*J$15 -> 580000 | K72: =K69*K$15 -> 580000 | L72: =L69*L$15 -> 580000 | ... N72: =N69*N$15 -> 580000
D73: Test Case Cumulative | E73: =E72 -> 580000 | F73: =E73+F72 -> 1160000 | G73: =F73+G72 -> 1740000 | H73: =G73+H72 -> 2320000 | I73: =H73+I72 -> 2900000 | J73: =I73+J72 -> 3480000 | K73: =J73+K72 -> 4060000 | L73: =K73+L72 -> 4640000 | M73: =L73+M72 -> 5220000 | N73: =M73+N72 -> 5800000
C74: USD Compounded | D74: Annual % | E74: =E68*E$15/$E$4 -> 0.58 | F74: =F68*F$15/$E$4-E74 -> 0.7482 | G74: =G68*G$15/$E$4-F74-E74 -> 0.965178 | H74: =H68*H$15/$E$4-G74-F74-E74 -> 1.2450796 | I74: =I68*I$15/$E$4-H74-G74-F74-E74 -> 1.6061527 | J74: =J68*J$15/$E$4-I74-H74-G74-F74-E74 -> 2.071937 | K74: =K68*K$15/$E$4-J74-I74-H74-G74-F74-E74 -> 2.6727987 | L74: =L68*L$15/$E$4-K74-J74-I74-H74-G74-F74-E74 -> 3.4479104 | M74: =M68*M$15/$E$4-L74-K74-J74-I74-H74-G74-F74-E74 -> 4.4478044 | N74: =N68*N$15/$E$4-M74-L74-K74-J74-I74-H74-G74-F74-E74 -> 5.7376676
D75: Annual Average % | I75: =AVERAGE(E74:I74) -> 1.0289221 | N75: =AVERAGE(E74:N74) -> 2.3522728
D76: Test Case Annual | E76: =E78 -> 580000 | F76: =F78-E78 -> 748200 | G76: =G78-F78 -> 965178 | H76: =H78-G78 -> 1245079.6 | I76: =I78-H78 -> 1606152.7 | J76: =J78-I78 -> 2071937 | K76: =K78-J78 -> 2672798.7 | L76: =L78-K78 -> 3447910.4 | M76: =M78-L78 -> 4447804.4 | N76: =N78-M78 -> 5737667.6
D77: Test Case Annual Average | I77: =AVERAGE(E76:I76) -> 1028922.1 | N77: =AVERAGE(E76:N76) -> 2352272.8
D78: Test Case Cumulative | E78: =E70*E$15 -> 580000 | F78: =F70*F$15 -> 1328200 | G78: =G70*G$15 -> 2293378 | H78: =H70*H$15 -> 3538457.6 | I78: =I70*I$15 -> 5144610.3 | J78: =J70*J$15 -> 7216547.3 | K78: =K70*K$15 -> 9889346 | L78: =L70*L$15 -> 13337256 | ... N78: =N70*N$15 -> 23522728
B79: Bitcoin Liquidity Yield (BiLY) | C79: BTC | D79: Annual % | E79: =E$25 -> 0.055503876 | F79: =F$25 -> 0.052018509 | G79: =G$25 -> 0.049316673 | H79: =H$25 -> 0.047222227 | I79: =I$25 -> 0.045598626 | J79: =J$25 -> 0.04434002 | K79: =K$25 -> 0.043364357 | L79: =L$25 -> 0.042608028 | ... N79: =N$25 -> 0.041567231
D80: Annual Average % | I80: =AVERAGE(E79:I79) -> 0.049931982 | N80: =AVERAGE(E79:N79) -> 0.046356127
D81: Cumulative % | E81: =E$27 -> 0.055503876 | F81: =F$27 -> 0.10752238 | G81: =G$27 -> 0.15683906 | H81: =H$27 -> 0.20406129 | I81: =I$27 -> 0.24965991 | J81: =J$27 -> 0.29399993 | K81: =K$27 -> 0.33736429 | L81: =L$27 -> 0.37997232 | ... N81: =N$27 -> 0.46356127
D82: Test Case Annual | E82: =10*E79 -> 0.55503876 | F82: =10*F79 -> 0.52018509 | G82: =10*G79 -> 0.49316673 | H82: =10*H79 -> 0.47222227 | I82: =10*I79 -> 0.45598626 | J82: =10*J79 -> 0.4434002 | K82: =10*K79 -> 0.43364357 | L82: =10*L79 -> 0.42608028 | ... N82: =10*N79 -> 0.41567231
D83: Test Case Cumulative | E83: =10*E81 -> 0.55503876 | F83: =10*F81 -> 1.0752238 | G83: =10*G81 -> 1.5683906 | H83: =10*H81 -> 2.0406129 | I83: =10*I81 -> 2.4965991 | J83: =10*J81 -> 2.9399993 | K83: =10*K81 -> 3.3736429 | L83: =10*L81 -> 3.7997232 | ... N83: =10*N81 -> 4.6356127
C84: USD Simple | D84: Annual % | E84: =E79*E$15/$E$4 -> 0.0716 | F84: =F79*F$15/$E$4 -> 0.086564 | G84: =G79*G$15/$E$4 -> 0.10586756 | H84: =H79*H$15/$E$4 -> 0.13076915 | I84: =I79*I$15/$E$4 -> 0.16289221 | J84: =J79*J$15/$E$4 -> 0.20433095 | K84: =K79*K$15/$E$4 -> 0.25778692 | L84: =L79*L$15/$E$4 -> 0.32674513 | ... N84: =N79*N$15/$E$4 -> 0.53045457
D85: Annual Average % | I85: =AVERAGE(E84:I84) -> 0.11153858 | N85: =AVERAGE(E84:N84) -> 0.22927117
D86: Test Case Annual | E86: =E82*E$15 -> 71600 | F86: =F82*F$15 -> 86564 | G86: =G82*G$15 -> 105867.56 | H86: =H82*H$15 -> 130769.15 | I86: =I82*I$15 -> 162892.21 | J86: =J82*J$15 -> 204330.95 | K86: =K82*K$15 -> 257786.92 | L86: =L82*L$15 -> 326745.13 | ... N86: =N82*N$15 -> 530454.57
D87: Test Case Annual Average | I87: =AVERAGE(E86:I86) -> 111538.58 | N87: =AVERAGE(E86:N86) -> 229271.17
D88: Test Case Cumulative | E88: =E86 -> 71600 | F88: =E88+F86 -> 158164 | G88: =F88+G86 -> 264031.56 | H88: =G88+H86 -> 394800.71 | I88: =H88+I86 -> 557692.92 | J88: =I88+J86 -> 762023.87 | K88: =J88+K86 -> 1019810.8 | L88: =K88+L86 -> 1346555.9 | M88: =L88+M86 -> 1762257.1 | N88: =M88+N86 -> 2292711.7
C89: USD Compounded | D89: Annual % | E89: =E81*E$15/$E$4 -> 0.0716 | F89: =F81*F$15/$E$4-E89 -> 0.107328 | G89: =G81*G$15/$E$4-F89-E89 -> 0.15775668 | H89: =H81*H$15/$E$4-G89-F89-E89 -> 0.22840771 | I89: =I81*I$15/$E$4-H89-G89-F89-E89 -> 0.326769 | J89: =J81*J$15/$E$4-I89-H89-G89-F89-E89 -> 0.46297075 | K89: =K81*K$15/$E$4-J89-I89-H89-G89-F89-E89 -> 0.65068824 | L89: =L81*L$15/$E$4-K89-J89-I89-H89-G89-F89-E89 -> 0.90834604 | M89: =M81*M$15/$E$4-L89-K89-J89-I89-H89-G89-F89-E89 -> 1.2607225 | N89: =N81*N$15/$E$4-M89-L89-K89-J89-I89-H89-G89-F89-E89 -> 1.7410853
D90: Annual Average % | I90: =AVERAGE(E89:I89) -> 0.17837228 | N90: =AVERAGE(E89:N89) -> 0.59156742
D91: Test Case Annual | E91: =E93 -> 71600 | F91: =F93-E93 -> 107328 | G91: =G93-F93 -> 157756.68 | H91: =H93-G93 -> 228407.71 | I91: =I93-H93 -> 326769 | J91: =J93-I93 -> 462970.75 | K91: =K93-J93 -> 650688.24 | L91: =L93-K93 -> 908346.04 | M91: =M93-L93 -> 1260722.5 | N91: =N93-M93 -> 1741085.3
D92: Test Case Annual Average | I92: =AVERAGE(E91:I91) -> 178372.28 | N92: =AVERAGE(E91:N91) -> 591567.42
D93: Test Case Cumulative | E93: =E83*E$15 -> 71600 | F93: =F83*F$15 -> 178928 | G93: =G83*G$15 -> 336684.68 | H93: =H83*H$15 -> 565092.39 | I93: =I83*I$15 -> 891861.39 | J93: =J83*J$15 -> 1354832.1 | K93: =K83*K$15 -> 2005520.4 | L93: =L83*L$15 -> 2913866.4 | ... N93: =N83*N$15 -> 5915674.2
B94: Bitcoin Transaction Yield (BiTY) | C94: BTC | D94: Annual % | E94: =E$28 -> 0.027751938 | F94: =F$28 -> 0.026009254 | G94: =G$28 -> 0.024658337 | H94: =H$28 -> 0.023611114 | I94: =I$28 -> 0.022799313 | J94: =J$28 -> 0.02217001 | K94: =K$28 -> 0.021682178 | L94: =L$28 -> 0.021304014 | ... N94: =N$28 -> 0.020783615
D95: Annual Average % | I95: =AVERAGE(E94:I94) -> 0.024965991 | N95: =AVERAGE(E94:N94) -> 0.023178064
D96: Cumulative % | E96: =E$30 -> 0.027751938 | F96: =F$30 -> 0.053761192 | G96: =G$30 -> 0.078419529 | H96: =H$30 -> 0.10203064 | I96: =I$30 -> 0.12482996 | J96: =J$30 -> 0.14699997 | K96: =K$30 -> 0.16868214 | L96: =L$30 -> 0.18998616 | ... N96: =N$30 -> 0.23178064
D97: Test Case Annual | E97: =10*E94 -> 0.27751938 | F97: =10*F94 -> 0.26009254 | G97: =10*G94 -> 0.24658337 | H97: =10*H94 -> 0.23611114 | I97: =10*I94 -> 0.22799313 | J97: =10*J94 -> 0.2217001 | K97: =10*K94 -> 0.21682178 | L97: =10*L94 -> 0.21304014 | ... N97: =10*N94 -> 0.20783615
D98: Test Case Cumulative | E98: =10*E96 -> 0.27751938 | F98: =10*F96 -> 0.53761192 | G98: =10*G96 -> 0.78419529 | H98: =10*H96 -> 1.0203064 | I98: =10*I96 -> 1.2482996 | J98: =10*J96 -> 1.4699997 | K98: =10*K96 -> 1.6868214 | L98: =10*L96 -> 1.8998616 | ... N98: =10*N96 -> 2.3178064
C99: USD Simple | D99: Annual % | E99: =E94*E$15/$E$4 -> 0.0358 | F99: =F94*F$15/$E$4 -> 0.043282 | G99: =G94*G$15/$E$4 -> 0.05293378 | H99: =H94*H$15/$E$4 -> 0.065384576 | I99: =I94*I$15/$E$4 -> 0.081446103 | J99: =J94*J$15/$E$4 -> 0.10216547 | K99: =K94*K$15/$E$4 -> 0.12889346 | L99: =L94*L$15/$E$4 -> 0.16337256 | ... N99: =N94*N$15/$E$4 -> 0.26522728
D100: Annual Average % | I100: =AVERAGE(E99:I99) -> 0.055769292 | N100: =AVERAGE(E99:N99) -> 0.11463558
D101: Test Case Annual | E101: =E97*E$15 -> 35800 | F101: =F97*F$15 -> 43282 | G101: =G97*G$15 -> 52933.78 | H101: =H97*H$15 -> 65384.576 | I101: =I97*I$15 -> 81446.103 | J101: =J97*J$15 -> 102165.47 | K101: =K97*K$15 -> 128893.46 | L101: =L97*L$15 -> 163372.56 | ... N101: =N97*N$15 -> 265227.28
D102: Test Case Annual Average | I102: =AVERAGE(E101:I101) -> 55769.292 | N102: =AVERAGE(E101:N101) -> 114635.58
D103: Test Case Cumulative | E103: =E101 -> 35800 | F103: =E103+F101 -> 79082 | G103: =F103+G101 -> 132015.78 | H103: =G103+H101 -> 197400.36 | I103: =H103+I101 -> 278846.46 | J103: =I103+J101 -> 381011.93 | K103: =J103+K101 -> 509905.39 | L103: =K103+L101 -> 673277.96 | M103: =L103+M101 -> 881128.56 | N103: =M103+N101 -> 1146355.8
C104: USD Compounded | D104: Annual % | E104: =E96*E$15/$E$4 -> 0.0358 | F104: =F96*F$15/$E$4-E104 -> 0.053664 | G104: =G96*G$15/$E$4-F104-E104 -> 0.07887834 | H104: =H96*H$15/$E$4-G104-F104-E104 -> 0.11420385 | I104: =I96*I$15/$E$4-H104-G104-F104-E104 -> 0.1633845 | J104: =J96*J$15/$E$4-I104-H104-G104-F104-E104 -> 0.23148537 | K104: =K96*K$15/$E$4-J104-I104-H104-G104-F104-E104 -> 0.32534412 | L104: =L96*L$15/$E$4-K104-J104-I104-H104-G104-F104-E104 -> 0.45417302 | M104: =M96*M$15/$E$4-L104-K104-J104-I104-H104-G104-F104-E104 -> 0.63036124 | N104: =N96*N$15/$E$4-M104-L104-K104-J104-I104-H104-G104-F104-E104 -> 0.87054267
D105: Annual Average % | I105: =AVERAGE(E104:I104) -> 0.089186139 | N105: =AVERAGE(E104:N104) -> 0.29578371
D106: Test Case Annual | E106: =E108 -> 35800 | F106: =F108-E108 -> 53664 | G106: =G108-F108 -> 78878.34 | H106: =H108-G108 -> 114203.85 | I106: =I108-H108 -> 163384.5 | J106: =J108-I108 -> 231485.37 | K106: =K108-J108 -> 325344.12 | L106: =L108-K108 -> 454173.02 | M106: =M108-L108 -> 630361.24 | N106: =N108-M108 -> 870542.67
D107: Test Case Annual Average | I107: =AVERAGE(E106:I106) -> 89186.139 | N107: =AVERAGE(E106:N106) -> 295783.71
D108: Test Case Cumulative | E108: =E98*E$15 -> 35800 | F108: =F98*F$15 -> 89464 | G108: =G98*G$15 -> 168342.34 | H108: =H98*H$15 -> 282546.19 | I108: =I98*I$15 -> 445930.69 | J108: =J98*J$15 -> 677416.07 | K108: =K98*K$15 -> 1002760.2 | L108: =L98*L$15 -> 1456933.2 | ... N108: =N98*N$15 -> 2957837.1
B109: Total Yield | C109: BTC | D109: Annual % | E109: =E66+E79+E94-E34-E50 -> 0.35844961 | F109: =F66+F79+F94-F34-F50 -> 0.29135629 | G109: =G66+G79+G94-G34-G50 -> 0.23934596 | H109: =H66+H79+H94-H34-H50 -> 0.19902788 | I109: =I66+I79+I94-I34-I50 -> 0.16777355 | J109: =J66+J79+J94-J34-J50 -> 0.14354539 | K109: =K66+K79+K94-K34-K50 -> 0.12476386 | L109: =L66+L79+L94-L34-L50 -> 0.11020455 | ... N109: =N66+N79+N94-N34-N50 -> 0.090169188
...

Sheet 3.5X
B2: Bitcoin Lightning Credit Derivatives A permissionless, decentralized and distributed strategy for ultra-high yields using leveraged bitcoin growth and lightning transaction fee exposure | D2: Bitcoin Yield Estimate Variables BiGY = Bitcoin Growth Yield (CAGR) BiLY = Bitcoin Liquidity Yield BiTY = Bitcoin Transaction Yield | G2: Bitcoin Yield Estimate 5 Year Summary SR = Stable Receiver SB = Stable Balancer SP = Stable Provider | K2: Lightning Bank 5 Year Revenue Summary TVL = Total Value Locked
K3: Bitcoin TVL | L3: Measure | M3: BTC | N3: USD
D4: Bitcoin USD Price Start | E4: 100000 | G4: SR USD Comp. | H4: Annual Avg. % | I4: =I43 -> 0.17740036 | K4: =C127 -> 20000 | L4: Annual Avg. | M4: =I128 -> 461.12774 | N4: =M4*$I$15 -> 1.647289e+08
D5: Annual Bitcoin Growth Yield % | E5: =SUMMARY!H6 -> 0.29 | G5: SP BiGY BTC | H5: Annual Avg. % | I5: =I67 -> 0.36003435 | K5: =C127 -> 20000 | L5: Cumulative | M5: =I129 -> 2305.6387 | N5: =M5*$I$15 -> 8.2364451e+08
D6: Annual Bitcoin Liquidity Yield % | E6: =SUMMARY!L6 -> 0.02 | G6: SP BiLY BTC | H6: Annual Avg. % | I6: =I80 -> 0.059931982 | K6: =C130 -> 400000 | L6: Annual Avg. | M6: =I131 -> 9222.5549 | N6: =M6*$I$15 -> 3.294578e+09
D7: Annual Bitcoin Transaction Yield % | E7: =SUMMARY!P6 -> 0.01 | G7: SP BiTY BTC | H7: Annual Avg. % | I7: =I95 -> 0.029965991 | K7: =C130 -> 400000 | L7: Cumulative | M7: =I132 -> 46112.774 | N7: =M7*$I$15 -> 1.647289e+10
D8: Stable Receiver Security Annual USD % | E8: =SUMMARY!L21 -> 0.1 | G8: SP BiLY SR BTC | H8: Annual Avg. % | I8: =-I35 -> -0.049659911 | K8: =C133 -> 1000000 | L8: Annual Avg. | M8: =I134 -> 23056.387 | N8: =M8*$I$15 -> 8.2364451e+09
D9: Stable Balancer Security Annual USD % | E9: =SUMMARY!L22 -> 0.05 | G9: SP BiLY SB BTC | H9: Annual Avg. % | I9: =-I51 -> -0.080697355 | K9: =C133 -> 1000000 | L9: Cumulative | M9: =I135 -> 115281.94 | N9: =M9*$I$15 -> 4.1182226e+10
D10: Stable Balancer Debt Annual USD % | E10: =SUMMARY!L23 -> 0.075 | G10: SP Total BTC | H10: Annual Avg. % | I10: =I110 -> 0.31957506
D11: Stable Provider Debt-to-Value % | E11: =SUMMARY!L10 -> 1.5
B13: Yield Estimate Calculator | C13: Unit of Account | D13: Measure | E13: Year 1 | F13: Year 2 | G13: Year 3 | H13: Year 4 | I13: Year 5 | J13: Year 6 | K13: Year 7 | L13: Year 8 | M13: Year 9 | N13: Year 10
B15: Bitcoin | C15: USD | D15: Price | E15: =($E$4 * $E$5) + $E$4 -> 129000 | F15: =(E15 * $E$5) + E15 -> 166410 | G15: =(F15 * $E$5) + F15 -> 214668.9 | H15: =(G15 * $E$5) + G15 -> 276922.88 | I15: =(H15 * $E$5) + H15 -> 357230.52 | J15: =(I15 * $E$5) + I15 -> 460827.37 | K15: =(J15 * $E$5) + J15 -> 594467.3 | L15: =(K15 * $E$5) + K15 -> 766862.82 | M15: =(L15 * $E$5) + L15 -> 989253.04 | N15: =(M15 * $E$5) + M15 -> 1276136.4
D16: Marketcap | E16: =E15*21000000 -> 2709000000000 | F16: =F15*21000000 -> 3494610000000 | G16: =G15*21000000 -> 4508046900000 | H16: =H15*21000000 -> 5815380501000 | I16: =I15*21000000 -> 7.5018408e+12 | J16: =J15*21000000 -> 9.6773747e+12 | K16: =K15*21000000 -> 1.2483813e+13 | L16: =L15*21000000 -> 1.6104119e+13 | ... N16: =N15*21000000 -> 2.6798865e+13
B17: Bitcoin Growth Yield (BiGY) | C17: BTC | D17: Stable Security Cumulative % | E17: =(E15-$E4)/E15 -> 0.2248062 | F17: =(F15-$E4)/F15 -> 0.39907457 | G17: =(G15-$E4)/G15 -> 0.53416634 | H17: =(H15-$E4)/H15 -> 0.63888863 | I17: =(I15-$E4)/I15 -> 0.72006871 | J17: =(J15-$E4)/J15 -> 0.782999 | K17: =(K15-$E4)/K15 -> 0.83178217 | L17: =(L15-$E4)/L15 -> 0.86959858 | ... N17: =(N15-$E4)/N15 -> 0.92163847
D18: Stable Security Remaining % | E18: =1-E17 -> 0.7751938 | F18: =1-F17 -> 0.60092543 | G18: =1-G17 -> 0.46583366 | H18: =1-H17 -> 0.36111137 | I18: =1-I17 -> 0.27993129 | J18: =1-J17 -> 0.217001 | K18: =1-K17 -> 0.16821783 | L18: =1-L17 -> 0.13040142 | ... N18: =1-N17 -> 0.078361528
D19: Stable Security Annual % | E19: =E17 -> 0.2248062 | F19: =F17-E17 -> 0.17426837 | G19: =G17-F17 -> 0.13509176 | H19: =H17-G17 -> 0.1047223 | I19: =I17-H17 -> 0.081180075 | J19: =J17-I17 -> 0.06293029 | K19: =K17-J17 -> 0.048783171 | L19: =L17-K17 -> 0.037816412 | M19: =M17-L17 -> 0.029315048 | N19: =N17-M17 -> 0.022724843
D20: Stable Security Annual Average % | I20: =AVERAGE(E19:I19) -> 0.14401374 | N20: =AVERAGE(E19:N19) -> 0.092163847
D21: Stable Debt Annual % | E21: =$E$11*E19 -> 0.3372093 | F21: =$E$11*F19 -> 0.26140256 | G21: =$E$11*G19 -> 0.20263764 | H21: =$E$11*H19 -> 0.15708344 | I21: =$E$11*I19 -> 0.12177011 | J21: =$E$11*J19 -> 0.094395436 | K21: =$E$11*K19 -> 0.073174756 | L21: =$E$11*L19 -> 0.056724617 | ... N21: =$E$11*N19 -> 0.034087265
D22: Stable Debt Annual Avg. % | I22: =AVERAGE(E21:I21) -> 0.21602061 | N22: =AVERAGE(E21:N21) -> 0.13824577
D23: Total Annual % | E23: =E19+E21 -> 0.5620155 | F23: =F19+F21 -> 0.43567093 | G23: =G19+G21 -> 0.33772941 | H23: =H19+H21 -> 0.26180574 | I23: =I19+I21 -> 0.20295019 | J23: =J19+J21 -> 0.15732573 | K23: =K19+K21 -> 0.12195793 | L23: =L19+L21 -> 0.094541029 | ... N23: =N19+N21 -> 0.056812108
D24: Total Annual Average % | I24: =AVERAGE(E23:I23) -> 0.36003435 | N24: =AVERAGE(E23:N23) -> 0.23040962
B25: Bitcoin Liquidity Yield (BiLY) | C25: BTC | D25: Annual % | E25: =((1+$E$11)*$E$6)+($E$6*E18) -> 0.065503876 | F25: =((1+$E$11)*$E$6)+($E$6*F18) -> 0.062018509 | G25: =((1+$E$11)*$E$6)+($E$6*G18) -> 0.059316673 | H25: =((1+$E$11)*$E$6)+($E$6*H18) -> 0.057222227 | I25: =((1+$E$11)*$E$6)+($E$6*I18) -> 0.055598626 | J25: =((1+$E$11)*$E$6)+($E$6*J18) -> 0.05434002 | K25: =((1+$E$11)*$E$6)+($E$6*K18) -> 0.053364357 | L25: =((1+$E$11)*$E$6)+($E$6*L18) -> 0.052608028 | ... N25: =((1+$E$11)*$E$6)+($E$6*N18) -> 0.051567231
D26: Annual Average % | I26: =AVERAGE(E25:I25) -> 0.059931982 | N26: =AVERAGE(E25:N25) -> 0.056356127
D27: Cumulative % | E27: =E25 -> 0.065503876 | F27: =E27+F25 -> 0.12752238 | G27: =F27+G25 -> 0.18683906 | H27: =G27+H25 -> 0.24406129 | I27: =H27+I25 -> 0.29965991 | J27: =I27+J25 -> 0.35399993 | K27: =J27+K25 -> 0.40736429 | L27: =K27+L25 -> 0.45997232 | M27: =L27+M25 -> 0.51199404 | N27: =M27+N25 -> 0.56356127
B28: Bitcoin Transaction Yield (BiTY) | C28: BTC | D28: Annual % | E28: =((1+$E$11)*$E$7)+($E$7*E18) -> 0.032751938 | F28: =((1+$E$11)*$E$7)+($E$7*F18) -> 0.031009254 | G28: =((1+$E$11)*$E$7)+($E$7*G18) -> 0.029658337 | H28: =((1+$E$11)*$E$7)+($E$7*H18) -> 0.028611114 | I28: =((1+$E$11)*$E$7)+($E$7*I18) -> 0.027799313 | J28: =((1+$E$11)*$E$7)+($E$7*J18) -> 0.02717001 | K28: =((1+$E$11)*$E$7)+($E$7*K18) -> 0.026682178 | L28: =((1+$E$11)*$E$7)+($E$7*L18) -> 0.026304014 | ... N28: =((1+$E$11)*$E$7)+($E$7*N18) -> 0.025783615
D29: Annual Average % | I29: =AVERAGE(E28:I28) -> 0.029965991 | N29: =AVERAGE(E28:N28) -> 0.028178064
D30: Cumulative % | E30: =E28 -> 0.032751938 | F30: =E30+F28 -> 0.063761192 | G30: =F30+G28 -> 0.093419529 | H30: =G30+H28 -> 0.12203064 | I30: =H30+I28 -> 0.14982996 | J30: =I30+J28 -> 0.17699997 | K30: =J30+K28 -> 0.20368214 | L30: =K30+L28 -> 0.22998616 | M30: =L30+M28 -> 0.25599702 | N30: =M30+N28 -> 0.28178064
B32: Stable Receiver / Fiat Lender | C32: Test Case | D32: ="10 BTC / "&TEXT($E$4*10, "$###0.00,,")&"M USD" -> 10 BTC / $1.00M USD | E32: Year 1 | F32: Year 2 | G32: Year 3 | H32: Year 4 | I32: Year 5 | J32: Year 6 | K32: Year 7 | L32: Year 8 | M32: Year 9 | N32: Year 10
B34: Bitcoin Liquidity Yield (BiLY) | C34: BTC | D34: Total Annual % | E34: =E39*$E$4/E$15 -> 0.07751938 | F34: =F39*$E$4/F$15 -> 0.060092543 | G34: =G39*$E$4/G$15 -> 0.046583366 | H34: =H39*$E$4/H$15 -> 0.036111137 | I34: =I39*$E$4/I$15 -> 0.027993129 | J34: =J39*$E$4/J$15 -> 0.0217001 | K34: =K39*$E$4/K$15 -> 0.016821783 | L34: =L39*$E$4/L$15 -> 0.013040142 | ... N34: =N39*$E$4/N$15 -> 0.0078361528
D35: Total Annual Average % | I35: =AVERAGE(E34:I34) -> 0.049659911 | N35: =AVERAGE(E34:N34) -> 0.031780637
D36: Cumulative % | E36: =E$17*(E34/E$19) -> 0.07751938 | F36: =F$17*(F34/F$19) -> 0.13761192 | G36: =G$17*(G34/G$19) -> 0.18419529 | H36: =H$17*(H34/H$19) -> 0.22030643 | I36: =I$17*(I34/I$19) -> 0.24829955 | J36: =J$17*(J34/J$19) -> 0.26999965 | K36: =K$17*(K34/K$19) -> 0.28682144 | L36: =L$17*(L34/L$19) -> 0.29986158 | ... N36: =N$17*(N34/N$19) -> 0.31780637
D37: Test Case Annual | E37: =10*E34 -> 0.7751938 | F37: =10*F34 -> 0.60092543 | G37: =10*G34 -> 0.46583366 | H37: =10*H34 -> 0.36111137 | I37: =10*I34 -> 0.27993129 | J37: =10*J34 -> 0.217001 | K37: =10*K34 -> 0.16821783 | L37: =10*L34 -> 0.13040142 | ... N37: =10*N34 -> 0.078361528
D38: Test Case Cumulative | E38: =10*E36 -> 0.7751938 | F38: =10*F36 -> 1.3761192 | G38: =10*G36 -> 1.8419529 | H38: =10*H36 -> 2.2030643 | I38: =10*I36 -> 2.4829955 | J38: =10*J36 -> 2.6999965 | K38: =10*K36 -> 2.8682144 | L38: =10*L36 -> 2.9986158 | ... N38: =10*N36 -> 3.1780637
C39: USD Simple | D39: Annual % | E39: =E8 -> 0.1 | F39: =E39 -> 0.1 | G39: =F39 -> 0.1 | H39: =G39 -> 0.1 | I39: =H39 -> 0.1 | J39: =I39 -> 0.1 | K39: =J39 -> 0.1 | L39: =K39 -> 0.1 | M39: =L39 -> 0.1 | N39: =M39 -> 0.1
D40: Test Case Annual | E40: =E37*E$15 -> 100000 | F40: =F37*F$15 -> 100000 | G40: =G37*G$15 -> 100000 | H40: =H37*H$15 -> 100000 | I40: =I37*I$15 -> 100000 | J40: =J37*J$15 -> 100000 | K40: =K37*K$15 -> 100000 | L40: =L37*L$15 -> 100000 | ... N40: =N37*N$15 -> 100000
D41: Test Case Cumulative | E41: =E40 -> 100000 | F41: =E41+F40 -> 200000 | G41: =F41+G40 -> 300000 | H41: =G41+H40 -> 400000 | I41: =H41+I40 -> 500000 | J41: =I41+J40 -> 600000 | K41: =J41+K40 -> 700000 | L41: =K41+L40 -> 800000 | M41: =L41+M40 -> 900000 | N41: =M41+N40 -> 1000000
C42: USD Compounded | D42: Annual % | E42: =E36*E$15/$E$4 -> 0.1 | F42: =F36*F$15/$E$4-E42 -> 0.129 | G42: =G36*G$15/$E$4-F42-E42 -> 0.16641 | H42: =H36*H$15/$E$4-G42-F42-E42 -> 0.2146689 | I42: =I36*I$15/$E$4-H42-G42-F42-E42 -> 0.27692288 | J42: =J36*J$15/$E$4-I42-H42-G42-F42-E42 -> 0.35723052 | K42: =K36*K$15/$E$4-J42-I42-H42-G42-F42-E42 -> 0.46082737 | L42: =L36*L$15/$E$4-K42-J42-I42-H42-G42-F42-E42 -> 0.5944673 | M42: =M36*M$15/$E$4-L42-K42-J42-I42-H42-G42-F42-E42 -> 0.76686282 | N42: =N36*N$15/$E$4-M42-L42-K42-J42-I42-H42-G42-F42-E42 -> 0.98925304
D43: Annual Average % | I43: =AVERAGE(E42:I42) -> 0.17740036 | N43: =AVERAGE(E42:N42) -> 0.40556428
D44: Test Case Annual | E44: =E46 -> 100000 | F44: =F46-E46 -> 129000 | G44: =G46-F46 -> 166410 | H44: =H46-G46 -> 214668.9 | I44: =I46-H46 -> 276922.88 | J44: =J46-I46 -> 357230.52 | K44: =K46-J46 -> 460827.37 | L44: =L46-K46 -> 594467.3 | M44: =M46-L46 -> 766862.82 | N44: =N46-M46 -> 989253.04
D45: Test Case Annual Average | I45: =AVERAGE(E44:I44) -> 177400.36 | N45: =AVERAGE(E44:N44) -> 405564.28
D46: Test Case Cumulative | E46: =E38*E$15 -> 100000 | F46: =F38*F$15 -> 229000 | G46: =G38*G$15 -> 395410 | H46: =H38*H$15 -> 610078.9 | I46: =I38*I$15 -> 887001.78 | J46: =J38*J$15 -> 1244232.3 | K46: =K38*K$15 -> 1705059.7 | L46: =L38*L$15 -> 2299527 | ... N46: =N38*N$15 -> 4055642.8
B48: Stable Balancer / Lightning Service Provider | C48: Test Case | D48: ="10 BTC / "&TEXT($E$4*10, "$###0.00,,")&"M USD" -> 10 BTC / $1.00M USD | E48: Year 1 | F48: Year 2 | G48: Year 3 | H48: Year 4 | I48: Year 5 | J48: Year 6 | K48: Year 7 | L48: Year 8 | M48: Year 9 | N48: Year 10
B50: Bitcoin Liquidity Yield (BiLY) | C50: BTC | D50: Annual % | E50: =E55*$E$4/E$15 -> 0.12596899 | F50: =F55*$E$4/F$15 -> 0.097650382 | G50: =G55*$E$4/G$15 -> 0.07569797 | H50: =H55*$E$4/H$15 -> 0.058680597 | I50: =I55*$E$4/I$15 -> 0.045488835 | J50: =J55*$E$4/J$15 -> 0.035262663 | K50: =K55*$E$4/K$15 -> 0.027335397 | L50: =L55*$E$4/L$15 -> 0.021190231 | ... N50: =N55*$E$4/N$15 -> 0.012733748
D51: Annual Average % | I51: =AVERAGE(E50:I50) -> 0.080697355 | N51: =AVERAGE(E50:N50) -> 0.051643535
D52: Cumulative % | E52: =E$17*(E50/E$19) -> 0.12596899 | F52: =F$17*(F50/F$19) -> 0.22361937 | G52: =G$17*(G50/G$19) -> 0.29931734 | H52: =H$17*(H50/H$19) -> 0.35799794 | I52: =I$17*(I50/I$19) -> 0.40348678 | J52: =J$17*(J50/J$19) -> 0.43874944 | K52: =K$17*(K50/K$19) -> 0.46608484 | L52: =L$17*(L50/L$19) -> 0.48727507 | ... N52: =N$17*(N50/N$19) -> 0.51643535
D53: Test Case Annual | E53: =10*E50 -> 1.2596899 | F53: =10*F50 -> 0.97650382 | G53: =10*G50 -> 0.7569797 | H53: =10*H50 -> 0.58680597 | I53: =10*I50 -> 0.45488835 | J53: =10*J50 -> 0.35262663 | K53: =10*K50 -> 0.27335397 | L53: =10*L50 -> 0.21190231 | ... N53: =10*N50 -> 0.12733748
D54: Test Case Cumulative | E54: =10*E52 -> 1.2596899 | F54: =10*F52 -> 2.2361937 | G54: =10*G52 -> 2.9931734 | H54: =10*H52 -> 3.5799794 | I54: =10*I52 -> 4.0348678 | J54: =10*J52 -> 4.3874944 | K54: =10*K52 -> 4.6608484 | L54: =10*L52 -> 4.8727507 | ... N54: =10*N52 -> 5.1643535
C55: USD Simple | D55: Annual % | E55: =$E9+($E$10*$E$11) -> 0.1625 | F55: =$E9+($E$10*$E$11) -> 0.1625 | G55: =$E9+($E$10*$E$11) -> 0.1625 | H55: =$E9+($E$10*$E$11) -> 0.1625 | I55: =$E9+($E$10*$E$11) -> 0.1625 | J55: =$E9+($E$10*$E$11) -> 0.1625 | K55: =$E9+($E$10*$E$11) -> 0.1625 | L55: =$E9+($E$10*$E$11) -> 0.1625 | ... N55: =$E9+($E$10*$E$11) -> 0.1625
D56: Test Case Annual | E56: =E53*E$15 -> 162500 | F56: =F53*F$15 -> 162500 | G56: =G53*G$15 -> 162500 | H56: =H53*H$15 -> 162500 | I56: =I53*I$15 -> 162500 | J56: =J53*J$15 -> 162500 | K56: =K53*K$15 -> 162500 | L56: =L53*L$15 -> 162500 | ... N56: =N53*N$15 -> 162500
D57: Test Case Cumulative | E57: =E56 -> 162500 | F57: =E57+F56 -> 325000 | G57: =F57+G56 -> 487500 | H57: =G57+H56 -> 650000 | I57: =H57+I56 -> 812500 | J57: =I57+J56 -> 975000 | K57: =J57+K56 -> 1137500 | L57: =K57+L56 -> 1300000 | M57: =L57+M56 -> 1462500 | N57: =M57+N56 -> 1625000
C58: USD Compounded | D58: Annual % | E58: =E52*E$15/$E$4 -> 0.1625 | F58: =F52*F$15/$E$4-E58 -> 0.209625 | G58: =G52*G$15/$E$4-F58-E58 -> 0.27041625 | H58: =H52*H$15/$E$4-G58-F58-E58 -> 0.34883696 | I58: =I52*I$15/$E$4-H58-G58-F58-E58 -> 0.44999968 | J58: =J52*J$15/$E$4-I58-H58-G58-F58-E58 -> 0.58049959 | K58: =K52*K$15/$E$4-J58-I58-H58-G58-F58-E58 -> 0.74884447 | L58: =L52*L$15/$E$4-K58-J58-I58-H58-G58-F58-E58 -> 0.96600937 | M58: =M52*M$15/$E$4-L58-K58-J58-I58-H58-G58-F58-E58 -> 1.2461521 | N58: =N52*N$15/$E$4-M58-L58-K58-J58-I58-H58-G58-F58-E58 -> 1.6075362
D59: Annual Average % | I59: =AVERAGE(E58:I58) -> 0.28827558 | N59: =AVERAGE(E58:N58) -> 0.65904196
D60: Test Case Annual | E60: =E62 -> 162500 | F60: =F62-E62 -> 209625 | G60: =G62-F62 -> 270416.25 | H60: =H62-G62 -> 348836.96 | I60: =I62-H62 -> 449999.68 | J60: =J62-I62 -> 580499.59 | K60: =K62-J62 -> 748844.47 | L60: =L62-K62 -> 966009.37 | M60: =M62-L62 -> 1246152.1 | N60: =N62-M62 -> 1607536.2
D61: Test Case Annual Average | I61: =AVERAGE(E60:I60) -> 288275.58 | N61: =AVERAGE(E60:N60) -> 659041.96
D62: Test Case Cumulative | E62: =E54*E$15 -> 162500 | F62: =F54*F$15 -> 372125 | G62: =G54*G$15 -> 642541.25 | H62: =H54*H$15 -> 991378.21 | I62: =I54*I$15 -> 1441377.9 | J62: =J54*J$15 -> 2021877.5 | K62: =K54*K$15 -> 2770722 | L62: =L54*L$15 -> 3736731.3 | ... N62: =N54*N$15 -> 6590419.6
B64: Stable Provider / Bitcoin Borrower | C64: Test Case | D64: ="10 BTC / "&TEXT($E$4*10, "$###0.00,,")&"M USD" -> 10 BTC / $1.00M USD | E64: Year 1 | F64: Year 2 | G64: Year 3 | H64: Year 4 | I64: Year 5 | J64: Year 6 | K64: Year 7 | L64: Year 8 | M64: Year 9 | N64: Year 10
B66: Bitcoin Growth Yield (BiGY) | C66: BTC | D66: Total Annual % | E66: =E$23 -> 0.5620155 | F66: =F$23 -> 0.43567093 | G66: =G$23 -> 0.33772941 | H66: =H$23 -> 0.26180574 | I66: =I$23 -> 0.20295019 | J66: =J$23 -> 0.15732573 | K66: =K$23 -> 0.12195793 | L66: =L$23 -> 0.094541029 | ... N66: =N$23 -> 0.056812108
D67: Total Annual Average % | I67: =AVERAGE(E66:I66) -> 0.36003435 | N67: =AVERAGE(E66:N66) -> 0.23040962
D68: Cumulative % | E68: =E$17*(E66/E$19) -> 0.5620155 | F68: =F$17*(F66/F$19) -> 0.99768644 | G68: =G$17*(G66/G$19) -> 1.3354158 | H68: =H$17*(H66/H$19) -> 1.5972216 | I68: =I$17*(I66/I$19) -> 1.8001718 | J68: =J$17*(J66/J$19) -> 1.9574975 | K68: =K$17*(K66/K$19) -> 2.0794554 | L68: =L$17*(L66/L$19) -> 2.1739965 | ... N68: =N$17*(N66/N$19) -> 2.3040962
D69: Test Case Annual | E69: =10*E66 -> 5.620155 | F69: =10*F66 -> 4.3567093 | G69: =10*G66 -> 3.3772941 | H69: =10*H66 -> 2.6180574 | I69: =10*I66 -> 2.0295019 | J69: =10*J66 -> 1.5732573 | K69: =10*K66 -> 1.2195793 | L69: =10*L66 -> 0.94541029 | ... N69: =10*N66 -> 0.56812108
D70: Test Case Cumulative | E70: =10*E68 -> 5.620155 | F70: =10*F68 -> 9.9768644 | G70: =10*G68 -> 13.354158 | H70: =10*H68 -> 15.972216 | I70: =10*I68 -> 18.001718 | J70: =10*J68 -> 19.574975 | K70: =10*K68 -> 20.794554 | L70: =10*L68 -> 21.739965 | ... N70: =10*N68 -> 23.040962
C71: USD Simple | D71: Annual % | E71: =E66*E$15/$E$4 -> 0.725 | F71: =F66*F$15/$E$4 -> 0.725 | G71: =G66*G$15/$E$4 -> 0.725 | H71: =H66*H$15/$E$4 -> 0.725 | I71: =I66*I$15/$E$4 -> 0.725 | J71: =J66*J$15/$E$4 -> 0.725 | K71: =K66*K$15/$E$4 -> 0.725 | L71: =L66*L$15/$E$4 -> 0.725 | ... N71: =N66*N$15/$E$4 -> 0.725
D72: Test Case Annual | E72: =E69*E$15 -> 725000 | F72: =F69*F$15 -> 725000 | G72: =G69*G$15 -> 725000 | H72: =H69*H$15 -> 725000 | I72: =I69*I$15 -> 725000 | J72: =J69*J$15 -> 725000 | K72: =K69*K$15 -> 725000 | L72: =L69*L$15 -> 725000 | ... N72: =N69*N$15 -> 725000
D73: Test Case Cumulative | E73: =E72 -> 725000 | F73: =E73+F72 -> 1450000 | G73: =F73+G72 -> 2175000 | H73: =G73+H72 -> 2900000 | I73: =H73+I72 -> 3625000 | J73: =I73+J72 -> 4350000 | K73: =J73+K72 -> 5075000 | L73: =K73+L72 -> 5800000 | M73: =L73+M72 -> 6525000 | N73: =M73+N72 -> 7250000
C74: USD Compounded | D74: Annual % | E74: =E68*E$15/$E$4 -> 0.725 | F74: =F68*F$15/$E$4-E74 -> 0.93525 | G74: =G68*G$15/$E$4-F74-E74 -> 1.2064725 | H74: =H68*H$15/$E$4-G74-F74-E74 -> 1.5563495 | I74: =I68*I$15/$E$4-H74-G74-F74-E74 -> 2.0076909 | J74: =J68*J$15/$E$4-I74-H74-G74-F74-E74 -> 2.5899212 | K74: =K68*K$15/$E$4-J74-I74-H74-G74-F74-E74 -> 3.3409984 | L74: =L68*L$15/$E$4-K74-J74-I74-H74-G74-F74-E74 -> 4.3098879 | M74: =M68*M$15/$E$4-L74-K74-J74-I74-H74-G74-F74-E74 -> 5.5597554 | N74: =N68*N$15/$E$4-M74-L74-K74-J74-I74-H74-G74-F74-E74 -> 7.1720845
D75: Annual Average % | I75: =AVERAGE(E74:I74) -> 1.2861526 | N75: =AVERAGE(E74:N74) -> 2.940341
D76: Test Case Annual | E76: =E78 -> 725000 | F76: =F78-E78 -> 935250 | G76: =G78-F78 -> 1206472.5 | H76: =H78-G78 -> 1556349.5 | I76: =I78-H78 -> 2007690.9 | J76: =J78-I78 -> 2589921.2 | K76: =K78-J78 -> 3340998.4 | L76: =L78-K78 -> 4309887.9 | M76: =M78-L78 -> 5559755.4 | N76: =N78-M78 -> 7172084.5
D77: Test Case Annual Average | I77: =AVERAGE(E76:I76) -> 1286152.6 | N77: =AVERAGE(E76:N76) -> 2940341
D78: Test Case Cumulative | E78: =E70*E$15 -> 725000 | F78: =F70*F$15 -> 1660250 | G78: =G70*G$15 -> 2866722.5 | H78: =H70*H$15 -> 4423072 | I78: =I70*I$15 -> 6430762.9 | J78: =J70*J$15 -> 9020684.2 | K78: =K70*K$15 -> 12361683 | L78: =L70*L$15 -> 16671571 | ... N78: =N70*N$15 -> 29403410
B79: Bitcoin Liquidity Yield (BiLY) | C79: BTC | D79: Annual % | E79: =E$25 -> 0.065503876 | F79: =F$25 -> 0.062018509 | G79: =G$25 -> 0.059316673 | H79: =H$25 -> 0.057222227 | I79: =I$25 -> 0.055598626 | J79: =J$25 -> 0.05434002 | K79: =K$25 -> 0.053364357 | L79: =L$25 -> 0.052608028 | ... N79: =N$25 -> 0.051567231
D80: Annual Average % | I80: =AVERAGE(E79:I79) -> 0.059931982 | N80: =AVERAGE(E79:N79) -> 0.056356127
D81: Cumulative % | E81: =E$27 -> 0.065503876 | F81: =F$27 -> 0.12752238 | G81: =G$27 -> 0.18683906 | H81: =H$27 -> 0.24406129 | I81: =I$27 -> 0.29965991 | J81: =J$27 -> 0.35399993 | K81: =K$27 -> 0.40736429 | L81: =L$27 -> 0.45997232 | ... N81: =N$27 -> 0.56356127
D82: Test Case Annual | E82: =10*E79 -> 0.65503876 | F82: =10*F79 -> 0.62018509 | G82: =10*G79 -> 0.59316673 | H82: =10*H79 -> 0.57222227 | I82: =10*I79 -> 0.55598626 | J82: =10*J79 -> 0.5434002 | K82: =10*K79 -> 0.53364357 | L82: =10*L79 -> 0.52608028 | ... N82: =10*N79 -> 0.51567231
D83: Test Case Cumulative | E83: =10*E81 -> 0.65503876 | F83: =10*F81 -> 1.2752238 | G83: =10*G81 -> 1.8683906 | H83: =10*H81 -> 2.4406129 | I83: =10*I81 -> 2.9965991 | J83: =10*J81 -> 3.5399993 | K83: =10*K81 -> 4.0736429 | L83: =10*L81 -> 4.5997232 | ... N83: =10*N81 -> 5.6356127
C84: USD Simple | D84: Annual % | E84: =E79*E$15/$E$4 -> 0.0845 | F84: =F79*F$15/$E$4 -> 0.103205 | G84: =G79*G$15/$E$4 -> 0.12733445 | H84: =H79*H$15/$E$4 -> 0.15846144 | I84: =I79*I$15/$E$4 -> 0.19861526 | J84: =J79*J$15/$E$4 -> 0.25041368 | K84: =K79*K$15/$E$4 -> 0.31723365 | L84: =L79*L$15/$E$4 -> 0.40343141 | ... N84: =N79*N$15/$E$4 -> 0.65806821
D85: Annual Average % | I85: =AVERAGE(E84:I84) -> 0.13442323 | N85: =AVERAGE(E84:N84) -> 0.28158896
D86: Test Case Annual | E86: =E82*E$15 -> 84500 | F86: =F82*F$15 -> 103205 | G86: =G82*G$15 -> 127334.45 | H86: =H82*H$15 -> 158461.44 | I86: =I82*I$15 -> 198615.26 | J86: =J82*J$15 -> 250413.68 | K86: =K82*K$15 -> 317233.65 | L86: =L82*L$15 -> 403431.41 | ... N86: =N82*N$15 -> 658068.21
D87: Test Case Annual Average | I87: =AVERAGE(E86:I86) -> 134423.23 | N87: =AVERAGE(E86:N86) -> 281588.96
D88: Test Case Cumulative | E88: =E86 -> 84500 | F88: =E88+F86 -> 187705 | G88: =F88+G86 -> 315039.45 | H88: =G88+H86 -> 473500.89 | I88: =H88+I86 -> 672116.15 | J88: =I88+J86 -> 922529.83 | K88: =J88+K86 -> 1239763.5 | L88: =K88+L86 -> 1643194.9 | M88: =L88+M86 -> 2157821.4 | N88: =M88+N86 -> 2815889.6
C89: USD Compounded | D89: Annual % | E89: =E81*E$15/$E$4 -> 0.0845 | F89: =F81*F$15/$E$4-E89 -> 0.12771 | G89: =G81*G$15/$E$4-F89-E89 -> 0.18887535 | H89: =H81*H$15/$E$4-G89-F89-E89 -> 0.27477619 | I89: =I81*I$15/$E$4-H89-G89-F89-E89 -> 0.39461511 | J89: =J81*J$15/$E$4-I89-H89-G89-F89-E89 -> 0.56085191 | K89: =K81*K$15/$E$4-J89-I89-H89-G89-F89-E89 -> 0.79031893 | L89: =L81*L$15/$E$4-K89-J89-I89-H89-G89-F89-E89 -> 1.1057092 | M89: =M81*M$15/$E$4-L89-K89-J89-I89-H89-G89-F89-E89 -> 1.53756 | N89: =N81*N$15/$E$4-M89-L89-K89-J89-I89-H89-G89-F89-E89 -> 2.126894
D90: Annual Average % | I90: =AVERAGE(E89:I89) -> 0.21409533 | N90: =AVERAGE(E89:N89) -> 0.71918107
D91: Test Case Annual | E91: =E93 -> 84500 | F91: =F93-E93 -> 127710 | G91: =G93-F93 -> 188875.35 | H91: =H93-G93 -> 274776.19 | I91: =I93-H93 -> 394615.11 | J91: =J93-I93 -> 560851.91 | K91: =K93-J93 -> 790318.93 | L91: =L93-K93 -> 1105709.2 | M91: =M93-L93 -> 1537560 | N91: =N93-M93 -> 2126894
D92: Test Case Annual Average | I92: =AVERAGE(E91:I91) -> 214095.33 | N92: =AVERAGE(E91:N91) -> 719181.07
D93: Test Case Cumulative | E93: =E83*E$15 -> 84500 | F93: =F83*F$15 -> 212210 | G93: =G83*G$15 -> 401085.35 | H93: =H83*H$15 -> 675861.54 | I93: =I83*I$15 -> 1070476.6 | J93: =J83*J$15 -> 1631328.6 | K93: =K83*K$15 -> 2421647.5 | L93: =L83*L$15 -> 3527356.7 | ... N93: =N83*N$15 -> 7191810.7
B94: Bitcoin Transaction Yield (BiTY) | C94: BTC | D94: Annual % | E94: =E$28 -> 0.032751938 | F94: =F$28 -> 0.031009254 | G94: =G$28 -> 0.029658337 | H94: =H$28 -> 0.028611114 | I94: =I$28 -> 0.027799313 | J94: =J$28 -> 0.02717001 | K94: =K$28 -> 0.026682178 | L94: =L$28 -> 0.026304014 | ... N94: =N$28 -> 0.025783615
D95: Annual Average % | I95: =AVERAGE(E94:I94) -> 0.029965991 | N95: =AVERAGE(E94:N94) -> 0.028178064
D96: Cumulative % | E96: =E$30 -> 0.032751938 | F96: =F$30 -> 0.063761192 | G96: =G$30 -> 0.093419529 | H96: =H$30 -> 0.12203064 | I96: =I$30 -> 0.14982996 | J96: =J$30 -> 0.17699997 | K96: =K$30 -> 0.20368214 | L96: =L$30 -> 0.22998616 | ... N96: =N$30 -> 0.28178064
D97: Test Case Annual | E97: =10*E94 -> 0.32751938 | F97: =10*F94 -> 0.31009254 | G97: =10*G94 -> 0.29658337 | H97: =10*H94 -> 0.28611114 | I97: =10*I94 -> 0.27799313 | J97: =10*J94 -> 0.2717001 | K97: =10*K94 -> 0.26682178 | L97: =10*L94 -> 0.26304014 | ... N97: =10*N94 -> 0.25783615
D98: Test Case Cumulative | E98: =10*E96 -> 0.32751938 | F98: =10*F96 -> 0.63761192 | G98: =10*G96 -> 0.93419529 | H98: =10*H96 -> 1.2203064 | I98: =10*I96 -> 1.4982996 | J98: =10*J96 -> 1.7699997 | K98: =10*K96 -> 2.0368214 | L98: =10*L96 -> 2.2998616 | ... N98: =10*N96 -> 2.8178064
C99: USD Simple | D99: Annual % | E99: =E94*E$15/$E$4 -> 0.04225 | F99: =F94*F$15/$E$4 -> 0.0516025 | G99: =G94*G$15/$E$4 -> 0.063667225 | H99: =H94*H$15/$E$4 -> 0.07923072 | I99: =I94*I$15/$E$4 -> 0.099307629 | J99: =J94*J$15/$E$4 -> 0.12520684 | K99: =K94*K$15/$E$4 -> 0.15861683 | L99: =L94*L$15/$E$4 -> 0.20171571 | ... N99: =N94*N$15/$E$4 -> 0.3290341
D100: Annual Average % | I100: =AVERAGE(E99:I99) -> 0.067211615 | N100: =AVERAGE(E99:N99) -> 0.14079448
D101: Test Case Annual | E101: =E97*E$15 -> 42250 | F101: =F97*F$15 -> 51602.5 | G101: =G97*G$15 -> 63667.225 | H101: =H97*H$15 -> 79230.72 | I101: =I97*I$15 -> 99307.629 | J101: =J97*J$15 -> 125206.84 | K101: =K97*K$15 -> 158616.83 | L101: =L97*L$15 -> 201715.71 | ... N101: =N97*N$15 -> 329034.1
D102: Test Case Annual Average | I102: =AVERAGE(E101:I101) -> 67211.615 | N102: =AVERAGE(E101:N101) -> 140794.48
D103: Test Case Cumulative | E103: =E101 -> 42250 | F103: =E103+F101 -> 93852.5 | G103: =F103+G101 -> 157519.73 | H103: =G103+H101 -> 236750.45 | I103: =H103+I101 -> 336058.07 | J103: =I103+J101 -> 461264.92 | K103: =J103+K101 -> 619881.74 | L103: =K103+L101 -> 821597.45 | M103: =L103+M101 -> 1078910.7 | N103: =M103+N101 -> 1407944.8
C104: USD Compounded | D104: Annual % | E104: =E96*E$15/$E$4 -> 0.04225 | F104: =F96*F$15/$E$4-E104 -> 0.063855 | G104: =G96*G$15/$E$4-F104-E104 -> 0.094437675 | H104: =H96*H$15/$E$4-G104-F104-E104 -> 0.1373881 | I104: =I96*I$15/$E$4-H104-G104-F104-E104 -> 0.19730755 | J104: =J96*J$15/$E$4-I104-H104-G104-F104-E104 -> 0.28042596 | K104: =K96*K$15/$E$4-J104-I104-H104-G104-F104-E104 -> 0.39515947 | L104: =L96*L$15/$E$4-K104-J104-I104-H104-G104-F104-E104 -> 0.55285459 | M104: =M96*M$15/$E$4-L104-K104-J104-I104-H104-G104-F104-E104 -> 0.76877998 | N104: =N96*N$15/$E$4-M104-L104-K104-J104-I104-H104-G104-F104-E104 -> 1.063447
D105: Annual Average % | I105: =AVERAGE(E104:I104) -> 0.10704766 | N105: =AVERAGE(E104:N104) -> 0.35959053
D106: Test Case Annual | E106: =E108 -> 42250 | F106: =F108-E108 -> 63855 | G106: =G108-F108 -> 94437.675 | H106: =H108-G108 -> 137388.1 | I106: =I108-H108 -> 197307.55 | J106: =J108-I108 -> 280425.96 | K106: =K108-J108 -> 395159.47 | L106: =L108-K108 -> 552854.59 | M106: =M108-L108 -> 768779.98 | N106: =N108-M108 -> 1063447
D107: Test Case Annual Average | I107: =AVERAGE(E106:I106) -> 107047.66 | N107: =AVERAGE(E106:N106) -> 359590.53
D108: Test Case Cumulative | E108: =E98*E$15 -> 42250 | F108: =F98*F$15 -> 106105 | G108: =G98*G$15 -> 200542.68 | H108: =H98*H$15 -> 337930.77 | I108: =I98*I$15 -> 535238.32 | J108: =J98*J$15 -> 815664.28 | K108: =K98*K$15 -> 1210823.7 | L108: =L98*L$15 -> 1763678.3 | ... N108: =N98*N$15 -> 3595905.3
B109: Total Yield | C109: BTC | D109: Annual % | E109: =E66+E79+E94-E34-E50 -> 0.45678295 | F109: =F66+F79+F94-F34-F50 -> 0.37095577 | G109: =G66+G79+G94-G34-G50 -> 0.30442308 | H109: =H66+H79+H94-H34-H50 -> 0.25284735 | I109: =I66+I79+I94-I34-I50 -> 0.21286616 | J109: =J66+J79+J94-J34-J50 -> 0.18187299 | K109: =K66+K79+K94-K34-K50 -> 0.15784728 | L109: =L66+L79+L94-L34-L50 -> 0.1392227 | ... N109: =N66+N79+N94-N34-N50 -> 0.11359305
...

Sheet 4X
B2: Bitcoin Lightning Credit Derivatives A permissionless, decentralized and distributed strategy for ultra-high yields using leveraged bitcoin growth and lightning transaction fee exposure | D2: Bitcoin Yield Estimate Variables BiGY = Bitcoin Growth Yield (CAGR) BiLY = Bitcoin Liquidity Yield BiTY = Bitcoin Transaction Yield | G2: Bitcoin Yield Estimate 5 Year Summary SR = Stable Receiver SB = Stable Balancer SP = Stable Provider | K2: Lightning Bank 5 Year Revenue Summary TVL = Total Value Locked
K3: Bitcoin TVL | L3: Measure | M3: BTC | N3: USD
D4: Bitcoin USD Price Start | E4: 100000 | G4: SR USD Comp. | H4: Annual Avg. % | I4: =I43 -> 0.17740036 | K4: =C127 -> 20000 | L4: Annual Avg. | M4: =I128 -> 496.59911 | N4: =M4*$I$15 -> 1.7740036e+08
D5: Annual Bitcoin Growth Yield % | E5: =SUMMARY!H6 -> 0.29 | G5: SP BiGY BTC | H5: Annual Avg. % | I5: =I67 -> 0.43204122 | K5: =C127 -> 20000 | L5: Cumulative | M5: =I129 -> 2482.9955 | N5: =M5*$I$15 -> 8.8700178e+08
D6: Annual Bitcoin Liquidity Yield % | E6: =SUMMARY!L6 -> 0.02 | G6: SP BiLY BTC | H6: Annual Avg. % | I6: =I80 -> 0.069931982 | K6: =C130 -> 400000 | L6: Annual Avg. | M6: =I131 -> 9931.9822 | N6: =M6*$I$15 -> 3.5480071e+09
D7: Annual Bitcoin Transaction Yield % | E7: =SUMMARY!P6 -> 0.01 | G7: SP BiTY BTC | H7: Annual Avg. % | I7: =I95 -> 0.034965991 | K7: =C130 -> 400000 | L7: Cumulative | M7: =I132 -> 49659.911 | N7: =M7*$I$15 -> 1.7740036e+10
D8: Stable Receiver Security Annual USD % | E8: =SUMMARY!N21 -> 0.1 | G8: SP BiLY SR BTC | H8: Annual Avg. % | I8: =-I35 -> -0.049659911 | K8: =C133 -> 1000000 | L8: Annual Avg. | M8: =I134 -> 24829.955 | N8: =M8*$I$15 -> 8870017810
D9: Stable Balancer Security Annual USD % | E9: =SUMMARY!N22 -> 0.05 | G9: SP BiLY SB BTC | H9: Annual Avg. % | I9: =-I51 -> -0.099319822 | K9: =C133 -> 1000000 | L9: Cumulative | M9: =I135 -> 124149.78 | N9: =M9*$I$15 -> 4.4350089e+10
D10: Stable Balancer Debt Annual USD % | E10: =SUMMARY!N23 -> 0.075 | G10: SP Total BTC | H10: Annual Avg. % | I10: =I110 -> 0.38795947
D11: Stable Provider Debt-to-Value % | E11: =SUMMARY!N10 -> 2
B13: Yield Estimate Calculator | C13: Unit of Account | D13: Measure | E13: Year 1 | F13: Year 2 | G13: Year 3 | H13: Year 4 | I13: Year 5 | J13: Year 6 | K13: Year 7 | L13: Year 8 | M13: Year 9 | N13: Year 10
B15: Bitcoin | C15: USD | D15: Price | E15: =($E$4 * $E$5) + $E$4 -> 129000 | F15: =(E15 * $E$5) + E15 -> 166410 | G15: =(F15 * $E$5) + F15 -> 214668.9 | H15: =(G15 * $E$5) + G15 -> 276922.88 | I15: =(H15 * $E$5) + H15 -> 357230.52 | J15: =(I15 * $E$5) + I15 -> 460827.37 | K15: =(J15 * $E$5) + J15 -> 594467.3 | L15: =(K15 * $E$5) + K15 -> 766862.82 | M15: =(L15 * $E$5) + L15 -> 989253.04 | N15: =(M15 * $E$5) + M15 -> 1276136.4
D16: Marketcap | E16: =E15*21000000 -> 2709000000000 | F16: =F15*21000000 -> 3494610000000 | G16: =G15*21000000 -> 4508046900000 | H16: =H15*21000000 -> 5815380501000 | I16: =I15*21000000 -> 7.5018408e+12 | J16: =J15*21000000 -> 9.6773747e+12 | K16: =K15*21000000 -> 1.2483813e+13 | L16: =L15*21000000 -> 1.6104119e+13 | ... N16: =N15*21000000 -> 2.6798865e+13
B17: Bitcoin Growth Yield (BiGY) | C17: BTC | D17: Stable Security Cumulative % | E17: =(E15-$E4)/E15 -> 0.2248062 | F17: =(F15-$E4)/F15 -> 0.39907457 | G17: =(G15-$E4)/G15 -> 0.53416634 | H17: =(H15-$E4)/H15 -> 0.63888863 | I17: =(I15-$E4)/I15 -> 0.72006871 | J17: =(J15-$E4)/J15 -> 0.782999 | K17: =(K15-$E4)/K15 -> 0.83178217 | L17: =(L15-$E4)/L15 -> 0.86959858 | ... N17: =(N15-$E4)/N15 -> 0.92163847
D18: Stable Security Remaining % | E18: =1-E17 -> 0.7751938 | F18: =1-F17 -> 0.60092543 | G18: =1-G17 -> 0.46583366 | H18: =1-H17 -> 0.36111137 | I18: =1-I17 -> 0.27993129 | J18: =1-J17 -> 0.217001 | K18: =1-K17 -> 0.16821783 | L18: =1-L17 -> 0.13040142 | ... N18: =1-N17 -> 0.078361528
D19: Stable Security Annual % | E19: =E17 -> 0.2248062 | F19: =F17-E17 -> 0.17426837 | G19: =G17-F17 -> 0.13509176 | H19: =H17-G17 -> 0.1047223 | I19: =I17-H17 -> 0.081180075 | J19: =J17-I17 -> 0.06293029 | K19: =K17-J17 -> 0.048783171 | L19: =L17-K17 -> 0.037816412 | M19: =M17-L17 -> 0.029315048 | N19: =N17-M17 -> 0.022724843
D20: Stable Security Annual Average % | I20: =AVERAGE(E19:I19) -> 0.14401374 | N20: =AVERAGE(E19:N19) -> 0.092163847
D21: Stable Debt Annual % | E21: =$E$11*E19 -> 0.4496124 | F21: =$E$11*F19 -> 0.34853675 | G21: =$E$11*G19 -> 0.27018352 | H21: =$E$11*H19 -> 0.20944459 | I21: =$E$11*I19 -> 0.16236015 | J21: =$E$11*J19 -> 0.12586058 | K21: =$E$11*K19 -> 0.097566342 | L21: =$E$11*L19 -> 0.075632823 | ... N21: =$E$11*N19 -> 0.045449686
D22: Stable Debt Annual Avg. % | I22: =AVERAGE(E21:I21) -> 0.28802748 | N22: =AVERAGE(E21:N21) -> 0.18432769
D23: Total Annual % | E23: =E19+E21 -> 0.6744186 | F23: =F19+F21 -> 0.52280512 | G23: =G19+G21 -> 0.40527529 | H23: =H19+H21 -> 0.31416689 | I23: =I19+I21 -> 0.24354022 | J23: =J19+J21 -> 0.18879087 | K23: =K19+K21 -> 0.14634951 | L23: =L19+L21 -> 0.11344923 | ... N23: =N19+N21 -> 0.06817453
D24: Total Annual Average % | I24: =AVERAGE(E23:I23) -> 0.43204122 | N24: =AVERAGE(E23:N23) -> 0.27649154
B25: Bitcoin Liquidity Yield (BiLY) | C25: BTC | D25: Annual % | E25: =((1+$E$11)*$E$6)+($E$6*E18) -> 0.075503876 | F25: =((1+$E$11)*$E$6)+($E$6*F18) -> 0.072018509 | G25: =((1+$E$11)*$E$6)+($E$6*G18) -> 0.069316673 | H25: =((1+$E$11)*$E$6)+($E$6*H18) -> 0.067222227 | I25: =((1+$E$11)*$E$6)+($E$6*I18) -> 0.065598626 | J25: =((1+$E$11)*$E$6)+($E$6*J18) -> 0.06434002 | K25: =((1+$E$11)*$E$6)+($E$6*K18) -> 0.063364357 | L25: =((1+$E$11)*$E$6)+($E$6*L18) -> 0.062608028 | ... N25: =((1+$E$11)*$E$6)+($E$6*N18) -> 0.061567231
D26: Annual Average % | I26: =AVERAGE(E25:I25) -> 0.069931982 | N26: =AVERAGE(E25:N25) -> 0.066356127
D27: Cumulative % | E27: =E25 -> 0.075503876 | F27: =E27+F25 -> 0.14752238 | G27: =F27+G25 -> 0.21683906 | H27: =G27+H25 -> 0.28406129 | I27: =H27+I25 -> 0.34965991 | J27: =I27+J25 -> 0.41399993 | K27: =J27+K25 -> 0.47736429 | L27: =K27+L25 -> 0.53997232 | M27: =L27+M25 -> 0.60199404 | N27: =M27+N25 -> 0.66356127
B28: Bitcoin Transaction Yield (BiTY) | C28: BTC | D28: Annual % | E28: =((1+$E$11)*$E$7)+($E$7*E18) -> 0.037751938 | F28: =((1+$E$11)*$E$7)+($E$7*F18) -> 0.036009254 | G28: =((1+$E$11)*$E$7)+($E$7*G18) -> 0.034658337 | H28: =((1+$E$11)*$E$7)+($E$7*H18) -> 0.033611114 | I28: =((1+$E$11)*$E$7)+($E$7*I18) -> 0.032799313 | J28: =((1+$E$11)*$E$7)+($E$7*J18) -> 0.03217001 | K28: =((1+$E$11)*$E$7)+($E$7*K18) -> 0.031682178 | L28: =((1+$E$11)*$E$7)+($E$7*L18) -> 0.031304014 | ... N28: =((1+$E$11)*$E$7)+($E$7*N18) -> 0.030783615
D29: Annual Average % | I29: =AVERAGE(E28:I28) -> 0.034965991 | N29: =AVERAGE(E28:N28) -> 0.033178064
D30: Cumulative % | E30: =E28 -> 0.037751938 | F30: =E30+F28 -> 0.073761192 | G30: =F30+G28 -> 0.10841953 | H30: =G30+H28 -> 0.14203064 | I30: =H30+I28 -> 0.17482996 | J30: =I30+J28 -> 0.20699997 | K30: =J30+K28 -> 0.23868214 | L30: =K30+L28 -> 0.26998616 | M30: =L30+M28 -> 0.30099702 | N30: =M30+N28 -> 0.33178064
B32: Stable Receiver / Fiat Lender | C32: Test Case | D32: ="10 BTC / "&TEXT($E$4*10, "$###0.00,,")&"M USD" -> 10 BTC / $1.00M USD | E32: Year 1 | F32: Year 2 | G32: Year 3 | H32: Year 4 | I32: Year 5 | J32: Year 6 | K32: Year 7 | L32: Year 8 | M32: Year 9 | N32: Year 10
B34: Bitcoin Liquidity Yield (BiLY) | C34: BTC | D34: Total Annual % | E34: =E39*$E$4/E$15 -> 0.07751938 | F34: =F39*$E$4/F$15 -> 0.060092543 | G34: =G39*$E$4/G$15 -> 0.046583366 | H34: =H39*$E$4/H$15 -> 0.036111137 | I34: =I39*$E$4/I$15 -> 0.027993129 | J34: =J39*$E$4/J$15 -> 0.0217001 | K34: =K39*$E$4/K$15 -> 0.016821783 | L34: =L39*$E$4/L$15 -> 0.013040142 | ... N34: =N39*$E$4/N$15 -> 0.0078361528
D35: Total Annual Average % | I35: =AVERAGE(E34:I34) -> 0.049659911 | N35: =AVERAGE(E34:N34) -> 0.031780637
D36: Cumulative % | E36: =E$17*(E34/E$19) -> 0.07751938 | F36: =F$17*(F34/F$19) -> 0.13761192 | G36: =G$17*(G34/G$19) -> 0.18419529 | H36: =H$17*(H34/H$19) -> 0.22030643 | I36: =I$17*(I34/I$19) -> 0.24829955 | J36: =J$17*(J34/J$19) -> 0.26999965 | K36: =K$17*(K34/K$19) -> 0.28682144 | L36: =L$17*(L34/L$19) -> 0.29986158 | ... N36: =N$17*(N34/N$19) -> 0.31780637
D37: Test Case Annual | E37: =10*E34 -> 0.7751938 | F37: =10*F34 -> 0.60092543 | G37: =10*G34 -> 0.46583366 | H37: =10*H34 -> 0.36111137 | I37: =10*I34 -> 0.27993129 | J37: =10*J34 -> 0.217001 | K37: =10*K34 -> 0.16821783 | L37: =10*L34 -> 0.13040142 | ... N37: =10*N34 -> 0.078361528
D38: Test Case Cumulative | E38: =10*E36 -> 0.7751938 | F38: =10*F36 -> 1.3761192 | G38: =10*G36 -> 1.8419529 | H38: =10*H36 -> 2.2030643 | I38: =10*I36 -> 2.4829955 | J38: =10*J36 -> 2.6999965 | K38: =10*K36 -> 2.8682144 | L38: =10*L36 -> 2.9986158 | ... N38: =10*N36 -> 3.1780637
C39: USD Simple | D39: Annual % | E39: =E8 -> 0.1 | F39: =E39 -> 0.1 | G39: =F39 -> 0.1 | H39: =G39 -> 0.1 | I39: =H39 -> 0.1 | J39: =I39 -> 0.1 | K39: =J39 -> 0.1 | L39: =K39 -> 0.1 | M39: =L39 -> 0.1 | N39: =M39 -> 0.1
D40: Test Case Annual | E40: =E37*E$15 -> 100000 | F40: =F37*F$15 -> 100000 | G40: =G37*G$15 -> 100000 | H40: =H37*H$15 -> 100000 | I40: =I37*I$15 -> 100000 | J40: =J37*J$15 -> 100000 | K40: =K37*K$15 -> 100000 | L40: =L37*L$15 -> 100000 | ... N40: =N37*N$15 -> 100000
D41: Test Case Cumulative | E41: =E40 -> 100000 | F41: =E41+F40 -> 200000 | G41: =F41+G40 -> 300000 | H41: =G41+H40 -> 400000 | I41: =H41+I40 -> 500000 | J41: =I41+J40 -> 600000 | K41: =J41+K40 -> 700000 | L41: =K41+L40 -> 800000 | M41: =L41+M40 -> 900000 | N41: =M41+N40 -> 1000000
C42: USD Compounded | D42: Annual % | E42: =E36*E$15/$E$4 -> 0.1 | F42: =F36*F$15/$E$4-E42 -> 0.129 | G42: =G36*G$15/$E$4-F42-E42 -> 0.16641 | H42: =H36*H$15/$E$4-G42-F42-E42 -> 0.2146689 | I42: =I36*I$15/$E$4-H42-G42-F42-E42 -> 0.27692288 | J42: =J36*J$15/$E$4-I42-H42-G42-F42-E42 -> 0.35723052 | K42: =K36*K$15/$E$4-J42-I42-H42-G42-F42-E42 -> 0.46082737 | L42: =L36*L$15/$E$4-K42-J42-I42-H42-G42-F42-E42 -> 0.5944673 | M42: =M36*M$15/$E$4-L42-K42-J42-I42-H42-G42-F42-E42 -> 0.76686282 | N42: =N36*N$15/$E$4-M42-L42-K42-J42-I42-H42-G42-F42-E42 -> 0.98925304
D43: Annual Average % | I43: =AVERAGE(E42:I42) -> 0.17740036 | N43: =AVERAGE(E42:N42) -> 0.40556428
D44: Test Case Annual | E44: =E46 -> 100000 | F44: =F46-E46 -> 129000 | G44: =G46-F46 -> 166410 | H44: =H46-G46 -> 214668.9 | I44: =I46-H46 -> 276922.88 | J44: =J46-I46 -> 357230.52 | K44: =K46-J46 -> 460827.37 | L44: =L46-K46 -> 594467.3 | M44: =M46-L46 -> 766862.82 | N44: =N46-M46 -> 989253.04
D45: Test Case Annual Average | I45: =AVERAGE(E44:I44) -> 177400.36 | N45: =AVERAGE(E44:N44) -> 405564.28
D46: Test Case Cumulative | E46: =E38*E$15 -> 100000 | F46: =F38*F$15 -> 229000 | G46: =G38*G$15 -> 395410 | H46: =H38*H$15 -> 610078.9 | I46: =I38*I$15 -> 887001.78 | J46: =J38*J$15 -> 1244232.3 | K46: =K38*K$15 -> 1705059.7 | L46: =L38*L$15 -> 2299527 | ... N46: =N38*N$15 -> 4055642.8
B48: Stable Balancer / Lightning Service Provider | C48: Test Case | D48: ="10 BTC / "&TEXT($E$4*10, "$###0.00,,")&"M USD" -> 10 BTC / $1.00M USD | E48: Year 1 | F48: Year 2 | G48: Year 3 | H48: Year 4 | I48: Year 5 | J48: Year 6 | K48: Year 7 | L48: Year 8 | M48: Year 9 | N48: Year 10
B50: Bitcoin Liquidity Yield (BiLY) | C50: BTC | D50: Annual % | E50: =E55*$E$4/E$15 -> 0.15503876 | F50: =F55*$E$4/F$15 -> 0.12018509 | G50: =G55*$E$4/G$15 -> 0.093166733 | H50: =H55*$E$4/H$15 -> 0.072222273 | I50: =I55*$E$4/I$15 -> 0.055986258 | J50: =J55*$E$4/J$15 -> 0.0434002 | K50: =K55*$E$4/K$15 -> 0.033643566 | L50: =L55*$E$4/L$15 -> 0.026080284 | ... N50: =N55*$E$4/N$15 -> 0.015672306
D51: Annual Average % | I51: =AVERAGE(E50:I50) -> 0.099319822 | N51: =AVERAGE(E50:N50) -> 0.063561274
D52: Cumulative % | E52: =E$17*(E50/E$19) -> 0.15503876 | F52: =F$17*(F50/F$19) -> 0.27522384 | G52: =G$17*(G50/G$19) -> 0.36839058 | H52: =H$17*(H50/H$19) -> 0.44061285 | I52: =I$17*(I50/I$19) -> 0.49659911 | J52: =J$17*(J50/J$19) -> 0.53999931 | K52: =K$17*(K50/K$19) -> 0.57364288 | L52: =L$17*(L50/L$19) -> 0.59972316 | ... N52: =N$17*(N50/N$19) -> 0.63561274
D53: Test Case Annual | E53: =10*E50 -> 1.5503876 | F53: =10*F50 -> 1.2018509 | G53: =10*G50 -> 0.93166733 | H53: =10*H50 -> 0.72222273 | I53: =10*I50 -> 0.55986258 | J53: =10*J50 -> 0.434002 | K53: =10*K50 -> 0.33643566 | L53: =10*L50 -> 0.26080284 | ... N53: =10*N50 -> 0.15672306
D54: Test Case Cumulative | E54: =10*E52 -> 1.5503876 | F54: =10*F52 -> 2.7522384 | G54: =10*G52 -> 3.6839058 | H54: =10*H52 -> 4.4061285 | I54: =10*I52 -> 4.9659911 | J54: =10*J52 -> 5.3999931 | K54: =10*K52 -> 5.7364288 | L54: =10*L52 -> 5.9972316 | ... N54: =10*N52 -> 6.3561274
C55: USD Simple | D55: Annual % | E55: =$E9+($E$10*$E$11) -> 0.2 | F55: =$E9+($E$10*$E$11) -> 0.2 | G55: =$E9+($E$10*$E$11) -> 0.2 | H55: =$E9+($E$10*$E$11) -> 0.2 | I55: =$E9+($E$10*$E$11) -> 0.2 | J55: =$E9+($E$10*$E$11) -> 0.2 | K55: =$E9+($E$10*$E$11) -> 0.2 | L55: =$E9+($E$10*$E$11) -> 0.2 | ... N55: =$E9+($E$10*$E$11) -> 0.2
D56: Test Case Annual | E56: =E53*E$15 -> 200000 | F56: =F53*F$15 -> 200000 | G56: =G53*G$15 -> 200000 | H56: =H53*H$15 -> 200000 | I56: =I53*I$15 -> 200000 | J56: =J53*J$15 -> 200000 | K56: =K53*K$15 -> 200000 | L56: =L53*L$15 -> 200000 | ... N56: =N53*N$15 -> 200000
D57: Test Case Cumulative | E57: =E56 -> 200000 | F57: =E57+F56 -> 400000 | G57: =F57+G56 -> 600000 | H57: =G57+H56 -> 800000 | I57: =H57+I56 -> 1000000 | J57: =I57+J56 -> 1200000 | K57: =J57+K56 -> 1400000 | L57: =K57+L56 -> 1600000 | M57: =L57+M56 -> 1800000 | N57: =M57+N56 -> 2000000
C58: USD Compounded | D58: Annual % | E58: =E52*E$15/$E$4 -> 0.2 | F58: =F52*F$15/$E$4-E58 -> 0.258 | G58: =G52*G$15/$E$4-F58-E58 -> 0.33282 | H58: =H52*H$15/$E$4-G58-F58-E58 -> 0.4293378 | I58: =I52*I$15/$E$4-H58-G58-F58-E58 -> 0.55384576 | J58: =J52*J$15/$E$4-I58-H58-G58-F58-E58 -> 0.71446103 | K58: =K52*K$15/$E$4-J58-I58-H58-G58-F58-E58 -> 0.92165473 | L58: =L52*L$15/$E$4-K58-J58-I58-H58-G58-F58-E58 -> 1.1889346 | M58: =M52*M$15/$E$4-L58-K58-J58-I58-H58-G58-F58-E58 -> 1.5337256 | N58: =N52*N$15/$E$4-M58-L58-K58-J58-I58-H58-G58-F58-E58 -> 1.9785061
D59: Annual Average % | I59: =AVERAGE(E58:I58) -> 0.35480071 | N59: =AVERAGE(E58:N58) -> 0.81112856
D60: Test Case Annual | E60: =E62 -> 200000 | F60: =F62-E62 -> 258000 | G60: =G62-F62 -> 332820 | H60: =H62-G62 -> 429337.8 | I60: =I62-H62 -> 553845.76 | J60: =J62-I62 -> 714461.03 | K60: =K62-J62 -> 921654.73 | L60: =L62-K62 -> 1188934.6 | M60: =M62-L62 -> 1533725.6 | N60: =N62-M62 -> 1978506.1
D61: Test Case Annual Average | I61: =AVERAGE(E60:I60) -> 354800.71 | N61: =AVERAGE(E60:N60) -> 811128.56
D62: Test Case Cumulative | E62: =E54*E$15 -> 200000 | F62: =F54*F$15 -> 458000 | G62: =G54*G$15 -> 790820 | H62: =H54*H$15 -> 1220157.8 | I62: =I54*I$15 -> 1774003.6 | J62: =J54*J$15 -> 2488464.6 | K62: =K54*K$15 -> 3410119.3 | L62: =L54*L$15 -> 4599053.9 | ... N62: =N54*N$15 -> 8111285.6
B64: Stable Provider / Bitcoin Borrower | C64: Test Case | D64: ="10 BTC / "&TEXT($E$4*10, "$###0.00,,")&"M USD" -> 10 BTC / $1.00M USD | E64: Year 1 | F64: Year 2 | G64: Year 3 | H64: Year 4 | I64: Year 5 | J64: Year 6 | K64: Year 7 | L64: Year 8 | M64: Year 9 | N64: Year 10
B66: Bitcoin Growth Yield (BiGY) | C66: BTC | D66: Total Annual % | E66: =E$23 -> 0.6744186 | F66: =F$23 -> 0.52280512 | G66: =G$23 -> 0.40527529 | H66: =H$23 -> 0.31416689 | I66: =I$23 -> 0.24354022 | J66: =J$23 -> 0.18879087 | K66: =K$23 -> 0.14634951 | L66: =L$23 -> 0.11344923 | ... N66: =N$23 -> 0.06817453
D67: Total Annual Average % | I67: =AVERAGE(E66:I66) -> 0.43204122 | N67: =AVERAGE(E66:N66) -> 0.27649154
D68: Cumulative % | E68: =E$17*(E66/E$19) -> 0.6744186 | F68: =F$17*(F66/F$19) -> 1.1972237 | G68: =G$17*(G66/G$19) -> 1.602499 | H68: =H$17*(H66/H$19) -> 1.9166659 | I68: =I$17*(I66/I$19) -> 2.1602061 | J68: =J$17*(J66/J$19) -> 2.348997 | K68: =K$17*(K66/K$19) -> 2.4953465 | L68: =L$17*(L66/L$19) -> 2.6087957 | ... N68: =N$17*(N66/N$19) -> 2.7649154
D69: Test Case Annual | E69: =10*E66 -> 6.744186 | F69: =10*F66 -> 5.2280512 | G69: =10*G66 -> 4.0527529 | H69: =10*H66 -> 3.1416689 | I69: =10*I66 -> 2.4354022 | J69: =10*J66 -> 1.8879087 | K69: =10*K66 -> 1.4634951 | L69: =10*L66 -> 1.1344923 | ... N69: =10*N66 -> 0.6817453
D70: Test Case Cumulative | E70: =10*E68 -> 6.744186 | F70: =10*F68 -> 11.972237 | G70: =10*G68 -> 16.02499 | H70: =10*H68 -> 19.166659 | I70: =10*I68 -> 21.602061 | J70: =10*J68 -> 23.48997 | K70: =10*K68 -> 24.953465 | L70: =10*L68 -> 26.087957 | ... N70: =10*N68 -> 27.649154
C71: USD Simple | D71: Annual % | E71: =E66*E$15/$E$4 -> 0.87 | F71: =F66*F$15/$E$4 -> 0.87 | G71: =G66*G$15/$E$4 -> 0.87 | H71: =H66*H$15/$E$4 -> 0.87 | I71: =I66*I$15/$E$4 -> 0.87 | J71: =J66*J$15/$E$4 -> 0.87 | K71: =K66*K$15/$E$4 -> 0.87 | L71: =L66*L$15/$E$4 -> 0.87 | ... N71: =N66*N$15/$E$4 -> 0.87
D72: Test Case Annual | E72: =E69*E$15 -> 870000 | F72: =F69*F$15 -> 870000 | G72: =G69*G$15 -> 870000 | H72: =H69*H$15 -> 870000 | I72: =I69*I$15 -> 870000 | J72: =J69*J$15 -> 870000 | K72: =K69*K$15 -> 870000 | L72: =L69*L$15 -> 870000 | ... N72: =N69*N$15 -> 870000
D73: Test Case Cumulative | E73: =E72 -> 870000 | F73: =E73+F72 -> 1740000 | G73: =F73+G72 -> 2610000 | H73: =G73+H72 -> 3480000 | I73: =H73+I72 -> 4350000 | J73: =I73+J72 -> 5220000 | K73: =J73+K72 -> 6090000 | L73: =K73+L72 -> 6960000 | M73: =L73+M72 -> 7830000 | N73: =M73+N72 -> 8700000
C74: USD Compounded | D74: Annual % | E74: =E68*E$15/$E$4 -> 0.87 | F74: =F68*F$15/$E$4-E74 -> 1.1223 | G74: =G68*G$15/$E$4-F74-E74 -> 1.447767 | H74: =H68*H$15/$E$4-G74-F74-E74 -> 1.8676194 | I74: =I68*I$15/$E$4-H74-G74-F74-E74 -> 2.4092291 | J74: =J68*J$15/$E$4-I74-H74-G74-F74-E74 -> 3.1079055 | K74: =K68*K$15/$E$4-J74-I74-H74-G74-F74-E74 -> 4.0091981 | L74: =L68*L$15/$E$4-K74-J74-I74-H74-G74-F74-E74 -> 5.1718655 | M74: =M68*M$15/$E$4-L74-K74-J74-I74-H74-G74-F74-E74 -> 6.6717065 | N74: =N68*N$15/$E$4-M74-L74-K74-J74-I74-H74-G74-F74-E74 -> 8.6065014
D75: Annual Average % | I75: =AVERAGE(E74:I74) -> 1.5433831 | N75: =AVERAGE(E74:N74) -> 3.5284093
D76: Test Case Annual | E76: =E78 -> 870000 | F76: =F78-E78 -> 1122300 | G76: =G78-F78 -> 1447767 | H76: =H78-G78 -> 1867619.4 | I76: =I78-H78 -> 2409229.1 | J76: =J78-I78 -> 3107905.5 | K76: =K78-J78 -> 4009198.1 | L76: =L78-K78 -> 5171865.5 | M76: =M78-L78 -> 6671706.5 | N76: =N78-M78 -> 8606501.4
D77: Test Case Annual Average | I77: =AVERAGE(E76:I76) -> 1543383.1 | N77: =AVERAGE(E76:N76) -> 3528409.3
D78: Test Case Cumulative | E78: =E70*E$15 -> 870000 | F78: =F70*F$15 -> 1992300 | G78: =G70*G$15 -> 3440067 | H78: =H70*H$15 -> 5307686.4 | I78: =I70*I$15 -> 7716915.5 | J78: =J70*J$15 -> 10824821 | K78: =K70*K$15 -> 14834019 | L78: =L70*L$15 -> 20005885 | ... N78: =N70*N$15 -> 35284093
B79: Bitcoin Liquidity Yield (BiLY) | C79: BTC | D79: Annual % | E79: =E$25 -> 0.075503876 | F79: =F$25 -> 0.072018509 | G79: =G$25 -> 0.069316673 | H79: =H$25 -> 0.067222227 | I79: =I$25 -> 0.065598626 | J79: =J$25 -> 0.06434002 | K79: =K$25 -> 0.063364357 | L79: =L$25 -> 0.062608028 | ... N79: =N$25 -> 0.061567231
D80: Annual Average % | I80: =AVERAGE(E79:I79) -> 0.069931982 | N80: =AVERAGE(E79:N79) -> 0.066356127
D81: Cumulative % | E81: =E$27 -> 0.075503876 | F81: =F$27 -> 0.14752238 | G81: =G$27 -> 0.21683906 | H81: =H$27 -> 0.28406129 | I81: =I$27 -> 0.34965991 | J81: =J$27 -> 0.41399993 | K81: =K$27 -> 0.47736429 | L81: =L$27 -> 0.53997232 | ... N81: =N$27 -> 0.66356127
D82: Test Case Annual | E82: =10*E79 -> 0.75503876 | F82: =10*F79 -> 0.72018509 | G82: =10*G79 -> 0.69316673 | H82: =10*H79 -> 0.67222227 | I82: =10*I79 -> 0.65598626 | J82: =10*J79 -> 0.6434002 | K82: =10*K79 -> 0.63364357 | L82: =10*L79 -> 0.62608028 | ... N82: =10*N79 -> 0.61567231
D83: Test Case Cumulative | E83: =10*E81 -> 0.75503876 | F83: =10*F81 -> 1.4752238 | G83: =10*G81 -> 2.1683906 | H83: =10*H81 -> 2.8406129 | I83: =10*I81 -> 3.4965991 | J83: =10*J81 -> 4.1399993 | K83: =10*K81 -> 4.7736429 | L83: =10*L81 -> 5.3997232 | ... N83: =10*N81 -> 6.6356127
C84: USD Simple | D84: Annual % | E84: =E79*E$15/$E$4 -> 0.0974 | F84: =F79*F$15/$E$4 -> 0.119846 | G84: =G79*G$15/$E$4 -> 0.14880134 | H84: =H79*H$15/$E$4 -> 0.18615373 | I84: =I79*I$15/$E$4 -> 0.23433831 | J84: =J79*J$15/$E$4 -> 0.29649642 | K84: =K79*K$15/$E$4 -> 0.37668038 | L84: =L79*L$15/$E$4 -> 0.48011769 | ... N84: =N79*N$15/$E$4 -> 0.78568185
D85: Annual Average % | I85: =AVERAGE(E84:I84) -> 0.15730788 | N85: =AVERAGE(E84:N84) -> 0.33390675
D86: Test Case Annual | E86: =E82*E$15 -> 97400 | F86: =F82*F$15 -> 119846 | G86: =G82*G$15 -> 148801.34 | H86: =H82*H$15 -> 186153.73 | I86: =I82*I$15 -> 234338.31 | J86: =J82*J$15 -> 296496.42 | K86: =K82*K$15 -> 376680.38 | L86: =L82*L$15 -> 480117.69 | ... N86: =N82*N$15 -> 785681.85
D87: Test Case Annual Average | I87: =AVERAGE(E86:I86) -> 157307.88 | N87: =AVERAGE(E86:N86) -> 333906.75
D88: Test Case Cumulative | E88: =E86 -> 97400 | F88: =E88+F86 -> 217246 | G88: =F88+G86 -> 366047.34 | H88: =G88+H86 -> 552201.07 | I88: =H88+I86 -> 786539.38 | J88: =I88+J86 -> 1083035.8 | K88: =J88+K86 -> 1459716.2 | L88: =K88+L86 -> 1939833.9 | M88: =L88+M86 -> 2553385.7 | N88: =M88+N86 -> 3339067.5
C89: USD Compounded | D89: Annual % | E89: =E81*E$15/$E$4 -> 0.0974 | F89: =F81*F$15/$E$4-E89 -> 0.148092 | G89: =G81*G$15/$E$4-F89-E89 -> 0.21999402 | H89: =H81*H$15/$E$4-G89-F89-E89 -> 0.32114467 | I89: =I81*I$15/$E$4-H89-G89-F89-E89 -> 0.46246121 | J89: =J81*J$15/$E$4-I89-H89-G89-F89-E89 -> 0.65873307 | K89: =K81*K$15/$E$4-J89-I89-H89-G89-F89-E89 -> 0.92994963 | L89: =L81*L$15/$E$4-K89-J89-I89-H89-G89-F89-E89 -> 1.3030723 | M89: =M81*M$15/$E$4-L89-K89-J89-I89-H89-G89-F89-E89 -> 1.8143974 | N89: =N81*N$15/$E$4-M89-L89-K89-J89-I89-H89-G89-F89-E89 -> 2.5127027
D90: Annual Average % | I90: =AVERAGE(E89:I89) -> 0.24981838 | N90: =AVERAGE(E89:N89) -> 0.84679471
D91: Test Case Annual | E91: =E93 -> 97400 | F91: =F93-E93 -> 148092 | G91: =G93-F93 -> 219994.02 | H91: =H93-G93 -> 321144.67 | I91: =I93-H93 -> 462461.21 | J91: =J93-I93 -> 658733.07 | K91: =K93-J93 -> 929949.63 | L91: =L93-K93 -> 1303072.3 | M91: =M93-L93 -> 1814397.4 | N91: =N93-M93 -> 2512702.7
D92: Test Case Annual Average | I92: =AVERAGE(E91:I91) -> 249818.38 | N92: =AVERAGE(E91:N91) -> 846794.71
D93: Test Case Cumulative | E93: =E83*E$15 -> 97400 | F93: =F83*F$15 -> 245492 | G93: =G83*G$15 -> 465486.02 | H93: =H83*H$15 -> 786630.69 | I93: =I83*I$15 -> 1249091.9 | J93: =J83*J$15 -> 1907825 | K93: =K83*K$15 -> 2837774.6 | L93: =L83*L$15 -> 4140846.9 | ... N93: =N83*N$15 -> 8467947.1
B94: Bitcoin Transaction Yield (BiTY) | C94: BTC | D94: Annual % | E94: =E$28 -> 0.037751938 | F94: =F$28 -> 0.036009254 | G94: =G$28 -> 0.034658337 | H94: =H$28 -> 0.033611114 | I94: =I$28 -> 0.032799313 | J94: =J$28 -> 0.03217001 | K94: =K$28 -> 0.031682178 | L94: =L$28 -> 0.031304014 | ... N94: =N$28 -> 0.030783615
D95: Annual Average % | I95: =AVERAGE(E94:I94) -> 0.034965991 | N95: =AVERAGE(E94:N94) -> 0.033178064
D96: Cumulative % | E96: =E$30 -> 0.037751938 | F96: =F$30 -> 0.073761192 | G96: =G$30 -> 0.10841953 | H96: =H$30 -> 0.14203064 | I96: =I$30 -> 0.17482996 | J96: =J$30 -> 0.20699997 | K96: =K$30 -> 0.23868214 | L96: =L$30 -> 0.26998616 | ... N96: =N$30 -> 0.33178064
D97: Test Case Annual | E97: =10*E94 -> 0.37751938 | F97: =10*F94 -> 0.36009254 | G97: =10*G94 -> 0.34658337 | H97: =10*H94 -> 0.33611114 | I97: =10*I94 -> 0.32799313 | J97: =10*J94 -> 0.3217001 | K97: =10*K94 -> 0.31682178 | L97: =10*L94 -> 0.31304014 | ... N97: =10*N94 -> 0.30783615
D98: Test Case Cumulative | E98: =10*E96 -> 0.37751938 | F98: =10*F96 -> 0.73761192 | G98: =10*G96 -> 1.0841953 | H98: =10*H96 -> 1.4203064 | I98: =10*I96 -> 1.7482996 | J98: =10*J96 -> 2.0699997 | K98: =10*K96 -> 2.3868214 | L98: =10*L96 -> 2.6998616 | ... N98: =10*N96 -> 3.3178064
C99: USD Simple | D99: Annual % | E99: =E94*E$15/$E$4 -> 0.0487 | F99: =F94*F$15/$E$4 -> 0.059923 | G99: =G94*G$15/$E$4 -> 0.07440067 | H99: =H94*H$15/$E$4 -> 0.093076864 | I99: =I94*I$15/$E$4 -> 0.11716915 | J99: =J94*J$15/$E$4 -> 0.14824821 | K99: =K94*K$15/$E$4 -> 0.18834019 | L99: =L94*L$15/$E$4 -> 0.24005885 | ... N99: =N94*N$15/$E$4 -> 0.39284093
D100: Annual Average % | I100: =AVERAGE(E99:I99) -> 0.078653938 | N100: =AVERAGE(E99:N99) -> 0.16695338
D101: Test Case Annual | E101: =E97*E$15 -> 48700 | F101: =F97*F$15 -> 59923 | G101: =G97*G$15 -> 74400.67 | H101: =H97*H$15 -> 93076.864 | I101: =I97*I$15 -> 117169.15 | J101: =J97*J$15 -> 148248.21 | K101: =K97*K$15 -> 188340.19 | L101: =L97*L$15 -> 240058.85 | ... N101: =N97*N$15 -> 392840.93
D102: Test Case Annual Average | I102: =AVERAGE(E101:I101) -> 78653.938 | N102: =AVERAGE(E101:N101) -> 166953.38
D103: Test Case Cumulative | E103: =E101 -> 48700 | F103: =E103+F101 -> 108623 | G103: =F103+G101 -> 183023.67 | H103: =G103+H101 -> 276100.53 | I103: =H103+I101 -> 393269.69 | J103: =I103+J101 -> 541517.9 | K103: =J103+K101 -> 729858.09 | L103: =K103+L101 -> 969916.94 | M103: =L103+M101 -> 1276692.8 | N103: =M103+N101 -> 1669533.8
C104: USD Compounded | D104: Annual % | E104: =E96*E$15/$E$4 -> 0.0487 | F104: =F96*F$15/$E$4-E104 -> 0.074046 | G104: =G96*G$15/$E$4-F104-E104 -> 0.10999701 | H104: =H96*H$15/$E$4-G104-F104-E104 -> 0.16057234 | I104: =I96*I$15/$E$4-H104-G104-F104-E104 -> 0.23123061 | J104: =J96*J$15/$E$4-I104-H104-G104-F104-E104 -> 0.32936654 | K104: =K96*K$15/$E$4-J104-I104-H104-G104-F104-E104 -> 0.46497481 | L104: =L96*L$15/$E$4-K104-J104-I104-H104-G104-F104-E104 -> 0.65153616 | M104: =M96*M$15/$E$4-L104-K104-J104-I104-H104-G104-F104-E104 -> 0.90719872 | N104: =N96*N$15/$E$4-M104-L104-K104-J104-I104-H104-G104-F104-E104 -> 1.2563514
D105: Annual Average % | I105: =AVERAGE(E104:I104) -> 0.12490919 | N105: =AVERAGE(E104:N104) -> 0.42339735
D106: Test Case Annual | E106: =E108 -> 48700 | F106: =F108-E108 -> 74046 | G106: =G108-F108 -> 109997.01 | H106: =H108-G108 -> 160572.34 | I106: =I108-H108 -> 231230.61 | J106: =J108-I108 -> 329366.54 | K106: =K108-J108 -> 464974.81 | L106: =L108-K108 -> 651536.16 | M106: =M108-L108 -> 907198.72 | N106: =N108-M108 -> 1256351.4
D107: Test Case Annual Average | I107: =AVERAGE(E106:I106) -> 124909.19 | N107: =AVERAGE(E106:N106) -> 423397.35
D108: Test Case Cumulative | E108: =E98*E$15 -> 48700 | F108: =F98*F$15 -> 122746 | G108: =G98*G$15 -> 232743.01 | H108: =H98*H$15 -> 393315.35 | I108: =I98*I$15 -> 624545.95 | J108: =J98*J$15 -> 953912.49 | K108: =K98*K$15 -> 1418887.3 | L108: =L98*L$15 -> 2070423.5 | ... N108: =N98*N$15 -> 4233973.5
B109: Total Yield | C109: BTC | D109: Annual % | E109: =E66+E79+E94-E34-E50 -> 0.55511628 | F109: =F66+F79+F94-F34-F50 -> 0.45055526 | G109: =G66+G79+G94-G34-G50 -> 0.3695002 | H109: =H66+H79+H94-H34-H50 -> 0.30666682 | I109: =I66+I79+I94-I34-I50 -> 0.25795878 | J109: =J66+J79+J94-J34-J50 -> 0.2202006 | K109: =K66+K79+K94-K34-K50 -> 0.1909307 | L109: =L66+L79+L94-L34-L50 -> 0.16824085 | ... N109: =N66+N79+N94-N34-N50 -> 0.13701692
...

Sheet 4.5X
B2: Bitcoin Lightning Credit Derivatives A permissionless, decentralized and distributed strategy for ultra-high yields using leveraged bitcoin growth and lightning transaction fee exposure | D2: Bitcoin Yield Estimate Variables BiGY = Bitcoin Growth Yield (CAGR) BiLY = Bitcoin Liquidity Yield BiTY = Bitcoin Transaction Yield | G2: Bitcoin Yield Estimate 5 Year Summary SR = Stable Receiver SB = Stable Balancer SP = Stable Provider | K2: Lightning Bank 5 Year Revenue Summary TVL = Total Value Locked
K3: Bitcoin TVL | L3: Measure | M3: BTC | N3: USD
D4: Bitcoin USD Price Start | E4: 100000 | G4: SR USD Comp. | H4: Annual Avg. % | I4: =I43 -> 0.17740036 | K4: =C127 -> 20000 | L4: Annual Avg. | M4: =I128 -> 524.18795 | N4: =M4*$I$15 -> 1.8725593e+08
D5: Annual Bitcoin Growth Yield % | E5: =SUMMARY!H6 -> 0.29 | G5: SP BiGY BTC | H5: Annual Avg. % | I5: =I67 -> 0.5040481 | K5: =C127 -> 20000 | L5: Cumulative | M5: =I129 -> 2620.9397 | N5: =M5*$I$15 -> 9.3627966e+08
D6: Annual Bitcoin Liquidity Yield % | E6: =SUMMARY!L6 -> 0.02 | G6: SP BiLY BTC | H6: Annual Avg. % | I6: =I80 -> 0.079931982 | K6: =C130 -> 400000 | L6: Annual Avg. | M6: =I131 -> 10483.759 | N6: =M6*$I$15 -> 3.7451186e+09
D7: Annual Bitcoin Transaction Yield % | E7: =SUMMARY!P6 -> 0.01 | G7: SP BiTY BTC | H7: Annual Avg. % | I7: =I95 -> 0.039965991 | K7: =C130 -> 400000 | L7: Cumulative | M7: =I132 -> 52418.795 | N7: =M7*$I$15 -> 1.8725593e+10
D8: Stable Receiver Security Annual USD % | E8: =SUMMARY!P21 -> 0.1 | G8: SP BiLY SR BTC | H8: Annual Avg. % | I8: =-I35 -> -0.049659911 | K8: =C133 -> 1000000 | L8: Annual Avg. | M8: =I134 -> 26209.397 | N8: =M8*$I$15 -> 9.3627966e+09
D9: Stable Balancer Security Annual USD % | E9: =SUMMARY!P22 -> 0.05 | G9: SP BiLY SB BTC | H9: Annual Avg. % | I9: =-I51 -> -0.11794229 | K9: =C133 -> 1000000 | L9: Cumulative | M9: =I135 -> 131046.99 | N9: =M9*$I$15 -> 4.6813983e+10
D10: Stable Balancer Debt Annual USD % | E10: =SUMMARY!P23 -> 0.075 | G10: SP Total BTC | H10: Annual Avg. % | I10: =I110 -> 0.45634387
D11: Stable Provider Debt-to-Value % | E11: =SUMMARY!P10 -> 2.5
B13: Yield Estimate Calculator | C13: Unit of Account | D13: Measure | E13: Year 1 | F13: Year 2 | G13: Year 3 | H13: Year 4 | I13: Year 5 | J13: Year 6 | K13: Year 7 | L13: Year 8 | M13: Year 9 | N13: Year 10
B15: Bitcoin | C15: USD | D15: Price | E15: =($E$4 * $E$5) + $E$4 -> 129000 | F15: =(E15 * $E$5) + E15 -> 166410 | G15: =(F15 * $E$5) + F15 -> 214668.9 | H15: =(G15 * $E$5) + G15 -> 276922.88 | I15: =(H15 * $E$5) + H15 -> 357230.52 | J15: =(I15 * $E$5) + I15 -> 460827.37 | K15: =(J15 * $E$5) + J15 -> 594467.3 | L15: =(K15 * $E$5) + K15 -> 766862.82 | M15: =(L15 * $E$5) + L15 -> 989253.04 | N15: =(M15 * $E$5) + M15 -> 1276136.4
D16: Marketcap | E16: =E15*21000000 -> 2709000000000 | F16: =F15*21000000 -> 3494610000000 | G16: =G15*21000000 -> 4508046900000 | H16: =H15*21000000 -> 5815380501000 | I16: =I15*21000000 -> 7.5018408e+12 | J16: =J15*21000000 -> 9.6773747e+12 | K16: =K15*21000000 -> 1.2483813e+13 | L16: =L15*21000000 -> 1.6104119e+13 | ... N16: =N15*21000000 -> 2.6798865e+13
B17: Bitcoin Growth Yield (BiGY) | C17: BTC | D17: Stable Security Cumulative % | E17: =(E15-$E4)/E15 -> 0.2248062 | F17: =(F15-$E4)/F15 -> 0.39907457 | G17: =(G15-$E4)/G15 -> 0.53416634 | H17: =(H15-$E4)/H15 -> 0.63888863 | I17: =(I15-$E4)/I15 -> 0.72006871 | J17: =(J15-$E4)/J15 -> 0.782999 | K17: =(K15-$E4)/K15 -> 0.83178217 | L17: =(L15-$E4)/L15 -> 0.86959858 | ... N17: =(N15-$E4)/N15 -> 0.92163847
D18: Stable Security Remaining % | E18: =1-E17 -> 0.7751938 | F18: =1-F17 -> 0.60092543 | G18: =1-G17 -> 0.46583366 | H18: =1-H17 -> 0.36111137 | I18: =1-I17 -> 0.27993129 | J18: =1-J17 -> 0.217001 | K18: =1-K17 -> 0.16821783 | L18: =1-L17 -> 0.13040142 | ... N18: =1-N17 -> 0.078361528
D19: Stable Security Annual % | E19: =E17 -> 0.2248062 | F19: =F17-E17 -> 0.17426837 | G19: =G17-F17 -> 0.13509176 | H19: =H17-G17 -> 0.1047223 | I19: =I17-H17 -> 0.081180075 | J19: =J17-I17 -> 0.06293029 | K19: =K17-J17 -> 0.048783171 | L19: =L17-K17 -> 0.037816412 | M19: =M17-L17 -> 0.029315048 | N19: =N17-M17 -> 0.022724843
D20: Stable Security Annual Average % | I20: =AVERAGE(E19:I19) -> 0.14401374 | N20: =AVERAGE(E19:N19) -> 0.092163847
D21: Stable Debt Annual % | E21: =$E$11*E19 -> 0.5620155 | F21: =$E$11*F19 -> 0.43567093 | G21: =$E$11*G19 -> 0.33772941 | H21: =$E$11*H19 -> 0.26180574 | I21: =$E$11*I19 -> 0.20295019 | J21: =$E$11*J19 -> 0.15732573 | K21: =$E$11*K19 -> 0.12195793 | L21: =$E$11*L19 -> 0.094541029 | ... N21: =$E$11*N19 -> 0.056812108
D22: Stable Debt Annual Avg. % | I22: =AVERAGE(E21:I21) -> 0.36003435 | N22: =AVERAGE(E21:N21) -> 0.23040962
D23: Total Annual % | E23: =E19+E21 -> 0.78682171 | F23: =F19+F21 -> 0.60993931 | G23: =G19+G21 -> 0.47282117 | H23: =H19+H21 -> 0.36652804 | I23: =I19+I21 -> 0.28413026 | J23: =J19+J21 -> 0.22025602 | K23: =K19+K21 -> 0.1707411 | L23: =L19+L21 -> 0.13235744 | ... N23: =N19+N21 -> 0.079536951
D24: Total Annual Average % | I24: =AVERAGE(E23:I23) -> 0.5040481 | N24: =AVERAGE(E23:N23) -> 0.32257347
B25: Bitcoin Liquidity Yield (BiLY) | C25: BTC | D25: Annual % | E25: =((1+$E$11)*$E$6)+($E$6*E18) -> 0.085503876 | F25: =((1+$E$11)*$E$6)+($E$6*F18) -> 0.082018509 | G25: =((1+$E$11)*$E$6)+($E$6*G18) -> 0.079316673 | H25: =((1+$E$11)*$E$6)+($E$6*H18) -> 0.077222227 | I25: =((1+$E$11)*$E$6)+($E$6*I18) -> 0.075598626 | J25: =((1+$E$11)*$E$6)+($E$6*J18) -> 0.07434002 | K25: =((1+$E$11)*$E$6)+($E$6*K18) -> 0.073364357 | L25: =((1+$E$11)*$E$6)+($E$6*L18) -> 0.072608028 | ... N25: =((1+$E$11)*$E$6)+($E$6*N18) -> 0.071567231
D26: Annual Average % | I26: =AVERAGE(E25:I25) -> 0.079931982 | N26: =AVERAGE(E25:N25) -> 0.076356127
D27: Cumulative % | E27: =E25 -> 0.085503876 | F27: =E27+F25 -> 0.16752238 | G27: =F27+G25 -> 0.24683906 | H27: =G27+H25 -> 0.32406129 | I27: =H27+I25 -> 0.39965991 | J27: =I27+J25 -> 0.47399993 | K27: =J27+K25 -> 0.54736429 | L27: =K27+L25 -> 0.61997232 | M27: =L27+M25 -> 0.69199404 | N27: =M27+N25 -> 0.76356127
B28: Bitcoin Transaction Yield (BiTY) | C28: BTC | D28: Annual % | E28: =((1+$E$11)*$E$7)+($E$7*E18) -> 0.042751938 | F28: =((1+$E$11)*$E$7)+($E$7*F18) -> 0.041009254 | G28: =((1+$E$11)*$E$7)+($E$7*G18) -> 0.039658337 | H28: =((1+$E$11)*$E$7)+($E$7*H18) -> 0.038611114 | I28: =((1+$E$11)*$E$7)+($E$7*I18) -> 0.037799313 | J28: =((1+$E$11)*$E$7)+($E$7*J18) -> 0.03717001 | K28: =((1+$E$11)*$E$7)+($E$7*K18) -> 0.036682178 | L28: =((1+$E$11)*$E$7)+($E$7*L18) -> 0.036304014 | ... N28: =((1+$E$11)*$E$7)+($E$7*N18) -> 0.035783615
D29: Annual Average % | I29: =AVERAGE(E28:I28) -> 0.039965991 | N29: =AVERAGE(E28:N28) -> 0.038178064
D30: Cumulative % | E30: =E28 -> 0.042751938 | F30: =E30+F28 -> 0.083761192 | G30: =F30+G28 -> 0.12341953 | H30: =G30+H28 -> 0.16203064 | I30: =H30+I28 -> 0.19982996 | J30: =I30+J28 -> 0.23699997 | K30: =J30+K28 -> 0.27368214 | L30: =K30+L28 -> 0.30998616 | M30: =L30+M28 -> 0.34599702 | N30: =M30+N28 -> 0.38178064
B32: Stable Receiver / Fiat Lender | C32: Test Case | D32: ="10 BTC / "&TEXT($E$4*10, "$###0.00,,")&"M USD" -> 10 BTC / $1.00M USD | E32: Year 1 | F32: Year 2 | G32: Year 3 | H32: Year 4 | I32: Year 5 | J32: Year 6 | K32: Year 7 | L32: Year 8 | M32: Year 9 | N32: Year 10
B34: Bitcoin Liquidity Yield (BiLY) | C34: BTC | D34: Total Annual % | E34: =E39*$E$4/E$15 -> 0.07751938 | F34: =F39*$E$4/F$15 -> 0.060092543 | G34: =G39*$E$4/G$15 -> 0.046583366 | H34: =H39*$E$4/H$15 -> 0.036111137 | I34: =I39*$E$4/I$15 -> 0.027993129 | J34: =J39*$E$4/J$15 -> 0.0217001 | K34: =K39*$E$4/K$15 -> 0.016821783 | L34: =L39*$E$4/L$15 -> 0.013040142 | ... N34: =N39*$E$4/N$15 -> 0.0078361528
D35: Total Annual Average % | I35: =AVERAGE(E34:I34) -> 0.049659911 | N35: =AVERAGE(E34:N34) -> 0.031780637
D36: Cumulative % | E36: =E$17*(E34/E$19) -> 0.07751938 | F36: =F$17*(F34/F$19) -> 0.13761192 | G36: =G$17*(G34/G$19) -> 0.18419529 | H36: =H$17*(H34/H$19) -> 0.22030643 | I36: =I$17*(I34/I$19) -> 0.24829955 | J36: =J$17*(J34/J$19) -> 0.26999965 | K36: =K$17*(K34/K$19) -> 0.28682144 | L36: =L$17*(L34/L$19) -> 0.29986158 | ... N36: =N$17*(N34/N$19) -> 0.31780637
D37: Test Case Annual | E37: =10*E34 -> 0.7751938 | F37: =10*F34 -> 0.60092543 | G37: =10*G34 -> 0.46583366 | H37: =10*H34 -> 0.36111137 | I37: =10*I34 -> 0.27993129 | J37: =10*J34 -> 0.217001 | K37: =10*K34 -> 0.16821783 | L37: =10*L34 -> 0.13040142 | ... N37: =10*N34 -> 0.078361528
D38: Test Case Cumulative | E38: =10*E36 -> 0.7751938 | F38: =10*F36 -> 1.3761192 | G38: =10*G36 -> 1.8419529 | H38: =10*H36 -> 2.2030643 | I38: =10*I36 -> 2.4829955 | J38: =10*J36 -> 2.6999965 | K38: =10*K36 -> 2.8682144 | L38: =10*L36 -> 2.9986158 | ... N38: =10*N36 -> 3.1780637
C39: USD Simple | D39: Annual % | E39: =E8 -> 0.1 | F39: =E39 -> 0.1 | G39: =F39 -> 0.1 | H39: =G39 -> 0.1 | I39: =H39 -> 0.1 | J39: =I39 -> 0.1 | K39: =J39 -> 0.1 | L39: =K39 -> 0.1 | M39: =L39 -> 0.1 | N39: =M39 -> 0.1
D40: Test Case Annual | E40: =E37*E$15 -> 100000 | F40: =F37*F$15 -> 100000 | G40: =G37*G$15 -> 100000 | H40: =H37*H$15 -> 100000 | I40: =I37*I$15 -> 100000 | J40: =J37*J$15 -> 100000 | K40: =K37*K$15 -> 100000 | L40: =L37*L$15 -> 100000 | ... N40: =N37*N$15 -> 100000
D41: Test Case Cumulative | E41: =E40 -> 100000 | F41: =E41+F40 -> 200000 | G41: =F41+G40 -> 300000 | H41: =G41+H40 -> 400000 | I41: =H41+I40 -> 500000 | J41: =I41+J40 -> 600000 | K41: =J41+K40 -> 700000 | L41: =K41+L40 -> 800000 | M41: =L41+M40 -> 900000 | N41: =M41+N40 -> 1000000
C42: USD Compounded | D42: Annual % | E42: =E36*E$15/$E$4 -> 0.1 | F42: =F36*F$15/$E$4-E42 -> 0.129 | G42: =G36*G$15/$E$4-F42-E42 -> 0.16641 | H42: =H36*H$15/$E$4-G42-F42-E42 -> 0.2146689 | I42: =I36*I$15/$E$4-H42-G42-F42-E42 -> 0.27692288 | J42: =J36*J$15/$E$4-I42-H42-G42-F42-E42 -> 0.35723052 | K42: =K36*K$15/$E$4-J42-I42-H42-G42-F42-E42 -> 0.46082737 | L42: =L36*L$15/$E$4-K42-J42-I42-H42-G42-F42-E42 -> 0.5944673 | M42: =M36*M$15/$E$4-L42-K42-J42-I42-H42-G42-F42-E42 -> 0.76686282 | N42: =N36*N$15/$E$4-M42-L42-K42-J42-I42-H42-G42-F42-E42 -> 0.98925304
D43: Annual Average % | I43: =AVERAGE(E42:I42) -> 0.17740036 | N43: =AVERAGE(E42:N42) -> 0.40556428
D44: Test Case Annual | E44: =E46 -> 100000 | F44: =F46-E46 -> 129000 | G44: =G46-F46 -> 166410 | H44: =H46-G46 -> 214668.9 | I44: =I46-H46 -> 276922.88 | J44: =J46-I46 -> 357230.52 | K44: =K46-J46 -> 460827.37 | L44: =L46-K46 -> 594467.3 | M44: =M46-L46 -> 766862.82 | N44: =N46-M46 -> 989253.04
D45: Test Case Annual Average | I45: =AVERAGE(E44:I44) -> 177400.36 | N45: =AVERAGE(E44:N44) -> 405564.28
D46: Test Case Cumulative | E46: =E38*E$15 -> 100000 | F46: =F38*F$15 -> 229000 | G46: =G38*G$15 -> 395410 | H46: =H38*H$15 -> 610078.9 | I46: =I38*I$15 -> 887001.78 | J46: =J38*J$15 -> 1244232.3 | K46: =K38*K$15 -> 1705059.7 | L46: =L38*L$15 -> 2299527 | ... N46: =N38*N$15 -> 4055642.8
B48: Stable Balancer / Lightning Service Provider | C48: Test Case | D48: ="10 BTC / "&TEXT($E$4*10, "$###0.00,,")&"M USD" -> 10 BTC / $1.00M USD | E48: Year 1 | F48: Year 2 | G48: Year 3 | H48: Year 4 | I48: Year 5 | J48: Year 6 | K48: Year 7 | L48: Year 8 | M48: Year 9 | N48: Year 10
B50: Bitcoin Liquidity Yield (BiLY) | C50: BTC | D50: Annual % | E50: =E55*$E$4/E$15 -> 0.18410853 | F50: =F55*$E$4/F$15 -> 0.14271979 | G50: =G55*$E$4/G$15 -> 0.11063549 | H50: =H55*$E$4/H$15 -> 0.08576395 | I50: =I55*$E$4/I$15 -> 0.066483682 | J50: =J55*$E$4/J$15 -> 0.051537738 | K50: =K55*$E$4/K$15 -> 0.039951735 | L50: =L55*$E$4/L$15 -> 0.030970337 | ... N50: =N55*$E$4/N$15 -> 0.018610863
D51: Annual Average % | I51: =AVERAGE(E50:I50) -> 0.11794229 | N51: =AVERAGE(E50:N50) -> 0.075479013
D52: Cumulative % | E52: =E$17*(E50/E$19) -> 0.18410853 | F52: =F$17*(F50/F$19) -> 0.32682832 | G52: =G$17*(G50/G$19) -> 0.43746381 | H52: =H$17*(H50/H$19) -> 0.52322776 | I52: =I$17*(I50/I$19) -> 0.58971144 | J52: =J$17*(J50/J$19) -> 0.64124918 | K52: =K$17*(K50/K$19) -> 0.68120091 | L52: =L$17*(L50/L$19) -> 0.71217125 | ... N52: =N$17*(N50/N$19) -> 0.75479013
D53: Test Case Annual | E53: =10*E50 -> 1.8410853 | F53: =10*F50 -> 1.4271979 | G53: =10*G50 -> 1.1063549 | H53: =10*H50 -> 0.8576395 | I53: =10*I50 -> 0.66483682 | J53: =10*J50 -> 0.51537738 | K53: =10*K50 -> 0.39951735 | L53: =10*L50 -> 0.30970337 | ... N53: =10*N50 -> 0.18610863
D54: Test Case Cumulative | E54: =10*E52 -> 1.8410853 | F54: =10*F52 -> 3.2682832 | G54: =10*G52 -> 4.3746381 | H54: =10*H52 -> 5.2322776 | I54: =10*I52 -> 5.8971144 | J54: =10*J52 -> 6.4124918 | K54: =10*K52 -> 6.8120091 | L54: =10*L52 -> 7.1217125 | ... N54: =10*N52 -> 7.5479013
C55: USD Simple | D55: Annual % | E55: =$E9+($E$10*$E$11) -> 0.2375 | F55: =$E9+($E$10*$E$11) -> 0.2375 | G55: =$E9+($E$10*$E$11) -> 0.2375 | H55: =$E9+($E$10*$E$11) -> 0.2375 | I55: =$E9+($E$10*$E$11) -> 0.2375 | J55: =$E9+($E$10*$E$11) -> 0.2375 | K55: =$E9+($E$10*$E$11) -> 0.2375 | L55: =$E9+($E$10*$E$11) -> 0.2375 | ... N55: =$E9+($E$10*$E$11) -> 0.2375
D56: Test Case Annual | E56: =E53*E$15 -> 237500 | F56: =F53*F$15 -> 237500 | G56: =G53*G$15 -> 237500 | H56: =H53*H$15 -> 237500 | I56: =I53*I$15 -> 237500 | J56: =J53*J$15 -> 237500 | K56: =K53*K$15 -> 237500 | L56: =L53*L$15 -> 237500 | ... N56: =N53*N$15 -> 237500
D57: Test Case Cumulative | E57: =E56 -> 237500 | F57: =E57+F56 -> 475000 | G57: =F57+G56 -> 712500 | H57: =G57+H56 -> 950000 | I57: =H57+I56 -> 1187500 | J57: =I57+J56 -> 1425000 | K57: =J57+K56 -> 1662500 | L57: =K57+L56 -> 1900000 | M57: =L57+M56 -> 2137500 | N57: =M57+N56 -> 2375000
C58: USD Compounded | D58: Annual % | E58: =E52*E$15/$E$4 -> 0.2375 | F58: =F52*F$15/$E$4-E58 -> 0.306375 | G58: =G52*G$15/$E$4-F58-E58 -> 0.39522375 | H58: =H52*H$15/$E$4-G58-F58-E58 -> 0.50983864 | I58: =I52*I$15/$E$4-H58-G58-F58-E58 -> 0.65769184 | J58: =J52*J$15/$E$4-I58-H58-G58-F58-E58 -> 0.84842248 | K58: =K52*K$15/$E$4-J58-I58-H58-G58-F58-E58 -> 1.094465 | L58: =L52*L$15/$E$4-K58-J58-I58-H58-G58-F58-E58 -> 1.4118598 | M58: =M52*M$15/$E$4-L58-K58-J58-I58-H58-G58-F58-E58 -> 1.8212992 | N58: =N52*N$15/$E$4-M58-L58-K58-J58-I58-H58-G58-F58-E58 -> 2.349476
D59: Annual Average % | I59: =AVERAGE(E58:I58) -> 0.42132585 | N59: =AVERAGE(E58:N58) -> 0.96321517
D60: Test Case Annual | E60: =E62 -> 237500 | F60: =F62-E62 -> 306375 | G60: =G62-F62 -> 395223.75 | H60: =H62-G62 -> 509838.64 | I60: =I62-H62 -> 657691.84 | J60: =J62-I62 -> 848422.48 | K60: =K62-J62 -> 1094465 | L60: =L62-K62 -> 1411859.8 | M60: =M62-L62 -> 1821299.2 | N60: =N62-M62 -> 2349476
D61: Test Case Annual Average | I61: =AVERAGE(E60:I60) -> 421325.85 | N61: =AVERAGE(E60:N60) -> 963215.17
D62: Test Case Cumulative | E62: =E54*E$15 -> 237500 | F62: =F54*F$15 -> 543875 | G62: =G54*G$15 -> 939098.75 | H62: =H54*H$15 -> 1448937.4 | I62: =I54*I$15 -> 2106629.2 | J62: =J54*J$15 -> 2955051.7 | K62: =K54*K$15 -> 4049516.7 | L62: =L54*L$15 -> 5461376.5 | ... N62: =N54*N$15 -> 9632151.7
B64: Stable Provider / Bitcoin Borrower | C64: Test Case | D64: ="10 BTC / "&TEXT($E$4*10, "$###0.00,,")&"M USD" -> 10 BTC / $1.00M USD | E64: Year 1 | F64: Year 2 | G64: Year 3 | H64: Year 4 | I64: Year 5 | J64: Year 6 | K64: Year 7 | L64: Year 8 | M64: Year 9 | N64: Year 10
B66: Bitcoin Growth Yield (BiGY) | C66: BTC | D66: Total Annual % | E66: =E$23 -> 0.78682171 | F66: =F$23 -> 0.60993931 | G66: =G$23 -> 0.47282117 | H66: =H$23 -> 0.36652804 | I66: =I$23 -> 0.28413026 | J66: =J$23 -> 0.22025602 | K66: =K$23 -> 0.1707411 | L66: =L$23 -> 0.13235744 | ... N66: =N$23 -> 0.079536951
D67: Total Annual Average % | I67: =AVERAGE(E66:I66) -> 0.5040481 | N67: =AVERAGE(E66:N66) -> 0.32257347
D68: Cumulative % | E68: =E$17*(E66/E$19) -> 0.78682171 | F68: =F$17*(F66/F$19) -> 1.396761 | G68: =G$17*(G66/G$19) -> 1.8695822 | H68: =H$17*(H66/H$19) -> 2.2361102 | I68: =I$17*(I66/I$19) -> 2.5202405 | J68: =J$17*(J66/J$19) -> 2.7404965 | K68: =K$17*(K66/K$19) -> 2.9112376 | L68: =L$17*(L66/L$19) -> 3.043595 | ... N68: =N$17*(N66/N$19) -> 3.2257347
D69: Test Case Annual | E69: =10*E66 -> 7.8682171 | F69: =10*F66 -> 6.0993931 | G69: =10*G66 -> 4.7282117 | H69: =10*H66 -> 3.6652804 | I69: =10*I66 -> 2.8413026 | J69: =10*J66 -> 2.2025602 | K69: =10*K66 -> 1.707411 | L69: =10*L66 -> 1.3235744 | ... N69: =10*N66 -> 0.79536951
D70: Test Case Cumulative | E70: =10*E68 -> 7.8682171 | F70: =10*F68 -> 13.96761 | G70: =10*G68 -> 18.695822 | H70: =10*H68 -> 22.361102 | I70: =10*I68 -> 25.202405 | J70: =10*J68 -> 27.404965 | K70: =10*K68 -> 29.112376 | L70: =10*L68 -> 30.43595 | ... N70: =10*N68 -> 32.257347
C71: USD Simple | D71: Annual % | E71: =E66*E$15/$E$4 -> 1.015 | F71: =F66*F$15/$E$4 -> 1.015 | G71: =G66*G$15/$E$4 -> 1.015 | H71: =H66*H$15/$E$4 -> 1.015 | I71: =I66*I$15/$E$4 -> 1.015 | J71: =J66*J$15/$E$4 -> 1.015 | K71: =K66*K$15/$E$4 -> 1.015 | L71: =L66*L$15/$E$4 -> 1.015 | ... N71: =N66*N$15/$E$4 -> 1.015
D72: Test Case Annual | E72: =E69*E$15 -> 1015000 | F72: =F69*F$15 -> 1015000 | G72: =G69*G$15 -> 1015000 | H72: =H69*H$15 -> 1015000 | I72: =I69*I$15 -> 1015000 | J72: =J69*J$15 -> 1015000 | K72: =K69*K$15 -> 1015000 | L72: =L69*L$15 -> 1015000 | ... N72: =N69*N$15 -> 1015000
D73: Test Case Cumulative | E73: =E72 -> 1015000 | F73: =E73+F72 -> 2030000 | G73: =F73+G72 -> 3045000 | H73: =G73+H72 -> 4060000 | I73: =H73+I72 -> 5075000 | J73: =I73+J72 -> 6090000 | K73: =J73+K72 -> 7105000 | L73: =K73+L72 -> 8120000 | M73: =L73+M72 -> 9135000 | N73: =M73+N72 -> 10150000
C74: USD Compounded | D74: Annual % | E74: =E68*E$15/$E$4 -> 1.015 | F74: =F68*F$15/$E$4-E74 -> 1.30935 | G74: =G68*G$15/$E$4-F74-E74 -> 1.6890615 | H74: =H68*H$15/$E$4-G74-F74-E74 -> 2.1788893 | I74: =I68*I$15/$E$4-H74-G74-F74-E74 -> 2.8107672 | J74: =J68*J$15/$E$4-I74-H74-G74-F74-E74 -> 3.6258897 | K74: =K68*K$15/$E$4-J74-I74-H74-G74-F74-E74 -> 4.6773978 | L74: =L68*L$15/$E$4-K74-J74-I74-H74-G74-F74-E74 -> 6.0338431 | M74: =M68*M$15/$E$4-L74-K74-J74-I74-H74-G74-F74-E74 -> 7.7836576 | N74: =N68*N$15/$E$4-M74-L74-K74-J74-I74-H74-G74-F74-E74 -> 10.040918
